Workbook

Sheet LEIA-ME
A1: Municípios do Brasil — IBGE
A2: Gerado em | B2: 29/10/2026 16:14 por build_municipios_ibge.py (pipeline reprodutível; fontes e hashes na aba Fontes).
A3: Cobertura | B3: 5.571 municípios (DTB 2025, que inclui Brasília/DF e o Distrito Estadual de Fernando de Noronha/PE, codificado pelo IBGE como município) · 10.751 distritos · 510 Regiões Geográficas Imediatas · 133 Intermediárias · 27 UFs.
A5: ABAS
A6: Municipios | B6: 1 linha por município: códigos, UF, regiões imediata e intermediária, coordenada da sede (com fonte, status e observação), distritos, centroide e ponto interno do polígono.
A7: Distritos | B7: 1 linha por distrito (tabela plana): distrito + município + UF + regiões + coordenada do município e da sede distrital.
A8: Regioes_Imediatas / Regioes_Intermediarias / UFs | B8: Dimensões para modelo estrela (Power BI).
A9: Resumo_UF | B9: Contagens por UF com fórmulas vivas (COUNTIF/COUNTIFS/SUM).
A10: Auditoria_Coordenadas | B10: 130 municípios: 112 com divergência > 5 km entre fontes, 14 com o ponto 2022 a ≥ 3 km das duas referências e os demais por status ≠ OK, precisão de minuto, sede na borda do limite, sede junto à de outro distrito ou curadoria — com os valores de cada fonte e a decisão.
A11: Validacao | B11: 61 checagens automáticas do pipeline + 11 checagens com fórmula viva.
A12: Fontes | B12: Produto IBGE, safra, origem do arquivo, endereço oficial e SHA-256 de cada insumo.
A14: COORDENADAS — O QUE SIGNIFICAM
A15: Latitude / Longitude | B15: Ponto oficial da SEDE MUNICIPAL (área urbana da sede) do IBGE — Localidades do Brasil 2022 (categoria 'Cidade' / 'Sede Municipal'). Graus decimais, datum SIRGAS 2000 (EPSG:4674). Município é uma área; este é o ponto de referência oficial da cidade-sede, padrão para mapas de pontos, distâncias e geocodificação. Não é necessariamente a prefeitura nem o marco zero.
A16: Precisão | B16: O IBGE publica os atributos de 2022 com 4 casas decimais (≈ 11 m). Os pontos IBGE 2010 têm precisão total (gravados com 6 casas, ≈ 0,1 m).
A17: Regra de correção | B17: O ponto IBGE 2022 é substituído pelo IBGE 2010 quando diverge > 5 km (> 10 km nas capitais, de área urbana extensa) de DUAS fontes independentes ao mesmo tempo (IBGE 2010 e a base comunitária kelvins). A observação registra a evidência: o ponto 2022 coincide com outra localidade (povoado, vila) ou está isolado. Também usa o 2010 quando o ponto 2022 foi arredondado ao minuto de arco. Resultado: 15 municípios corrigidos (ex.: Manicoré/AM, cujo ponto 2022 estava 237 km deslocado), dos quais 2 ainda 'a conferir' (Porto Velho, Boca do Acre). Além disso, União da Serra/RS manteve o ponto 2022 e está marcado 'a conferir'. 14 pontos 2022 mantidos a ≥ 3 km das duas referências (que concordam entre si) estão anotados na observação.
A18: Curadoria | B18: 8 municípios têm nota de curadoria documentada (status e/ou referência externa, com a distância calculada pelo pipeline); a coordenada continua sendo um ponto oficial do IBGE. Inclui as capitais: Porto Velho, São Paulo.
A19: Validação geométrica | B19: Todas as sedes foram testadas contra o polígono do próprio município (Malha Municipal IBGE 2025). 'Na borda' = até 1 km fora, efeito da simplificação da malha.
A20: Centroide x Ponto Interno | B20: Centroide = centro de massa do polígono (pode cair fora em municípios côncavos; ilhas oceânicas a > 50 km ficam de fora, ex.: Trindade/Martim Vaz em Vitória). Ponto interno = polo de inacessibilidade, sempre dentro. Entre si diferem em mediana 2,8 km (p25 1,4; p75 5,6); a sede fica em mediana a 5,5 km do centroide.
A21: Grandes cidades | B21: Em metrópoles o ponto IBGE da sede é um ponto representativo da área urbana e pode ficar a alguns km do centro histórico (ex.: em São Paulo o ponto fica a 5,6 km da Praça da Sé). Para análises intramunicipais, use distritos ou setores censitários.
A23: DISTRITOS
A24: Distrito-sede | B24: Convenção do IBGE: o distrito-sede recebe o sufixo 05 — validado: 5.564 das 5.565 sedes IBGE 2010 estão no distrito 05; a exceção é São Paulo/SP, com 96 distritos numerados 01–96 sem sede codificada ('Não se aplica'). Em 2 municípios o distrito-sede tem nome diferente do município (renomeações): São Vicente do Seridó/PB (sede 'Seridó'), União da Serra/RS (sede 'São Luiz').
A25: Coordenada do distrito | B25: Distrito-sede = sede municipal. Demais distritos, nesta ordem: ponto 'Vila' (sede distrital) do IBGE Localidades 2022 (GO, SC, AM, AP, PA, RR) → 'Vila' do IBGE 2010 → localidade IBGE homônima e única no município (povoado, núcleo etc.). Cada ponto só é aceito se cair dentro do próprio município. Isso reprovou 2 pontos — p.ex. a Vila 2022 de Marcílio Dias (-2,1355; -50,3903), que caía fora do município. Cobertura: 10.256 de 10.751 distritos (95,4%). Sem coordenada: 380: distrito criado após 2010 (sem ponto IBGE 2022 nos arquivos disponíveis, que cobrem só GO, SC, AM, AP, PA e RR) · 95: distrito urbano: o IBGE não publica ponto de sede para estes distritos · 13: distrito já existia em 2010, mas sem ponto 'Vila' no cadastro IBGE 2010 · 6: sem ponto 'Vila' no IBGE Localidades 2022 · 1: ponto disponível reprovado no teste de limite municipal. O motivo está na coluna Observação de cada linha.
A27: NOMES OFICIAIS
A28: Correção de codificação | B28: O IBGE publica 9 regiões (8 nomes distintos) com o caractere U+00BF (ponto de interrogação invertido) no lugar do travessão — defeito replicado pela API. Normalizados para ' - ': 'Belo Jardim [U+00BF] Pesqueira' → 'Belo Jardim - Pesqueira'; 'Goiana [U+00BF] Timbaúba' → 'Goiana - Timbaúba'; 'Pão de Açúcar - Olho d'Água das Flores [U+00BF] Batalha' → 'Pão de Açúcar - Olho d'Água das Flores - Batalha'; 'Ilhéus [U+00BF] Itabuna' → 'Ilhéus - Itabuna'; 'Nazaré [U+00BF] Maragogipe' → 'Nazaré - Maragogipe'; 'Xique-Xique [U+00BF] Barra' → 'Xique-Xique - Barra'; 'São Joaquim da Barra [U+00BF] Orlândia' → 'São Joaquim da Barra - Orlândia'; 'Cornélio Procópio [U+00BF] Bandeirantes' → 'Cornélio Procópio - Bandeirantes'.
A29: Grafias das regiões | B29: Os nomes das regiões seguem a grafia oficial da DTB, que às vezes difere da grafia atual do município homônimo (ex.: 'Juíz de Fora', 'Açu', 'Itapagé'). Relacione sempre por código.
A30: Dígito verificador | B30: 9 códigos oficiais não satisfazem o algoritmo do DV (2201919, 2201988, 2202251, 2611533, 3117836, 3152131, 4305871, 5203939, 5203962). São válidos.
A32: USO E ATUALIZAÇÃO
A33: Power BI — modelo | B33: Importe tbl_Municipios, tbl_Distritos, tbl_Regioes_Imediatas, tbl_Regioes_Intermediarias e tbl_UFs e desligue a detecção automática de relacionamentos. Relacione (N:1): Distritos[Código IBGE] → Municipios[Código IBGE]; Municipios[Código Região Imediata] → Regioes_Imediatas; Regioes_Imediatas[Código Região Intermediária] → Regioes_Intermediarias; Regioes_Intermediarias[Código UF] → UFs. Marque Latitude/Longitude com a categoria de dados correspondente, colunas de código como 'Não resumir' e use 'Município - UF' em filtros e rótulos (há nomes repetidos).
A34: Como atualizar | B34: Baixe as novas edições oficiais do IBGE (DTB, Localidades, Malha Municipal — endereços na aba Fontes), substitua os arquivos no diretório de fontes e rode: python build_municipios_ibge.py --fontes <dir> --saida <dir>. Se qualquer validação crítica falhar, o resultado vai para Municipios_Brasil_IBGE_FALHOU.xlsx (log em build_log_FALHOU.txt) e o arquivo anterior não é sobrescrito. Para pandas, leia a aba Resumo_UF com nrows=27 (a linha de total fica abaixo da tabela).

Sheet Municipios
A1: Código IBGE | B1: Código IBGE (6 dígitos) | C1: Município | D1: Município - UF | E1: UF | F1: Código UF | G1: Estado | H1: Região | I1: Código Região Intermediária | J1: Região Geográfica Intermediária | K1: Código Região Imediata | L1: Região Geográfica Imediata | M1: Latitude | N1: Longitude | O1: Fonte da Coordenada | P1: Status da Coordenada | Q1: Capital (Sim/Não) | R1: Qtd. Distritos | S1: Código Distrito-Sede | T1: Nome do Distrito-Sede | U1: Distritos | V1: Sede dentro do Limite Municipal | W1: Observação da Coordenada | X1: Latitude Centroide | Y1: Longitude Centroide | Z1: Centroide dentro do Município | AA1: Latitude Ponto Interno | AB1: Longitude Ponto Interno
A2: 1100015 | B2: 110001 | C2: Alta Floresta D'Oeste | D2: Alta Floresta D'Oeste - RO | E2: RO | F2: 11 | G2: Rondônia | H2: Norte | I2: 1102 | J2: Ji-Paraná | K2: 110005 | L2: Cacoal | M2: -11.933 | N2: -62.0037 | O2: IBGE Localidades 2022 (Sede Municipal) | P2: OK | Q2: Não | R2: 6 | S2: 110001505 | T2: Alta Floresta D'Oeste | U2: Alta Floresta D'Oeste; Filadélfia d'Oeste; Izidolândia; Nova Gease d'Oeste; Rolim de Moura do Guaporé; Santo Antônio d'Oeste | V2: Sim | X2: -12.469748 | Y2: -62.274475 | Z2: Não | AA2: -12.119936 | AB2: -62.222413
A3: 1100023 | B3: 110002 | C3: Ariquemes | D3: Ariquemes - RO | E3: RO | F3: 11 | G3: Rondônia | H3: Norte | I3: 1101 | J3: Porto Velho | K3: 110002 | L3: Ariquemes | M3: -9.912 | N3: -63.0338 | O3: IBGE Localidades 2022 (Sede Municipal) | P3: OK | Q3: Não | R3: 1 | S3: 110002305 | T3: Ariquemes | U3: Ariquemes | V3: Sim | X3: -9.951978 | Y3: -62.957227 | Z3: Sim | AA3: -9.966212 | AB3: -62.911906
A4: 1100031 | B4: 110003 | C4: Cabixi | D4: Cabixi - RO | E4: RO | F4: 11 | G4: Rondônia | H4: Norte | I4: 1102 | J4: Ji-Paraná | K4: 110006 | L4: Vilhena | M4: -13.4945 | N4: -60.5429 | O4: IBGE Localidades 2022 (Sede Municipal) | P4: OK | Q4: Não | R4: 1 | S4: 110003105 | T4: Cabixi | U4: Cabixi | V4: Sim | X4: -13.474933 | Y4: -60.639811 | Z4: Sim | AA4: -13.436056 | AB4: -60.611615
A5: 1100049 | B5: 110004 | C5: Cacoal | D5: Cacoal - RO | E5: RO | F5: 11 | G5: Rondônia | H5: Norte | I5: 1102 | J5: Ji-Paraná | K5: 110005 | L5: Cacoal | M5: -11.4356 | N5: -61.4512 | O5: IBGE Localidades 2022 (Sede Municipal) | P5: OK | Q5: Não | R5: 3 | S5: 110004905 | T5: Cacoal | U5: Cacoal; Riozinho; Divinópolis | V5: Sim | X5: -11.301275 | Y5: -61.324642 | Z5: Sim | AA5: -11.261263 | AB5: -61.240318
A6: 1100056 | B6: 110005 | C6: Cerejeiras | D6: Cerejeiras - RO | E6: RO | F6: 11 | G6: Rondônia | H6: Norte | I6: 1102 | J6: Ji-Paraná | K6: 110006 | L6: Vilhena | M6: -13.1864 | N6: -60.8117 | O6: IBGE Localidades 2022 (Sede Municipal) | P6: OK | Q6: Não | R6: 1 | S6: 110005605 | T6: Cerejeiras | U6: Cerejeiras | V6: Sim | X6: -13.203677 | Y6: -61.260923 | Z6: Sim | AA6: -13.232552 | AB6: -61.226979
A7: 1100064 | B7: 110006 | C7: Colorado do Oeste | D7: Colorado do Oeste - RO | E7: RO | F7: 11 | G7: Rondônia | H7: Norte | I7: 1102 | J7: Ji-Paraná | K7: 110006 | L7: Vilhena | M7: -13.1212 | N7: -60.5437 | O7: IBGE Localidades 2022 (Sede Municipal) | P7: OK | Q7: Não | R7: 1 | S7: 110006405 | T7: Colorado do Oeste | U7: Colorado do Oeste | V7: Sim | X7: -13.159152 | Y7: -60.550244 | Z7: Sim | AA7: -13.155651 | AB7: -60.556034
A8: 1100072 | B8: 110007 | C8: Corumbiara | D8: Corumbiara - RO | E8: RO | F8: 11 | G8: Rondônia | H8: Norte | I8: 1102 | J8: Ji-Paraná | K8: 110006 | L8: Vilhena | M8: -12.99752 | N8: -60.948701 | O8: IBGE Localidades 2010 (Cidade) | P8: Corrigida | Q8: Não | R8: 1 | S8: 110007205 | T8: Corumbiara | U8: Corumbiara | V8: Sim | W8: Ponto IBGE 2022 (-13,0092; -61,1279) divergia 19,5 km do IBGE 2010 e 26,0 km da base independente; substituído pelo IBGE 2010. O ponto 2022 coincide com Povoado 'Vitória da União' (IBGE 2010, a 0,29 km). IBGE 2010 x base independente: 7,5 km. A base independente aponta para o Povoado Alto Guarajus; o ponto IBGE 2010 é a área urbana (CIDADE) da sede. | X8: -12.92671 | Y8: -61.091629 | Z8: Sim | AA8: -12.942427 | AB8: -61.138893
A9: 1100080 | B9: 110008 | C9: Costa Marques | D9: Costa Marques - RO | E9: RO | F9: 11 | G9: Rondônia | H9: Norte | I9: 1102 | J9: Ji-Paraná | K9: 110004 | L9: Ji-Paraná | M9: -12.4384 | N9: -64.2292 | O9: IBGE Localidades 2022 (Sede Municipal) | P9: OK | Q9: Não | R9: 3 | S9: 110008005 | T9: Costa Marques | U9: Costa Marques; Real Forte Príncipe da Beira; São Domingos do Guaporé | V9: Sim | X9: -12.147029 | Y9: -64.05865 | Z9: Sim | AA9: -12.264719 | AB9: -64.266169
A10: 1100098 | B10: 110009 | C10: Espigão D'Oeste | D10: Espigão D'Oeste - RO | E10: RO | F10: 11 | G10: Rondônia | H10: Norte | I10: 1102 | J10: Ji-Paraná | K10: 110005 | L10: Cacoal | M10: -11.5347 | N10: -61.0164 | O10: IBGE Localidades 2022 (Sede Municipal) | P10: OK | Q10: Não | R10: 5 | S10: 110009805 | T10: Espigão D'Oeste | U10: Espigão D'Oeste; Boa Vista do Pacarana; Novo Paraíso; Flor da Serra; Nova Esperança | V10: Sim | X10: -11.35125 | Y10: -60.784792 | Z10: Sim | AA10: -11.380248 | AB10: -60.747569
A11: 1100106 | B11: 110010 | C11: Guajará-Mirim | D11: Guajará-Mirim - RO | E11: RO | F11: 11 | G11: Rondônia | H11: Norte | I11: 1101 | J11: Porto Velho | K11: 110001 | L11: Porto Velho | M11: -10.7871 | N11: -65.3401 | O11: IBGE Localidades 2022 (Sede Municipal) | P11: OK | Q11: Não | R11: 3 | S11: 110010605 | T11: Guajará-Mirim | U11: Guajará-Mirim; Iata; Surpresa | V11: Sim | X11: -11.305446 | Y11: -64.537754 | Z11: Sim | AA11: -11.4145 | AB11: -64.568417
A12: 1100114 | B12: 110011 | C12: Jaru | D12: Jaru - RO | E12: RO | F12: 11 | G12: Rondônia | H12: Norte | I12: 1101 | J12: Porto Velho | K12: 110003 | L12: Jaru | M12: -10.4382 | N12: -62.4616 | O12: IBGE Localidades 2022 (Sede Municipal) | P12: OK | Q12: Não | R12: 4 | S12: 110011405 | T12: Jaru | U12: Jaru; Bom Jesus; Santa Cruz da Serra; Tarilândia | V12: Sim | X12: -10.592342 | Y12: -62.58456 | Z12: Sim | AA12: -10.447166 | AB12: -62.436084
A13: 1100122 | B13: 110012 | C13: Ji-Paraná | D13: Ji-Paraná - RO | E13: RO | F13: 11 | G13: Rondônia | H13: Norte | I13: 1102 | J13: Ji-Paraná | K13: 110004 | L13: Ji-Paraná | M13: -10.8768 | N13: -61.9575 | O13: IBGE Localidades 2022 (Sede Municipal) | P13: OK | Q13: Não | R13: 3 | S13: 110012205 | T13: Ji-Paraná | U13: Ji-Paraná; Nova Colina; Nova Londrina | V13: Sim | X13: -10.461772 | Y13: -61.757131 | Z13: Sim | AA13: -10.726052 | AB13: -61.766934
A14: 1100130 | B14: 110013 | C14: Machadinho D'Oeste | D14: Machadinho D'Oeste - RO | E14: RO | F14: 11 | G14: Rondônia | H14: Norte | I14: 1101 | J14: Porto Velho | K14: 110003 | L14: Jaru | M14: -9.425562 | N14: -61.999593 | O14: IBGE Localidades 2010 (Cidade) | P14: Corrigida | Q14: Não | R14: 4 | S14: 110013005 | T14: Machadinho D'Oeste | U14: Machadinho D'Oeste; Oriente Novo; Quinto BEC; Tabajara | V14: Sim | W14: Ponto IBGE 2022 (-9,4657; -62,2562) divergia 28,5 km do IBGE 2010 e 30,2 km da base independente; substituído pelo IBGE 2010. O ponto 2022 está isolado (localidade IBGE 2010 mais próxima a 20,5 km). | X14: -9.203934 | Y14: -62.010232 | Z14: Sim | AA14: -9.205744 | AB14: -61.98143
A15: 1100148 | B15: 110014 | C15: Nova Brasilândia D'Oeste | D15: Nova Brasilândia D'Oeste - RO | E15: RO | F15: 11 | G15: Rondônia | H15: Norte | I15: 1102 | J15: Ji-Paraná | K15: 110005 | L15: Cacoal | M15: -11.7198 | N15: -62.3177 | O15: IBGE Localidades 2022 (Sede Municipal) | P15: OK | Q15: Não | R15: 1 | S15: 110014805 | T15: Nova Brasilândia D'Oeste | U15: Nova Brasilândia D'Oeste | V15: Sim | X15: -11.643028 | Y15: -62.280126 | Z15: Sim | AA15: -11.761104 | AB15: -62.342469
A16: 1100155 | B16: 110015 | C16: Ouro Preto do Oeste | D16: Ouro Preto do Oeste - RO | E16: RO | F16: 11 | G16: Rondônia | H16: Norte | I16: 1102 | J16: Ji-Paraná | K16: 110004 | L16: Ji-Paraná | M16: -10.7192 | N16: -62.2555 | O16: IBGE Localidades 2022 (Sede Municipal) | P16: OK | Q16: Não | R16: 2 | S16: 110015505 | T16: Ouro Preto do Oeste | U16: Ouro Preto do Oeste; Rondominas | V16: Sim | X16: -10.610499 | Y16: -62.172411 | Z16: Não | AA16: -10.708894 | AB16: -62.328823
A17: 1100189 | B17: 110018 | C17: Pimenta Bueno | D17: Pimenta Bueno - RO | E17: RO | F17: 11 | G17: Rondônia | H17: Norte | I17: 1102 | J17: Ji-Paraná | K17: 110005 | L17: Cacoal | M17: -11.6707 | N17: -61.1888 | O17: IBGE Localidades 2022 (Sede Municipal) | P17: OK | Q17: Não | R17: 3 | S17: 110018905 | T17: Pimenta Bueno | U17: Pimenta Bueno; Marco Rondon; Itaporanga | V17: Sim | X17: -11.894501 | Y17: -60.830539 | Z17: Sim | AA17: -11.93472 | AB17: -60.651141
A18: 1100205 | B18: 110020 | C18: Porto Velho | D18: Porto Velho - RO | E18: RO | F18: 11 | G18: Rondônia | H18: Norte | I18: 1101 | J18: Porto Velho | K18: 110001 | L18: Porto Velho | M18: -8.768892 | N18: -63.831446 | O18: IBGE Localidades 2010 (Cidade) | P18: Corrigida - a conferir | Q18: Sim | R18: 12 | S18: 110020505 | T18: Porto Velho | U18: Porto Velho; Abunã; Calama; Demarcação; Extrema; Fortaleza do Abunã; Jaci Paraná; Mutum Paraná; Nazaré; Nova Califórnia; São Carlos; Vista Alegre do Abunã | V18: Sim | W18: Ponto IBGE 2022 (-9,6462; -63,9599) divergia 98,6 km do IBGE 2010 e 98,7 km da base independente; substituído pelo IBGE 2010. O ponto 2022 está isolado (localidade IBGE 2010 mais próxima a 63,5 km). IBGE 2010 x base independente: 7,6 km. O ponto IBGE 2010 fica na Zona Leste da cidade; para análises que exijam o centro, use a coordenada publicada pela Prefeitura. Referência externa — Prefeitura de Porto Velho (8°45'43"S 63°54'14"W, centro): (-8,7619; -63,9039), a 8,0 km do ponto adotado. | X18: -9.154117 | Y18: -64.304271 | Z18: Sim | AA18: -9.445094 | AB18: -64.53976
A19: 1100254 | B19: 110025 | C19: Presidente Médici | D19: Presidente Médici - RO | E19: RO | F19: 11 | G19: Rondônia | H19: Norte | I19: 1102 | J19: Ji-Paraná | K19: 110004 | L19: Ji-Paraná | M19: -11.1698 | N19: -61.9041 | O19: IBGE Localidades 2022 (Sede Municipal) | P19: OK | Q19: Não | R19: 5 | S19: 110025405 | T19: Presidente Médici | U19: Presidente Médici; Estrela de Rondônia; Novo Riachuelo; Vila Bandeira Branca; Vila Camargo | V19: Sim | X19: -11.166306 | Y19: -61.877867 | Z19: Sim | AA19: -11.171763 | AB19: -61.822196
A20: 1100262 | B20: 110026 | C20: Rio Crespo | D20: Rio Crespo - RO | E20: RO | F20: 11 | G20: Rondônia | H20: Norte | I20: 1101 | J20: Porto Velho | K20: 110002 | L20: Ariquemes | M20: -9.7054 | N20: -62.8983 | O20: IBGE Localidades 2022 (Sede Municipal) | P20: OK | Q20: Não | R20: 1 | S20: 110026205 | T20: Rio Crespo | U20: Rio Crespo | V20: Sim | X20: -9.645216 | Y20: -62.790059 | Z20: Sim | AA20: -9.663163 | AB20: -62.729992
A21: 1100288 | B21: 110028 | C21: Rolim de Moura | D21: Rolim de Moura - RO | E21: RO | F21: 11 | G21: Rondônia | H21: Norte | I21: 1102 | J21: Ji-Paraná | K21: 110005 | L21: Cacoal | M21: -11.722259 | N21: -61.785781 | O21: IBGE Localidades 2010 (Cidade) | P21: Corrigida | Q21: Não | R21: 2 | S21: 110028805 | T21: Rolim de Moura | U21: Rolim de Moura; Nova Estrela | V21: Sim | W21: Ponto IBGE 2022 (-11,7251; -61,5543) divergia 25,2 km do IBGE 2010 e 23,6 km da base independente; substituído pelo IBGE 2010. O ponto 2022 coincide com Povoado 'Nova Estrela' (IBGE 2010, a 0,80 km). | X21: -11.732597 | Y21: -61.771654 | Z21: Sim | AA21: -11.720485 | AB21: -61.707357
A22: 1100296 | B22: 110029 | C22: Santa Luzia D'Oeste | D22: Santa Luzia D'Oeste - RO | E22: RO | F22: 11 | G22: Rondônia | H22: Norte | I22: 1102 | J22: Ji-Paraná | K22: 110005 | L22: Cacoal | M22: -11.9079 | N22: -61.7846 | O22: IBGE Localidades 2022 (Sede Municipal) | P22: OK | Q22: Não | R22: 1 | S22: 110029605 | T22: Santa Luzia D'Oeste | U22: Santa Luzia D'Oeste | V22: Sim | X22: -12.026896 | Y22: -61.701119 | Z22: Sim | AA22: -11.97654 | AB22: -61.718828
A23: 1100304 | B23: 110030 | C23: Vilhena | D23: Vilhena - RO | E23: RO | F23: 11 | G23: Rondônia | H23: Norte | I23: 1102 | J23: Ji-Paraná | K23: 110006 | L23: Vilhena | M23: -12.7351 | N23: -60.1348 | O23: IBGE Localidades 2022 (Sede Municipal) | P23: OK | Q23: Não | R23: 1 | S23: 110030405 | T23: Vilhena | U23: Vilhena | V23: Sim | X23: -12.094901 | Y23: -60.248545 | Z23: Sim | AA23: -12.476569 | AB23: -60.218252
A24: 1100320 | B24: 110032 | C24: São Miguel do Guaporé | D24: São Miguel do Guaporé - RO | E24: RO | F24: 11 | G24: Rondônia | H24: Norte | I24: 1102 | J24: Ji-Paraná | K24: 110004 | L24: Ji-Paraná | M24: -11.689 | N24: -62.7152 | O24: IBGE Localidades 2022 (Sede Municipal) | P24: OK | Q24: Não | R24: 2 | S24: 110032005 | T24: São Miguel do Guaporé | U24: São Miguel do Guaporé; Santana do Guaporé | V24: Sim | X24: -11.612069 | Y24: -62.98815 | Z24: Não | AA24: -11.328409 | AB24: -63.33839
A25: 1100338 | B25: 110033 | C25: Nova Mamoré | D25: Nova Mamoré - RO | E25: RO | F25: 11 | G25: Rondônia | H25: Norte | I25: 1101 | J25: Porto Velho | K25: 110001 | L25: Porto Velho | M25: -10.4174 | N25: -65.3321 | O25: IBGE Localidades 2022 (Sede Municipal) | P25: OK | Q25: Não | R25: 6 | S25: 110033805 | T25: Nova Mamoré | U25: Nova Mamoré; Araras; Jacynópolis; Nova Dimensão; Palmeiras; Nova Marechal Rondon | V25: Sim | X25: -10.382233 | Y25: -64.629367 | Z25: Sim | AA25: -10.284917 | AB25: -64.512351
A26: 1100346 | B26: 110034 | C26: Alvorada D'Oeste | D26: Alvorada D'Oeste - RO | E26: RO | F26: 11 | G26: Rondônia | H26: Norte | I26: 1102 | J26: Ji-Paraná | K26: 110004 | L26: Ji-Paraná | M26: -11.3547 | N26: -62.2845 | O26: IBGE Localidades 2022 (Sede Municipal) | P26: OK | Q26: Não | R26: 3 | S26: 110034605 | T26: Alvorada D'Oeste | U26: Alvorada D'Oeste; Tancredópolis; Terra Boa | V26: Sim | X26: -11.311477 | Y26: -62.545137 | Z26: Sim | AA26: -11.345299 | AB26: -62.42378
A27: 1100379 | B27: 110037 | C27: Alto Alegre dos Parecis | D27: Alto Alegre dos Parecis - RO | E27: RO | F27: 11 | G27: Rondônia | H27: Norte | I27: 1102 | J27: Ji-Paraná | K27: 110005 | L27: Cacoal | M27: -12.134 | N27: -61.8587 | O27: IBGE Localidades 2022 (Sede Municipal) | P27: OK | Q27: Não | R27: 1 | S27: 110037905 | T27: Alto Alegre dos Parecis | U27: Alto Alegre dos Parecis | V27: Sim | X27: -12.593422 | Y27: -61.880598 | Z27: Sim | AA27: -12.584885 | AB27: -61.798945
A28: 1100403 | B28: 110040 | C28: Alto Paraíso | D28: Alto Paraíso - RO | E28: RO | F28: 11 | G28: Rondônia | H28: Norte | I28: 1101 | J28: Porto Velho | K28: 110002 | L28: Ariquemes | M28: -9.7201 | N28: -63.3179 | O28: IBGE Localidades 2022 (Sede Municipal) | P28: OK | Q28: Não | R28: 1 | S28: 110040305 | T28: Alto Paraíso | U28: Alto Paraíso | V28: Sim | X28: -9.649294 | Y28: -63.394227 | Z28: Sim | AA28: -9.613147 | AB28: -63.346634
A29: 1100452 | B29: 110045 | C29: Buritis | D29: Buritis - RO | E29: RO | F29: 11 | G29: Rondônia | H29: Norte | I29: 1101 | J29: Porto Velho | K29: 110002 | L29: Ariquemes | M29: -10.2025 | N29: -63.8349 | O29: IBGE Localidades 2022 (Sede Municipal) | P29: OK | Q29: Não | R29: 1 | S29: 110045205 | T29: Buritis | U29: Buritis | V29: Sim | X29: -10.052139 | Y29: -63.94119 | Z29: Sim | AA29: -10.005082 | AB29: -63.9394
A30: 1100502 | B30: 110050 | C30: Novo Horizonte do Oeste | D30: Novo Horizonte do Oeste - RO | E30: RO | F30: 11 | G30: Rondônia | H30: Norte | I30: 1102 | J30: Ji-Paraná | K30: 110005 | L30: Cacoal | M30: -11.7065 | N30: -62.0001 | O30: IBGE Localidades 2022 (Sede Municipal) | P30: OK | Q30: Não | R30: 2 | S30: 110050205 | T30: Novo Horizonte do Oeste | U30: Novo Horizonte do Oeste; Migrantinópolis | V30: Sim | X30: -11.680995 | Y30: -62.083184 | Z30: Sim | AA30: -11.70893 | AB30: -62.088049
A31: 1100601 | B31: 110060 | C31: Cacaulândia | D31: Cacaulândia - RO | E31: RO | F31: 11 | G31: Rondônia | H31: Norte | I31: 1101 | J31: Porto Velho | K31: 110002 | L31: Ariquemes | M31: -10.3423 | N31: -62.9011 | O31: IBGE Localidades 2022 (Sede Municipal) | P31: OK | Q31: Não | R31: 1 | S31: 110060105 | T31: Cacaulândia | U31: Cacaulândia | V31: Sim | X31: -10.331607 | Y31: -62.987203 | Z31: Sim | AA31: -10.329488 | AB31: -63.072489
A32: 1100700 | B32: 110070 | C32: Campo Novo de Rondônia | D32: Campo Novo de Rondônia - RO | E32: RO | F32: 11 | G32: Rondônia | H32: Norte | I32: 1101 | J32: Porto Velho | K32: 110002 | L32: Ariquemes | M32: -10.568 | N32: -63.6201 | O32: IBGE Localidades 2022 (Sede Municipal) | P32: OK | Q32: Não | R32: 1 | S32: 110070005 | T32: Campo Novo de Rondônia | U32: Campo Novo de Rondônia | V32: Sim | X32: -10.484943 | Y32: -63.799717 | Z32: Sim | AA32: -10.538987 | AB32: -63.757288
A33: 1100809 | B33: 110080 | C33: Candeias do Jamari | D33: Candeias do Jamari - RO | E33: RO | F33: 11 | G33: Rondônia | H33: Norte | I33: 1101 | J33: Porto Velho | K33: 110001 | L33: Porto Velho | M33: -8.7966 | N33: -63.7006 | O33: IBGE Localidades 2022 (Sede Municipal) | P33: OK | Q33: Não | R33: 2 | S33: 110080905 | T33: Candeias do Jamari | U33: Candeias do Jamari; Rio Preto do Candeias | V33: Sim | X33: -8.886971 | Y33: -63.325398 | Z33: Sim | AA33: -8.738736 | AB33: -63.085037
A34: 1100908 | B34: 110090 | C34: Castanheiras | D34: Castanheiras - RO | E34: RO | F34: 11 | G34: Rondônia | H34: Norte | I34: 1102 | J34: Ji-Paraná | K34: 110005 | L34: Cacoal | M34: -11.426842 | N34: -61.949161 | O34: IBGE Localidades 2010 (Cidade) | P34: Corrigida | Q34: Não | R34: 1 | S34: 110090805 | T34: Castanheiras | U34: Castanheiras | V34: Sim | W34: Ponto IBGE 2022 (-11,5005; -61,8876) divergia 10,6 km do IBGE 2010 e 10,7 km da base independente; substituído pelo IBGE 2010. O ponto 2022 coincide com Povoado 'Jardinópolis' (IBGE 2010, a 0,55 km). | X34: -11.470791 | Y34: -61.880139 | Z34: Sim | AA34: -11.476983 | AB34: -61.892774
A35: 1100924 | B35: 110092 | C35: Chupinguaia | D35: Chupinguaia - RO | E35: RO | F35: 11 | G35: Rondônia | H35: Norte | I35: 1102 | J35: Ji-Paraná | K35: 110006 | L35: Vilhena | M35: -12.5514 | N35: -60.8997 | O35: IBGE Localidades 2022 (Sede Municipal) | P35: OK | Q35: Não | R35: 1 | S35: 110092405 | T35: Chupinguaia | U35: Chupinguaia | V35: Sim | X35: -12.537216 | Y35: -60.899259 | Z35: Sim | AA35: -12.490685 | AB35: -61.027419
A36: 1100940 | B36: 110094 | C36: Cujubim | D36: Cujubim - RO | E36: RO | F36: 11 | G36: Rondônia | H36: Norte | I36: 1101 | J36: Porto Velho | K36: 110002 | L36: Ariquemes | M36: -9.3683 | N36: -62.5825 | O36: IBGE Localidades 2022 (Sede Municipal) | P36: OK | Q36: Não | R36: 1 | S36: 110094005 | T36: Cujubim | U36: Cujubim | V36: Sim | X36: -9.170907 | Y36: -62.565257 | Z36: Sim | AA36: -9.17565 | AB36: -62.53364
A37: 1101005 | B37: 110100 | C37: Governador Jorge Teixeira | D37: Governador Jorge Teixeira - RO | E37: RO | F37: 11 | G37: Rondônia | H37: Norte | I37: 1101 | J37: Porto Velho | K37: 110003 | L37: Jaru | M37: -10.6136 | N37: -62.7341 | O37: IBGE Localidades 2022 (Sede Municipal) | P37: OK | Q37: Não | R37: 2 | S37: 110100505 | T37: Governador Jorge Teixeira | U37: Governador Jorge Teixeira; Colina Verde | V37: Sim | X37: -10.748038 | Y37: -63.183977 | Z37: Sim | AA37: -10.765933 | AB37: -63.276479
A38: 1101104 | B38: 110110 | C38: Itapuã do Oeste | D38: Itapuã do Oeste - RO | E38: RO | F38: 11 | G38: Rondônia | H38: Norte | I38: 1101 | J38: Porto Velho | K38: 110001 | L38: Porto Velho | M38: -9.1871 | N38: -63.1884 | O38: IBGE Localidades 2022 (Sede Municipal) | P38: OK | Q38: Não | R38: 1 | S38: 110110405 | T38: Itapuã do Oeste | U38: Itapuã do Oeste | V38: Sim | X38: -9.170292 | Y38: -63.044923 | Z38: Sim | AA38: -9.230147 | AB38: -63.043504
A39: 1101203 | B39: 110120 | C39: Ministro Andreazza | D39: Ministro Andreazza - RO | E39: RO | F39: 11 | G39: Rondônia | H39: Norte | I39: 1102 | J39: Ji-Paraná | K39: 110005 | L39: Cacoal | M39: -11.1969 | N39: -61.5177 | O39: IBGE Localidades 2022 (Sede Municipal) | P39: OK | Q39: Não | R39: 1 | S39: 110120305 | T39: Ministro Andreazza | U39: Ministro Andreazza | V39: Sim | X39: -11.160218 | Y39: -61.56891 | Z39: Sim | AA39: -11.183936 | AB39: -61.583733
A40: 1101302 | B40: 110130 | C40: Mirante da Serra | D40: Mirante da Serra - RO | E40: RO | F40: 11 | G40: Rondônia | H40: Norte | I40: 1102 | J40: Ji-Paraná | K40: 110004 | L40: Ji-Paraná | M40: -11.0308 | N40: -62.6746 | O40: IBGE Localidades 2022 (Sede Municipal) | P40: OK | Q40: Não | R40: 1 | S40: 110130205 | T40: Mirante da Serra | U40: Mirante da Serra | V40: Sim | X40: -11.076826 | Y40: -62.84783 | Z40: Sim | AA40: -11.048959 | AB40: -62.760346
A41: 1101401 | B41: 110140 | C41: Monte Negro | D41: Monte Negro - RO | E41: RO | F41: 11 | G41: Rondônia | H41: Norte | I41: 1101 | J41: Porto Velho | K41: 110002 | L41: Ariquemes | M41: -10.263098 | N41: -63.295559 | O41: IBGE Localidades 2010 (Cidade) | P41: Corrigida | Q41: Não | R41: 1 | S41: 110140105 | T41: Monte Negro | U41: Monte Negro | V41: Sim | W41: Ponto IBGE 2022 (-10,0375; -63,3339) divergia 25,4 km do IBGE 2010 e 23,7 km da base independente; substituído pelo IBGE 2010. O ponto 2022 está isolado (localidade IBGE 2010 mais próxima a 35,7 km). | X41: -10.210767 | Y41: -63.372356 | Z41: Sim | AA41: -10.152991 | AB41: -63.371326
A42: 1101435 | B42: 110143 | C42: Nova União | D42: Nova União - RO | E42: RO | F42: 11 | G42: Rondônia | H42: Norte | I42: 1102 | J42: Ji-Paraná | K42: 110004 | L42: Ji-Paraná | M42: -10.9164 | N42: -62.5553 | O42: IBGE Localidades 2022 (Sede Municipal) | P42: OK | Q42: Não | R42: 1 | S42: 110143505 | T42: Nova União | U42: Nova União | V42: Sim | X42: -10.889337 | Y42: -62.532363 | Z42: Sim | AA42: -10.889015 | AB42: -62.532038
A43: 1101450 | B43: 110145 | C43: Parecis | D43: Parecis - RO | E43: RO | F43: 11 | G43: Rondônia | H43: Norte | I43: 1102 | J43: Ji-Paraná | K43: 110005 | L43: Cacoal | M43: -12.1796 | N43: -61.6043 | O43: IBGE Localidades 2022 (Sede Municipal) | P43: OK | Q43: Não | R43: 1 | S43: 110145005 | T43: Parecis | U43: Parecis | V43: Sim | X43: -12.262324 | Y43: -61.415379 | Z43: Sim | AA43: -12.283664 | AB43: -61.399522
A44: 1101468 | B44: 110146 | C44: Pimenteiras do Oeste | D44: Pimenteiras do Oeste - RO | E44: RO | F44: 11 | G44: Rondônia | H44: Norte | I44: 1102 | J44: Ji-Paraná | K44: 110006 | L44: Vilhena | M44: -13.4835 | N44: -61.0465 | O44: IBGE Localidades 2022 (Sede Municipal) | P44: OK | Q44: Não | R44: 1 | S44: 110146805 | T44: Pimenteiras do Oeste | U44: Pimenteiras do Oeste | V44: Sim | X44: -13.17378 | Y44: -61.545517 | Z44: Não | AA44: -13.050516 | AB44: -61.790505
A45: 1101476 | B45: 110147 | C45: Primavera de Rondônia | D45: Primavera de Rondônia - RO | E45: RO | F45: 11 | G45: Rondônia | H45: Norte | I45: 1102 | J45: Ji-Paraná | K45: 110005 | L45: Cacoal | M45: -11.825707 | N45: -61.316546 | O45: IBGE Localidades 2010 (Cidade) | P45: Corrigida | Q45: Não | R45: 1 | S45: 110147605 | T45: Primavera de Rondônia | U45: Primavera de Rondônia | V45: Sim | W45: Ponto IBGE 2022 (-11,9749; -61,3769) divergia 17,8 km do IBGE 2010 e 17,5 km da base independente; substituído pelo IBGE 2010. O ponto 2022 coincide com Povoado 'Querência do Norte' (IBGE 2010, a 0,14 km). | X45: -11.878747 | Y45: -61.315336 | Z45: Sim | AA45: -11.812942 | AB45: -61.312256
A46: 1101484 | B46: 110148 | C46: São Felipe D'Oeste | D46: São Felipe D'Oeste - RO | E46: RO | F46: 11 | G46: Rondônia | H46: Norte | I46: 1102 | J46: Ji-Paraná | K46: 110005 | L46: Cacoal | M46: -11.914389 | N46: -61.512508 | O46: IBGE Localidades 2010 (Cidade) | P46: Corrigida | Q46: Não | R46: 1 | S46: 110148405 | T46: São Felipe D'Oeste | U46: São Felipe D'Oeste | V46: Sim | W46: Ponto IBGE 2022 (-11,8002; -61,4737) divergia 13,4 km do IBGE 2010 e 11,8 km da base independente; substituído pelo IBGE 2010. O ponto 2022 coincide com Povoado 'Novo Paraíso' (IBGE 2010, a 0,09 km). | X46: -11.904908 | Y46: -61.467095 | Z46: Sim | AA46: -11.826367 | AB46: -61.464465
A47: 1101492 | B47: 110149 | C47: São Francisco do Guaporé | D47: São Francisco do Guaporé - RO | E47: RO | F47: 11 | G47: Rondônia | H47: Norte | I47: 1102 | J47: Ji-Paraná | K47: 110004 | L47: Ji-Paraná | M47: -12.0794 | N47: -63.5677 | O47: IBGE Localidades 2022 (Sede Municipal) | P47: OK | Q47: Não | R47: 4 | S47: 110149205 | T47: São Francisco do Guaporé | U47: São Francisco do Guaporé; Porto Murtinho; Pedras Negras; Santo Antônio do Guaporé | V47: Sim | X47: -12.368499 | Y47: -63.122725 | Z47: Sim | AA47: -12.540153 | AB47: -62.769768
A48: 1101500 | B48: 110150 | C48: Seringueiras | D48: Seringueiras - RO | E48: RO | F48: 11 | G48: Rondônia | H48: Norte | I48: 1102 | J48: Ji-Paraná | K48: 110004 | L48: Ji-Paraná | M48: -11.7714 | N48: -63.0369 | O48: IBGE Localidades 2022 (Sede Municipal) | P48: OK | Q48: Não | R48: 1 | S48: 110150005 | T48: Seringueiras | U48: Seringueiras | V48: Sim | X48: -11.782392 | Y48: -63.18651 | Z48: Sim | AA48: -11.745529 | AB48: -63.1266
A49: 1101559 | B49: 110155 | C49: Teixeirópolis | D49: Teixeirópolis - RO | E49: RO | F49: 11 | G49: Rondônia | H49: Norte | I49: 1102 | J49: Ji-Paraná | K49: 110004 | L49: Ji-Paraná | M49: -10.9336 | N49: -62.2553 | O49: IBGE Localidades 2022 (Sede Municipal) | P49: OK | Q49: Não | R49: 1 | S49: 110155905 | T49: Teixeirópolis | U49: Teixeirópolis | V49: Sim | X49: -10.943448 | Y49: -62.279771 | Z49: Sim | AA49: -10.928776 | AB49: -62.277738
A50: 1101609 | B50: 110160 | C50: Theobroma | D50: Theobroma - RO | E50: RO | F50: 11 | G50: Rondônia | H50: Norte | I50: 1101 | J50: Porto Velho | K50: 110003 | L50: Jaru | M50: -10.2459 | N50: -62.3495 | O50: IBGE Localidades 2022 (Sede Municipal) | P50: OK | Q50: Não | R50: 1 | S50: 110160905 | T50: Theobroma | U50: Theobroma | V50: Sim | X50: -10.121763 | Y50: -62.342434 | Z50: Sim | AA50: -10.117329 | AB50: -62.372491
A51: 1101708 | B51: 110170 | C51: Urupá | D51: Urupá - RO | E51: RO | F51: 11 | G51: Rondônia | H51: Norte | I51: 1102 | J51: Ji-Paraná | K51: 110004 | L51: Ji-Paraná | M51: -11.1215 | N51: -62.3756 | O51: IBGE Localidades 2022 (Sede Municipal) | P51: OK | Q51: Não | R51: 1 | S51: 110170805 | T51: Urupá | U51: Urupá | V51: Sim | X51: -11.103963 | Y51: -62.424209 | Z51: Sim | AA51: -11.09242 | AB51: -62.331196
A52: 1101757 | B52: 110175 | C52: Vale do Anari | D52: Vale do Anari - RO | E52: RO | F52: 11 | G52: Rondônia | H52: Norte | I52: 1101 | J52: Porto Velho | K52: 110003 | L52: Jaru | M52: -9.8557 | N52: -62.1762 | O52: IBGE Localidades 2022 (Sede Municipal) | P52: OK | Q52: Não | R52: 1 | S52: 110175705 | T52: Vale do Anari | U52: Vale do Anari | V52: Sim | X52: -9.732444 | Y52: -61.938965 | Z52: Sim | AA52: -9.861048 | AB52: -62.129179
A53: 1101807 | B53: 110180 | C53: Vale do Paraíso | D53: Vale do Paraíso - RO | E53: RO | F53: 11 | G53: Rondônia | H53: Norte | I53: 1102 | J53: Ji-Paraná | K53: 110004 | L53: Ji-Paraná | M53: -10.427 | N53: -62.1332 | O53: IBGE Localidades 2022 (Sede Municipal) | P53: OK | Q53: Não | R53: 1 | S53: 110180705 | T53: Vale do Paraíso | U53: Vale do Paraíso | V53: Sim | X53: -10.384172 | Y53: -62.09399 | Z53: Sim | AA53: -10.48286 | AB53: -62.138496
A54: 1200013 | B54: 120001 | C54: Acrelândia | D54: Acrelândia - AC | E54: AC | F54: 12 | G54: Acre | H54: Norte | I54: 1201 | J54: Rio Branco | K54: 120001 | L54: Rio Branco | M54: -10.0774 | N54: -67.0504 | O54: IBGE Localidades 2022 (Sede Municipal) | P54: OK | Q54: Não | R54: 1 | S54: 120001305 | T54: Acrelândia | U54: Acrelândia | V54: Sim | X54: -9.933862 | Y54: -66.950161 | Z54: Sim | AA54: -9.936192 | AB54: -66.932479
A55: 1200054 | B55: 120005 | C55: Assis Brasil | D55: Assis Brasil - AC | E55: AC | F55: 12 | G55: Acre | H55: Norte | I55: 1201 | J55: Rio Branco | K55: 120002 | L55: Brasiléia | M55: -10.9401 | N55: -69.5672 | O55: IBGE Localidades 2022 (Sede Municipal) | P55: OK | Q55: Não | R55: 1 | S55: 120005405 | T55: Assis Brasil | U55: Assis Brasil | V55: Sim | X55: -10.779812 | Y55: -70.004443 | Z55: Sim | AA55: -10.881766 | AB55: -70.278787
A56: 1200104 | B56: 120010 | C56: Brasiléia | D56: Brasiléia - AC | E56: AC | F56: 12 | G56: Acre | H56: Norte | I56: 1201 | J56: Rio Branco | K56: 120002 | L56: Brasiléia | M56: -11.0154 | N56: -68.75 | O56: IBGE Localidades 2022 (Sede Municipal) | P56: OK | Q56: Não | R56: 1 | S56: 120010405 | T56: Brasiléia | U56: Brasiléia | V56: Sim | X56: -10.747332 | Y56: -69.207465 | Z56: Sim | AA56: -10.74614 | AB56: -69.19061
A57: 1200138 | B57: 120013 | C57: Bujari | D57: Bujari - AC | E57: AC | F57: 12 | G57: Acre | H57: Norte | I57: 1201 | J57: Rio Branco | K57: 120001 | L57: Rio Branco | M57: -9.8311 | N57: -67.9524 | O57: IBGE Localidades 2022 (Sede Municipal) | P57: OK | Q57: Não | R57: 1 | S57: 120013805 | T57: Bujari | U57: Bujari | V57: Sim | X57: -9.613992 | Y57: -68.173717 | Z57: Sim | AA57: -9.628872 | AB57: -68.250277
A58: 1200179 | B58: 120017 | C58: Capixaba | D58: Capixaba - AC | E58: AC | F58: 12 | G58: Acre | H58: Norte | I58: 1201 | J58: Rio Branco | K58: 120001 | L58: Rio Branco | M58: -10.5722 | N58: -67.6753 | O58: IBGE Localidades 2022 (Sede Municipal) | P58: OK | Q58: Não | R58: 1 | S58: 120017905 | T58: Capixaba | U58: Capixaba | V58: Sim | X58: -10.474263 | Y58: -67.835896 | Z58: Sim | AA58: -10.453967 | AB58: -67.876172
... A87: 1300680 | B87: 130068 | C87: Boa Vista do Ramos | D87: Boa Vista do Ramos - AM | E87: AM | F87: 13 | G87: Amazonas | H87: Norte | I87: 1304 | J87: Parintins | K87: 130010 | L87: Parintins | M87: -2.9704 | N87: -57.5884 | O87: IBGE Localidades 2022 (Sede Municipal) | P87: OK | Q87: Não | R87: 4 | S87: 130068005 | T87: Boa Vista do Ramos | U87: Boa Vista do Ramos; Lago Preto; Massauari; Do Rio Urubu | V87: Sim | X87: -3.138774 | Y87: -57.670151 | Z87: Não | AA87: -3.029851 | AB87: -57.576781
A88: 1300706 | B88: 130070 | C88: Boca do Acre | D88: Boca do Acre - AM | E88: AM | F88: 13 | G88: Amazonas | H88: Norte | I88: 1303 | J88: Lábrea | K88: 130008 | L88: Lábrea | M88: -8.751243 | N88: -67.399578 | O88: IBGE Localidades 2010 (Cidade) | P88: Corrigida - a conferir | Q88: Não | R88: 2 | S88: 130070605 | T88: Boca do Acre | U88: Boca do Acre; Floriano Peixoto | V88: Sim | W88: Ponto IBGE 2022 (-8,7724; -67,3360) divergia 7,4 km do IBGE 2010 e 7,0 km da base independente; substituído pelo IBGE 2010. Fontes divergem ~7 km; o município tem mais de um núcleo urbano. | X88: -8.772993 | Y88: -68.047873 | Z88: Sim | AA88: -8.615059 | AB88: -68.358061
A89: 1300805 | B89: 130080 | C89: Borba | D89: Borba - AM | E89: AM | F89: 13 | G89: Amazonas | H89: Norte | I89: 1301 | J89: Manaus | K89: 130001 | L89: Manaus | M89: -4.3945 | N89: -59.589 | O89: IBGE Localidades 2022 (Sede Municipal) | P89: OK | Q89: Não | R89: 3 | S89: 130080505 | T89: Borba | U89: Borba; Canumã; Axinin | V89: Sim | X89: -4.967847 | Y89: -59.535141 | Z89: Sim | AA89: -4.74493 | AB89: -59.238295
A90: 1300839 | B90: 130083 | C90: Caapiranga | D90: Caapiranga - AM | E90: AM | F90: 13 | G90: Amazonas | H90: Norte | I90: 1301 | J90: Manaus | K90: 130004 | L90: Manacapuru | M90: -3.3268 | N90: -61.2134 | O90: IBGE Localidades 2022 (Sede Municipal) | P90: OK | Q90: Não | R90: 1 | S90: 130083905 | T90: Caapiranga | U90: Caapiranga | V90: Sim | X90: -3.073816 | Y90: -61.873606 | Z90: Sim | AA90: -2.958419 | AB90: -61.893371
A91: 1300904 | B91: 130090 | C91: Canutama | D91: Canutama - AM | E91: AM | F91: 13 | G91: Amazonas | H91: Norte | I91: 1303 | J91: Lábrea | K91: 130008 | L91: Lábrea | M91: -6.5328 | N91: -64.3872 | O91: IBGE Localidades 2022 (Sede Municipal) | P91: OK | Q91: Não | R91: 3 | S91: 130090405 | T91: Canutama | U91: Canutama; Belo Monte; Açuanópolis | V91: Sim | X91: -7.297876 | Y91: -64.062921 | Z91: Sim | AA91: -7.032278 | AB91: -63.938693
A92: 1301001 | B92: 130100 | C92: Carauari | D92: Carauari - AM | E92: AM | F92: 13 | G92: Amazonas | H92: Norte | I92: 1302 | J92: Tefé | K92: 130005 | L92: Tefé | M92: -4.8781 | N92: -66.8972 | O92: IBGE Localidades 2022 (Sede Municipal) | P92: OK | Q92: Não | R92: 1 | S92: 130100105 | T92: Carauari | U92: Carauari | V92: Sim | X92: -5.11208 | Y92: -67.331923 | Z92: Sim | AA92: -5.188828 | AB92: -67.507575
A93: 1301100 | B93: 130110 | C93: Careiro | D93: Careiro - AM | E93: AM | F93: 13 | G93: Amazonas | H93: Norte | I93: 1301 | J93: Manaus | K93: 130001 | L93: Manaus | M93: -3.8239 | N93: -60.3627 | O93: IBGE Localidades 2022 (Sede Municipal) | P93: OK | Q93: Não | R93: 3 | S93: 130110005 | T93: Careiro | U93: Careiro; Purupuru; Janauacá | V93: Sim | X93: -3.772717 | Y93: -60.185095 | Z93: Sim | AA93: -3.642911 | AB93: -60.060004
A94: 1301159 | B94: 130115 | C94: Careiro da Várzea | D94: Careiro da Várzea - AM | E94: AM | F94: 13 | G94: Amazonas | H94: Norte | I94: 1301 | J94: Manaus | K94: 130001 | L94: Manaus | M94: -3.1988 | N94: -59.825 | O94: IBGE Localidades 2022 (Sede Municipal) | P94: OK | Q94: Não | R94: 1 | S94: 130115905 | T94: Careiro da Várzea | U94: Careiro da Várzea | V94: Sim | X94: -3.287479 | Y94: -59.602639 | Z94: Sim | AA94: -3.312813 | AB94: -59.500334
A95: 1301209 | B95: 130120 | C95: Coari | D95: Coari - AM | E95: AM | F95: 13 | G95: Amazonas | H95: Norte | I95: 1301 | J95: Manaus | K95: 130003 | L95: Coari | M95: -4.0861 | N95: -63.1426 | O95: IBGE Localidades 2022 (Sede Municipal) | P95: OK | Q95: Não | R95: 1 | S95: 130120905 | T95: Coari | U95: Coari | V95: Sim | X95: -4.441521 | Y95: -64.127155 | Z95: Sim | AA95: -4.475875 | AB95: -63.893756
A96: 1301308 | B96: 130130 | C96: Codajás | D96: Codajás - AM | E96: AM | F96: 13 | G96: Amazonas | H96: Norte | I96: 1301 | J96: Manaus | K96: 130003 | L96: Coari | M96: -3.8387 | N96: -62.0596 | O96: IBGE Localidades 2022 (Sede Municipal) | P96: OK | Q96: Não | R96: 2 | S96: 130130805 | T96: Codajás | U96: Codajás; Badajós | V96: Sim | X96: -3.279657 | Y96: -62.985834 | Z96: Sim | AA96: -3.16198 | AB96: -63.230358
A97: 1301407 | B97: 130140 | C97: Eirunepé | D97: Eirunepé - AM | E97: AM | F97: 13 | G97: Amazonas | H97: Norte | I97: 1302 | J97: Tefé | K97: 130007 | L97: Eirunepé | M97: -6.6678 | N97: -69.865 | O97: IBGE Localidades 2022 (Sede Municipal) | P97: OK | Q97: Não | R97: 1 | S97: 130140705 | T97: Eirunepé | U97: Eirunepé | V97: Sim | X97: -7.017155 | Y97: -70.212689 | Z97: Sim | AA97: -6.987065 | AB97: -70.33423
A98: 1301506 | B98: 130150 | C98: Envira | D98: Envira - AM | E98: AM | F98: 13 | G98: Amazonas | H98: Norte | I98: 1302 | J98: Tefé | K98: 130007 | L98: Eirunepé | M98: -7.4363 | N98: -70.0233 | O98: IBGE Localidades 2022 (Sede Municipal) | P98: OK | Q98: Não | R98: 1 | S98: 130150605 | T98: Envira | U98: Envira | V98: Sim | X98: -7.575697 | Y98: -70.058609 | Z98: Sim | AA98: -7.58526 | AB98: -69.921057
A99: 1301605 | B99: 130160 | C99: Fonte Boa | D99: Fonte Boa - AM | E99: AM | F99: 13 | G99: Amazonas | H99: Norte | I99: 1302 | J99: Tefé | K99: 130005 | L99: Tefé | M99: -2.515 | N99: -66.104 | O99: IBGE Localidades 2022 (Sede Municipal) | P99: OK | Q99: Não | R99: 1 | S99: 130160505 | T99: Fonte Boa | U99: Fonte Boa | V99: Sim | X99: -2.493498 | Y99: -66.36805 | Z99: Sim | AA99: -2.423522 | AB99: -66.126776
A100: 1301654 | B100: 130165 | C100: Guajará | D100: Guajará - AM | E100: AM | F100: 13 | G100: Amazonas | H100: Norte | I100: 1302 | J100: Tefé | K100: 130007 | L100: Eirunepé | M100: -7.5484 | N100: -72.5888 | O100: IBGE Localidades 2022 (Sede Municipal) | P100: OK | Q100: Não | R100: 1 | S100: 130165405 | T100: Guajará | U100: Guajará | V100: Sim | X100: -7.236986 | Y100: -72.829347 | Z100: Sim | AA100: -7.221318 | AB100: -72.844414
... A112: 1302553 | B112: 130255 | C112: Manaquiri | D112: Manaquiri - AM | E112: AM | F112: 13 | G112: Amazonas | H112: Norte | I112: 1301 | J112: Manaus | K112: 130001 | L112: Manaus | M112: -3.4297 | N112: -60.4594 | O112: IBGE Localidades 2022 (Sede Municipal) | P112: OK | Q112: Não | R112: 1 | S112: 130255305 | T112: Manaquiri | U112: Manaquiri | V112: Sim | X112: -3.774811 | Y112: -60.697625 | Z112: Sim | AA112: -3.948626 | AB112: -60.839301
A113: 1302603 | B113: 130260 | C113: Manaus | D113: Manaus - AM | E113: AM | F113: 13 | G113: Amazonas | H113: Norte | I113: 1301 | J113: Manaus | K113: 130001 | L113: Manaus | M113: -3.0922 | N113: -60.0604 | O113: IBGE Localidades 2022 (Sede Municipal) | P113: OK | Q113: Sim | R113: 1 | S113: 130260305 | T113: Manaus | U113: Manaus | V113: Sim | W113: Ponto IBGE 2022 mantido (capital: o ponto só é substituído acima de 10 km), mas o IBGE 2010 (-3,1347; -60,0233) fica a 6,3 km e a base independente a 5,3 km dele; entre si, as duas referências distam 1,8 km. | X113: -2.621236 | Y113: -60.25867 | Z113: Sim | AA113: -2.611034 | AB113: -60.407052
A114: 1302702 | B114: 130270 | C114: Manicoré | D114: Manicoré - AM | E114: AM | F114: 13 | G114: Amazonas | H114: Norte | I114: 1303 | J114: Lábrea | K114: 130009 | L114: Manicoré | M114: -5.813205 | N114: -61.299248 | O114: IBGE Localidades 2010 (Cidade) | P114: Corrigida | Q114: Não | R114: 2 | S114: 130270205 | T114: Manicoré | U114: Manicoré; Santo Antônio do Matupi | V114: Sim | W114: Ponto IBGE 2022 (-7,9257; -61,5645) divergia 236,7 km do IBGE 2010 e 237,8 km da base independente; substituído pelo IBGE 2010. O ponto 2022 coincide com Projeto de Assentamento 'Agrovila do PA Santo Antonio do Matupi' (IBGE 2010, a 0,82 km). | X114: -6.457981 | Y114: -61.444467 | Z114: Sim | AA114: -5.903311 | AB114: -61.22329
A115: 1302801 | B115: 130280 | C115: Maraã | D115: Maraã - AM | E115: AM | F115: 13 | G115: Amazonas | H115: Norte | I115: 1302 | J115: Tefé | K115: 130005 | L115: Tefé | M115: -1.8604 | N115: -65.5913 | O115: IBGE Localidades 2022 (Sede Municipal) | P115: OK | Q115: Não | R115: 1 | S115: 130280105 | T115: Maraã | U115: Maraã | V115: Sim | X115: -2.423676 | Y115: -65.042423 | Z115: Sim | AA115: -1.977092 | AB115: -65.720989
A116: 1302900 | B116: 130290 | C116: Maués | D116: Maués - AM | E116: AM | F116: 13 | G116: Amazonas | H116: Norte | I116: 1304 | J116: Parintins | K116: 130010 | L116: Parintins | M116: -3.3959 | N116: -57.7187 | O116: IBGE Localidades 2022 (Sede Municipal) | P116: OK | Q116: Não | R116: 3 | S116: 130290005 | T116: Maués | U116: Maués; Osório da Fonseca; Repartimento | V116: Sim | X116: -4.982999 | Y116: -58.059792 | Z116: Sim | AA116: -3.972184 | AB116: -57.691062
A117: 1303007 | B117: 130300 | C117: Nhamundá | D117: Nhamundá - AM | E117: AM | F117: 13 | G117: Amazonas | H117: Norte | I117: 1304 | J117: Parintins | K117: 130010 | L117: Parintins | M117: -2.1898 | N117: -56.7121 | O117: IBGE Localidades 2022 (Sede Municipal) | P117: OK | Q117: Não | R117: 1 | S117: 130300705 | T117: Nhamundá | U117: Nhamundá | V117: Sim | X117: -1.682528 | Y117: -57.654661 | Z117: Sim | AA117: -2.045416 | AB117: -57.324928
A118: 1303106 | B118: 130310 | C118: Nova Olinda do Norte | D118: Nova Olinda do Norte - AM | E118: AM | F118: 13 | G118: Amazonas | H118: Norte | I118: 1301 | J118: Manaus | K118: 130001 | L118: Manaus | M118: -3.8859 | N118: -59.0901 | O118: IBGE Localidades 2022 (Sede Municipal) | P118: OK | Q118: Não | R118: 1 | S118: 130310605 | T118: Nova Olinda do Norte | U118: Nova Olinda do Norte | V118: Sim | X118: -3.988954 | Y118: -58.599821 | Z118: Sim | AA118: -4.285306 | AB118: -58.433051
A119: 1303205 | B119: 130320 | C119: Novo Airão | D119: Novo Airão - AM | E119: AM | F119: 13 | G119: Amazonas | H119: Norte | I119: 1301 | J119: Manaus | K119: 130004 | L119: Manacapuru | M119: -2.6233 | N119: -60.9429 | O119: IBGE Localidades 2022 (Sede Municipal) | P119: OK | Q119: Não | R119: 1 | S119: 130320505 | T119: Novo Airão | U119: Novo Airão | V119: Sim | X119: -2.031564 | Y119: -61.679501 | Z119: Sim | AA119: -2.307073 | AB119: -61.197282
A120: 1303304 | B120: 130330 | C120: Novo Aripuanã | D120: Novo Aripuanã - AM | E120: AM | F120: 13 | G120: Amazonas | H120: Norte | I120: 1303 | J120: Lábrea | K120: 130009 | L120: Manicoré | M120: -5.1209 | N120: -60.38 | O120: IBGE Localidades 2022 (Sede Municipal) | P120: OK | Q120: Não | R120: 1 | S120: 130330405 | T120: Novo Aripuanã | U120: Novo Aripuanã | V120: Sim | X120: -6.823733 | Y120: -60.472649 | Z120: Sim | AA120: -5.994191 | AB120: -60.051598
A121: 1303403 | B121: 130340 | C121: Parintins | D121: Parintins - AM | E121: AM | F121: 13 | G121: Amazonas | H121: Norte | I121: 1304 | J121: Parintins | K121: 130010 | L121: Parintins | M121: -2.6264 | N121: -56.7349 | O121: IBGE Localidades 2022 (Sede Municipal) | P121: OK | Q121: Não | R121: 6 | S121: 130340305 | T121: Parintins | U121: Parintins; Mocambo; Caburi; Vila Amazônia; Tracajá; Uaicurapá | V121: Sim | X121: -2.694309 | Y121: -56.856999 | Z121: Sim | AA121: -2.566902 | AB121: -56.658626
A122: 1303502 | B122: 130350 | C122: Pauini | D122: Pauini - AM | E122: AM | F122: 13 | G122: Amazonas | H122: Norte | I122: 1303 | J122: Lábrea | K122: 130008 | L122: Lábrea | M122: -7.7149 | N122: -66.9992 | O122: IBGE Localidades 2022 (Sede Municipal) | P122: OK | Q122: Não | R122: 1 | S122: 130350205 | T122: Pauini | U122: Pauini | V122: Sim | X122: -7.758034 | Y122: -68.1981 | Z122: Sim | AA122: -7.938863 | AB122: -67.443915
A123: 1303536 | B123: 130353 | C123: Presidente Figueiredo | D123: Presidente Figueiredo - AM | E123: AM | F123: 13 | G123: Amazonas | H123: Norte | I123: 1301 | J123: Manaus | K123: 130001 | L123: Manaus | M123: -2.0502 | N123: -60.027 | O123: IBGE Localidades 2022 (Sede Municipal) | P123: OK | Q123: Não | R123: 2 | S123: 130353605 | T123: Presidente Figueiredo | U123: Presidente Figueiredo; Balbina | V123: Sim | X123: -1.369398 | Y123: -59.976494 | Z123: Sim | AA123: -1.489339 | AB123: -60.013227
A124: 1303569 | B124: 130356 | C124: Rio Preto da Eva | D124: Rio Preto da Eva - AM | E124: AM | F124: 13 | G124: Amazonas | H124: Norte | I124: 1301 | J124: Manaus | K124: 130001 | L124: Manaus | M124: -2.6996 | N124: -59.6996 | O124: IBGE Localidades 2022 (Sede Municipal) | P124: OK | Q124: Não | R124: 1 | S124: 130356905 | T124: Rio Preto da Eva | U124: Rio Preto da Eva | V124: Sim | X124: -2.52946 | Y124: -59.638222 | Z124: Sim | AA124: -2.619607 | AB124: -59.559757
A125: 1303601 | B125: 130360 | C125: Santa Isabel do Rio Negro | D125: Santa Isabel do Rio Negro - AM | E125: AM | F125: 13 | G125: Amazonas | H125: Norte | I125: 1301 | J125: Manaus | K125: 130002 | L125: São Gabriel da Cachoeira | M125: -0.4152 | N125: -65.0191 | O125: IBGE Localidades 2022 (Sede Municipal) | P125: OK | Q125: Não | R125: 1 | S125: 130360105 | T125: Santa Isabel do Rio Negro | U125: Santa Isabel do Rio Negro | V125: Sim | X125: -0.31436 | Y125: -65.514577 | Z125: Sim | AA125: 0.249801 | AB125: -64.880114
A126: 1303700 | B126: 130370 | C126: Santo Antônio do Içá | D126: Santo Antônio do Içá - AM | E126: AM | F126: 13 | G126: Amazonas | H126: Norte | I126: 1302 | J126: Tefé | K126: 130006 | L126: Tabatinga | M126: -3.0995 | N126: -67.9465 | O126: IBGE Localidades 2022 (Sede Municipal) | P126: OK | Q126: Não | R126: 2 | S126: 130370005 | T126: Santo Antônio do Içá | U126: Santo Antônio do Içá; Alterosa | V126: Sim | X126: -3.047274 | Y126: -69.094044 | Z126: Sim | AA126: -3.009119 | AB126: -69.368904
... A451: 1722107 | B451: 172210 | C451: Xambioá | D451: Xambioá - TO | E451: TO | F451: 17 | G451: Tocantins | H451: Norte | I451: 1702 | J451: Araguaína | K451: 170005 | L451: Araguaína | M451: -6.4113 | N451: -48.5303 | O451: IBGE Localidades 2022 (Sede Municipal) | P451: OK | Q451: Não | R451: 1 | S451: 172210705 | T451: Xambioá | U451: Xambioá | V451: Sim | X451: -6.545368 | Y451: -48.451043 | Z451: Sim | AA451: -6.519273 | AB451: -48.475604
A452: 2100055 | B452: 210005 | C452: Açailândia | D452: Açailândia - MA | E452: MA | F452: 21 | G452: Maranhão | H452: Nordeste | I452: 2105 | J452: Imperatriz | K452: 210021 | L452: Açailândia | M452: -4.9403 | N452: -47.4653 | O452: IBGE Localidades 2022 (Sede Municipal) | P452: OK | Q452: Não | R452: 1 | S452: 210005505 | T452: Açailândia | U452: Açailândia | V452: Sim | W452: Ponto IBGE 2022 mantido, mas o IBGE 2010 (-4,9514; -47,5067) fica a 4,7 km e a base independente a 4,0 km dele; entre si, as duas referências distam 0,8 km. | X452: -4.78582 | Y452: -47.332347 | Z452: Sim | AA452: -4.854336 | AB452: -47.142865
A453: 2100105 | B453: 210010 | C453: Afonso Cunha | D453: Afonso Cunha - MA | E453: MA | F453: 21 | G453: Maranhão | H453: Nordeste | I453: 2103 | J453: Caxias | K453: 210013 | L453: Caxias | M453: -4.1341 | N453: -43.324 | O453: IBGE Localidades 2022 (Sede Municipal) | P453: OK | Q453: Não | R453: 1 | S453: 210010505 | T453: Afonso Cunha | U453: Afonso Cunha | V453: Sim | X453: -4.214767 | Y453: -43.29739 | Z453: Sim | AA453: -4.21336 | AB453: -43.309747
A454: 2100154 | B454: 210015 | C454: Água Doce do Maranhão | D454: Água Doce do Maranhão - MA | E454: MA | F454: 21 | G454: Maranhão | H454: Nordeste | I454: 2101 | J454: São Luís | K454: 210007 | L454: Tutóia - Araioses | M454: -2.8379 | N454: -42.1163 | O454: IBGE Localidades 2022 (Sede Municipal) | P454: OK | Q454: Não | R454: 1 | S454: 210015405 | T454: Água Doce do Maranhão | U454: Água Doce do Maranhão | V454: Sim | X454: -2.946529 | Y454: -42.166197 | Z454: Sim | AA454: -2.998523 | AB454: -42.18844
A455: 2100204 | B455: 210020 | C455: Alcântara | D455: Alcântara - MA | E455: MA | F455: 21 | G455: Maranhão | H455: Nordeste | I455: 2101 | J455: São Luís | K455: 210001 | L455: São Luís | M455: -2.4089 | N455: -44.4176 | O455: IBGE Localidades 2022 (Sede Municipal) | P455: OK | Q455: Não | R455: 2 | S455: 210020405 | T455: Alcântara | U455: Alcântara; São João de Cortes | V455: Sim | X455: -2.379288 | Y455: -44.539812 | Z455: Sim | AA455: -2.300346 | AB455: -44.493184
A456: 2100303 | B456: 210030 | C456: Aldeias Altas | D456: Aldeias Altas - MA | E456: MA | F456: 21 | G456: Maranhão | H456: Nordeste | I456: 2103 | J456: Caxias | K456: 210013 | L456: Caxias | M456: -4.6288 | N456: -43.471 | O456: IBGE Localidades 2022 (Sede Municipal) | P456: OK | Q456: Não | R456: 1 | S456: 210030305 | T456: Aldeias Altas | U456: Aldeias Altas | V456: Sim | X456: -4.502896 | Y456: -43.383438 | Z456: Sim | AA456: -4.475839 | AB456: -43.341561
A457: 2100402 | B457: 210040 | C457: Altamira do Maranhão | D457: Altamira do Maranhão - MA | E457: MA | F457: 21 | G457: Maranhão | H457: Nordeste | I457: 2102 | J457: Santa Inês - Bacabal | K457: 210010 | L457: Bacabal | M457: -4.167 | N457: -45.4648 | O457: IBGE Localidades 2022 (Sede Municipal) | P457: OK | Q457: Não | R457: 1 | S457: 210040205 | T457: Altamira do Maranhão | U457: Altamira do Maranhão | V457: Sim | X457: -4.167103 | Y457: -45.502755 | Z457: Sim | AA457: -4.190837 | AB457: -45.506328
A458: 2100436 | B458: 210043 | C458: Alto Alegre do Maranhão | D458: Alto Alegre do Maranhão - MA | E458: MA | F458: 21 | G458: Maranhão | H458: Nordeste | I458: 2102 | J458: Santa Inês - Bacabal | K458: 210010 | L458: Bacabal | M458: -4.2096 | N458: -44.444 | O458: IBGE Localidades 2022 (Sede Municipal) | P458: OK | Q458: Não | R458: 1 | S458: 210043605 | T458: Alto Alegre do Maranhão | U458: Alto Alegre do Maranhão | V458: Sim | X458: -4.210631 | Y458: -44.395852 | Z458: Sim | AA458: -4.200308 | AB458: -44.400824
A459: 2100477 | B459: 210047 | C459: Alto Alegre do Pindaré | D459: Alto Alegre do Pindaré - MA | E459: MA | F459: 21 | G459: Maranhão | H459: Nordeste | I459: 2102 | J459: Santa Inês - Bacabal | K459: 210009 | L459: Santa Inês | M459: -3.6661 | N459: -45.8447 | O459: IBGE Localidades 2022 (Sede Municipal) | P459: OK | Q459: Não | R459: 1 | S459: 210047705 | T459: Alto Alegre do Pindaré | U459: Alto Alegre do Pindaré | V459: Sim | X459: -3.870326 | Y459: -46.001721 | Z459: Sim | AA459: -3.849203 | AB459: -46.031362
A460: 2100501 | B460: 210050 | C460: Alto Parnaíba | D460: Alto Parnaíba - MA | E460: MA | F460: 21 | G460: Maranhão | H460: Nordeste | I460: 2105 | J460: Imperatriz | K460: 210022 | L460: Balsas | M460: -9.1118 | N460: -45.9333 | O460: IBGE Localidades 2022 (Sede Municipal) | P460: OK | Q460: Não | R460: 2 | S460: 210050105 | T460: Alto Parnaíba | U460: Alto Parnaíba; Curupá | V460: Sim | X460: -9.508134 | Y460: -46.213351 | Z460: Sim | AA460: -9.280689 | AB460: -46.263962
A461: 2100550 | B461: 210055 | C461: Amapá do Maranhão | D461: Amapá do Maranhão - MA | E461: MA | F461: 21 | G461: Maranhão | H461: Nordeste | I461: 2102 | J461: Santa Inês - Bacabal | K461: 210011 | L461: Governador Nunes Freire | M461: -1.6749 | N461: -46.0099 | O461: IBGE Localidades 2022 (Sede Municipal) | P461: OK | Q461: Não | R461: 1 | S461: 210055005 | T461: Amapá do Maranhão | U461: Amapá do Maranhão | V461: Sim | X461: -1.672946 | Y461: -45.949824 | Z461: Sim | AA461: -1.701815 | AB461: -45.952603
A462: 2100600 | B462: 210060 | C462: Amarante do Maranhão | D462: Amarante do Maranhão - MA | E462: MA | F462: 21 | G462: Maranhão | H462: Nordeste | I462: 2105 | J462: Imperatriz | K462: 210019 | L462: Imperatriz | M462: -5.569 | N462: -46.7471 | O462: IBGE Localidades 2022 (Sede Municipal) | P462: OK | Q462: Não | R462: 1 | S462: 210060005 | T462: Amarante do Maranhão | U462: Amarante do Maranhão | V462: Sim | X462: -5.278224 | Y462: -46.582004 | Z462: Sim | AA462: -5.448756 | AB462: -46.616703
A463: 2100709 | B463: 210070 | C463: Anajatuba | D463: Anajatuba - MA | E463: MA | F463: 21 | G463: Maranhão | H463: Nordeste | I463: 2101 | J463: São Luís | K463: 210004 | L463: Itapecuru Mirim | M463: -3.2656 | N463: -44.6178 | O463: IBGE Localidades 2022 (Sede Municipal) | P463: OK | Q463: Não | R463: 2 | S463: 210070905 | T463: Anajatuba | U463: Anajatuba; Porto das Gabarras | V463: Sim | X463: -3.255633 | Y463: -44.599232 | Z463: Sim | AA463: -3.274351 | AB463: -44.612975
...

Sheet Distritos
A1: Código Distrito | B1: Distrito | C1: Distrito-Sede | D1: Código IBGE | E1: Município | F1: Município - UF | G1: UF | H1: Código UF | I1: Estado | J1: Região | K1: Código Região Intermediária | L1: Região Geográfica Intermediária | M1: Código Região Imediata | N1: Região Geográfica Imediata | O1: Latitude Município | P1: Longitude Município | Q1: Latitude Distrito | R1: Longitude Distrito | S1: Fonte Coordenada Distrito | T1: Observação
A2: 110001505 | B2: Alta Floresta D'Oeste | C2: Sim | D2: 1100015 | E2: Alta Floresta D'Oeste | F2: Alta Floresta D'Oeste - RO | G2: RO | H2: 11 | I2: Rondônia | J2: Norte | K2: 1102 | L2: Ji-Paraná | M2: 110005 | N2: Cacoal | O2: -11.933 | P2: -62.0037 | Q2: -11.933 | R2: -62.0037 | S2: IBGE Localidades 2022 (Sede Municipal) — sede municipal
A3: 110001515 | B3: Filadélfia d'Oeste | C3: Não | D3: 1100015 | E3: Alta Floresta D'Oeste | F3: Alta Floresta D'Oeste - RO | G3: RO | H3: 11 | I3: Rondônia | J3: Norte | K3: 1102 | L3: Ji-Paraná | M3: 110005 | N3: Cacoal | O3: -11.933 | P3: -62.0037 | Q3: -12.437239 | R3: -62.043898 | S3: IBGE Localidades 2010 (Vila)
A4: 110001520 | B4: Izidolândia | C4: Não | D4: 1100015 | E4: Alta Floresta D'Oeste | F4: Alta Floresta D'Oeste - RO | G4: RO | H4: 11 | I4: Rondônia | J4: Norte | K4: 1102 | L4: Ji-Paraná | M4: 110005 | N4: Cacoal | O4: -11.933 | P4: -62.0037 | Q4: -12.601415 | R4: -62.175549 | S4: IBGE Localidades 2010 (Vila)
A5: 110001525 | B5: Nova Gease d'Oeste | C5: Não | D5: 1100015 | E5: Alta Floresta D'Oeste | F5: Alta Floresta D'Oeste - RO | G5: RO | H5: 11 | I5: Rondônia | J5: Norte | K5: 1102 | L5: Ji-Paraná | M5: 110005 | N5: Cacoal | O5: -11.933 | P5: -62.0037 | Q5: -11.919792 | R5: -62.31865 | S5: IBGE Localidades 2010 (Vila)
A6: 110001530 | B6: Rolim de Moura do Guaporé | C6: Não | D6: 1100015 | E6: Alta Floresta D'Oeste | F6: Alta Floresta D'Oeste - RO | G6: RO | H6: 11 | I6: Rondônia | J6: Norte | K6: 1102 | L6: Ji-Paraná | M6: 110005 | N6: Cacoal | O6: -11.933 | P6: -62.0037 | Q6: -13.079806 | R6: -62.276812 | S6: IBGE Localidades 2010 (Vila)
A7: 110001535 | B7: Santo Antônio d'Oeste | C7: Não | D7: 1100015 | E7: Alta Floresta D'Oeste | F7: Alta Floresta D'Oeste - RO | G7: RO | H7: 11 | I7: Rondônia | J7: Norte | K7: 1102 | L7: Ji-Paraná | M7: 110005 | N7: Cacoal | O7: -11.933 | P7: -62.0037 | Q7: -12.089439 | R7: -62.104428 | S7: IBGE Localidades 2010 (Vila)
A8: 110002305 | B8: Ariquemes | C8: Sim | D8: 1100023 | E8: Ariquemes | F8: Ariquemes - RO | G8: RO | H8: 11 | I8: Rondônia | J8: Norte | K8: 1101 | L8: Porto Velho | M8: 110002 | N8: Ariquemes | O8: -9.912 | P8: -63.0338 | Q8: -9.912 | R8: -63.0338 | S8: IBGE Localidades 2022 (Sede Municipal) — sede municipal
A9: 110003105 | B9: Cabixi | C9: Sim | D9: 1100031 | E9: Cabixi | F9: Cabixi - RO | G9: RO | H9: 11 | I9: Rondônia | J9: Norte | K9: 1102 | L9: Ji-Paraná | M9: 110006 | N9: Vilhena | O9: -13.4945 | P9: -60.5429 | Q9: -13.4945 | R9: -60.5429 | S9: IBGE Localidades 2022 (Sede Municipal) — sede municipal
A10: 110004905 | B10: Cacoal | C10: Sim | D10: 1100049 | E10: Cacoal | F10: Cacoal - RO | G10: RO | H10: 11 | I10: Rondônia | J10: Norte | K10: 1102 | L10: Ji-Paraná | M10: 110005 | N10: Cacoal | O10: -11.4356 | P10: -61.4512 | Q10: -11.4356 | R10: -61.4512 | S10: IBGE Localidades 2022 (Sede Municipal) — sede municipal
A11: 110004910 | B11: Riozinho | C11: Não | D11: 1100049 | E11: Cacoal | F11: Cacoal - RO | G11: RO | H11: 11 | I11: Rondônia | J11: Norte | K11: 1102 | L11: Ji-Paraná | M11: 110005 | N11: Cacoal | O11: -11.4356 | P11: -61.4512 | Q11: -11.51061 | R11: -61.359715 | S11: IBGE Localidades 2010 (Vila)
A12: 110004915 | B12: Divinópolis | C12: Não | D12: 1100049 | E12: Cacoal | F12: Cacoal - RO | G12: RO | H12: 11 | I12: Rondônia | J12: Norte | K12: 1102 | L12: Ji-Paraná | M12: 110005 | N12: Cacoal | O12: -11.4356 | P12: -61.4512 | S12: Sem ponto oficial de sede distrital | T12: Distrito criado após 2010 (sem ponto IBGE 2022 nos arquivos disponíveis, que cobrem só GO, SC, AM, AP, PA e RR).
A13: 110005605 | B13: Cerejeiras | C13: Sim | D13: 1100056 | E13: Cerejeiras | F13: Cerejeiras - RO | G13: RO | H13: 11 | I13: Rondônia | J13: Norte | K13: 1102 | L13: Ji-Paraná | M13: 110006 | N13: Vilhena | O13: -13.1864 | P13: -60.8117 | Q13: -13.1864 | R13: -60.8117 | S13: IBGE Localidades 2022 (Sede Municipal) — sede municipal
A14: 110006405 | B14: Colorado do Oeste | C14: Sim | D14: 1100064 | E14: Colorado do Oeste | F14: Colorado do Oeste - RO | G14: RO | H14: 11 | I14: Rondônia | J14: Norte | K14: 1102 | L14: Ji-Paraná | M14: 110006 | N14: Vilhena | O14: -13.1212 | P14: -60.5437 | Q14: -13.1212 | R14: -60.5437 | S14: IBGE Localidades 2022 (Sede Municipal) — sede municipal
A15: 110007205 | B15: Corumbiara | C15: Sim | D15: 1100072 | E15: Corumbiara | F15: Corumbiara - RO | G15: RO | H15: 11 | I15: Rondônia | J15: Norte | K15: 1102 | L15: Ji-Paraná | M15: 110006 | N15: Vilhena | O15: -12.99752 | P15: -60.948701 | Q15: -12.99752 | R15: -60.948701 | S15: IBGE Localidades 2010 (Cidade) — sede municipal
A16: 110008005 | B16: Costa Marques | C16: Sim | D16: 1100080 | E16: Costa Marques | F16: Costa Marques - RO | G16: RO | H16: 11 | I16: Rondônia | J16: Norte | K16: 1102 | L16: Ji-Paraná | M16: 110004 | N16: Ji-Paraná | O16: -12.4384 | P16: -64.2292 | Q16: -12.4384 | R16: -64.2292 | S16: IBGE Localidades 2022 (Sede Municipal) — sede municipal
A17: 110008015 | B17: Real Forte Príncipe da Beira | C17: Não | D17: 1100080 | E17: Costa Marques | F17: Costa Marques - RO | G17: RO | H17: 11 | I17: Rondônia | J17: Norte | K17: 1102 | L17: Ji-Paraná | M17: 110004 | N17: Ji-Paraná | O17: -12.4384 | P17: -64.2292 | Q17: -12.42668 | R17: -64.42086 | S17: IBGE Localidades 2010 (Vila) | T17: Grafia na fonte do ponto: Príncipe da Beira.
A18: 110008035 | B18: São Domingos do Guaporé | C18: Não | D18: 1100080 | E18: Costa Marques | F18: Costa Marques - RO | G18: RO | H18: 11 | I18: Rondônia | J18: Norte | K18: 1102 | L18: Ji-Paraná | M18: 110004 | N18: Ji-Paraná | O18: -12.4384 | P18: -64.2292 | S18: Sem ponto oficial de sede distrital | T18: Distrito criado após 2010 (sem ponto IBGE 2022 nos arquivos disponíveis, que cobrem só GO, SC, AM, AP, PA e RR).
A19: 110009805 | B19: Espigão D'Oeste | C19: Sim | D19: 1100098 | E19: Espigão D'Oeste | F19: Espigão D'Oeste - RO | G19: RO | H19: 11 | I19: Rondônia | J19: Norte | K19: 1102 | L19: Ji-Paraná | M19: 110005 | N19: Cacoal | O19: -11.5347 | P19: -61.0164 | Q19: -11.5347 | R19: -61.0164 | S19: IBGE Localidades 2022 (Sede Municipal) — sede municipal
A20: 110009810 | B20: Boa Vista do Pacarana | C20: Não | D20: 1100098 | E20: Espigão D'Oeste | F20: Espigão D'Oeste - RO | G20: RO | H20: 11 | I20: Rondônia | J20: Norte | K20: 1102 | L20: Ji-Paraná | M20: 110005 | N20: Cacoal | O20: -11.5347 | P20: -61.0164 | Q20: -11.003153 | R20: -60.846795 | S20: IBGE Localidades 2010 (Vila)
A21: 110009812 | B21: Novo Paraíso | C21: Não | D21: 1100098 | E21: Espigão D'Oeste | F21: Espigão D'Oeste - RO | G21: RO | H21: 11 | I21: Rondônia | J21: Norte | K21: 1102 | L21: Ji-Paraná | M21: 110005 | N21: Cacoal | O21: -11.5347 | P21: -61.0164 | Q21: -11.461613 | R21: -60.923816 | S21: IBGE Localidades 2010 (Vila)
A22: 110009815 | B22: Flor da Serra | C22: Não | D22: 1100098 | E22: Espigão D'Oeste | F22: Espigão D'Oeste - RO | G22: RO | H22: 11 | I22: Rondônia | J22: Norte | K22: 1102 | L22: Ji-Paraná | M22: 110005 | N22: Cacoal | O22: -11.5347 | P22: -61.0164 | Q22: -11.405385 | R22: -60.751286 | S22: IBGE Localidades 2010 (Vila)
A23: 110009818 | B23: Nova Esperança | C23: Não | D23: 1100098 | E23: Espigão D'Oeste | F23: Espigão D'Oeste - RO | G23: RO | H23: 11 | I23: Rondônia | J23: Norte | K23: 1102 | L23: Ji-Paraná | M23: 110005 | N23: Cacoal | O23: -11.5347 | P23: -61.0164 | Q23: -11.50379 | R23: -61.132056 | S23: IBGE Localidades 2010 (Vila)
A24: 110010605 | B24: Guajará-Mirim | C24: Sim | D24: 1100106 | E24: Guajará-Mirim | F24: Guajará-Mirim - RO | G24: RO | H24: 11 | I24: Rondônia | J24: Norte | K24: 1101 | L24: Porto Velho | M24: 110001 | N24: Porto Velho | O24: -10.7871 | P24: -65.3401 | Q24: -10.7871 | R24: -65.3401 | S24: IBGE Localidades 2022 (Sede Municipal) — sede municipal
A25: 110010612 | B25: Iata | C25: Não | D25: 1100106 | E25: Guajará-Mirim | F25: Guajará-Mirim - RO | G25: RO | H25: 11 | I25: Rondônia | J25: Norte | K25: 1101 | L25: Porto Velho | M25: 110001 | N25: Porto Velho | O25: -10.7871 | P25: -65.3401 | Q25: -10.589854 | R25: -65.382828 | S25: IBGE Localidades 2010 (Vila)
A26: 110010622 | B26: Surpresa | C26: Não | D26: 1100106 | E26: Guajará-Mirim | F26: Guajará-Mirim - RO | G26: RO | H26: 11 | I26: Rondônia | J26: Norte | K26: 1101 | L26: Porto Velho | M26: 110001 | N26: Porto Velho | O26: -10.7871 | P26: -65.3401 | Q26: -11.88231 | R26: -65.021521 | S26: IBGE Localidades 2010 (Vila)
A27: 110011405 | B27: Jaru | C27: Sim | D27: 1100114 | E27: Jaru | F27: Jaru - RO | G27: RO | H27: 11 | I27: Rondônia | J27: Norte | K27: 1101 | L27: Porto Velho | M27: 110003 | N27: Jaru | O27: -10.4382 | P27: -62.4616 | Q27: -10.4382 | R27: -62.4616 | S27: IBGE Localidades 2022 (Sede Municipal) — sede municipal
A28: 110011410 | B28: Bom Jesus | C28: Não | D28: 1100114 | E28: Jaru | F28: Jaru - RO | G28: RO | H28: 11 | I28: Rondônia | J28: Norte | K28: 1101 | L28: Porto Velho | M28: 110003 | N28: Jaru | O28: -10.4382 | P28: -62.4616 | Q28: -10.315466 | R28: -62.24075 | S28: IBGE Localidades 2010 (Vila)
A29: 110011420 | B29: Santa Cruz da Serra | C29: Não | D29: 1100114 | E29: Jaru | F29: Jaru - RO | G29: RO | H29: 11 | I29: Rondônia | J29: Norte | K29: 1101 | L29: Porto Velho | M29: 110003 | N29: Jaru | O29: -10.4382 | P29: -62.4616 | Q29: -10.651474 | R29: -62.587104 | S29: IBGE Localidades 2010 (Vila)
A30: 110011425 | B30: Tarilândia | C30: Não | D30: 1100114 | E30: Jaru | F30: Jaru - RO | G30: RO | H30: 11 | I30: Rondônia | J30: Norte | K30: 1101 | L30: Porto Velho | M30: 110003 | N30: Jaru | O30: -10.4382 | P30: -62.4616 | Q30: -10.856914 | R30: -62.801313 | S30: IBGE Localidades 2010 (Vila)
... A42: 110018915 | B42: Marco Rondon | C42: Não | D42: 1100189 | E42: Pimenta Bueno | F42: Pimenta Bueno - RO | G42: RO | H42: 11 | I42: Rondônia | J42: Norte | K42: 1102 | L42: Ji-Paraná | M42: 110005 | N42: Cacoal | O42: -11.6707 | P42: -61.1888 | Q42: -12.013427 | R42: -60.860058 | S42: IBGE Localidades 2010 (Vila)
A43: 110018920 | B43: Itaporanga | C43: Não | D43: 1100189 | E43: Pimenta Bueno | F43: Pimenta Bueno - RO | G43: RO | H43: 11 | I43: Rondônia | J43: Norte | K43: 1102 | L43: Ji-Paraná | M43: 110005 | N43: Cacoal | O43: -11.6707 | P43: -61.1888 | S43: Sem ponto oficial de sede distrital | T43: Distrito criado após 2010 (sem ponto IBGE 2022 nos arquivos disponíveis, que cobrem só GO, SC, AM, AP, PA e RR).
A44: 110020505 | B44: Porto Velho | C44: Sim | D44: 1100205 | E44: Porto Velho | F44: Porto Velho - RO | G44: RO | H44: 11 | I44: Rondônia | J44: Norte | K44: 1101 | L44: Porto Velho | M44: 110001 | N44: Porto Velho | O44: -8.768892 | P44: -63.831446 | Q44: -8.768892 | R44: -63.831446 | S44: IBGE Localidades 2010 (Cidade) — sede municipal — a conferir | T44: Sede municipal marcada 'a conferir' — ver a observação na aba Municipios.
A45: 110020510 | B45: Abunã | C45: Não | D45: 1100205 | E45: Porto Velho | F45: Porto Velho - RO | G45: RO | H45: 11 | I45: Rondônia | J45: Norte | K45: 1101 | L45: Porto Velho | M45: 110001 | N45: Porto Velho | O45: -8.768892 | P45: -63.831446 | Q45: -9.685618 | R45: -65.371506 | S45: IBGE Localidades 2010 (Vila)
A46: 110020515 | B46: Calama | C46: Não | D46: 1100205 | E46: Porto Velho | F46: Porto Velho - RO | G46: RO | H46: 11 | I46: Rondônia | J46: Norte | K46: 1101 | L46: Porto Velho | M46: 110001 | N46: Porto Velho | O46: -8.768892 | P46: -63.831446 | Q46: -8.025412 | R46: -62.871889 | S46: IBGE Localidades 2010 (Vila)
A47: 110020516 | B47: Demarcação | C47: Não | D47: 1100205 | E47: Porto Velho | F47: Porto Velho - RO | G47: RO | H47: 11 | I47: Rondônia | J47: Norte | K47: 1101 | L47: Porto Velho | M47: 110001 | N47: Porto Velho | O47: -8.768892 | P47: -63.831446 | Q47: -8.166927 | R47: -62.777883 | S47: IBGE Localidades 2010 (Vila)
A48: 110020517 | B48: Extrema | C48: Não | D48: 1100205 | E48: Porto Velho | F48: Porto Velho - RO | G48: RO | H48: 11 | I48: Rondônia | J48: Norte | K48: 1101 | L48: Porto Velho | M48: 110001 | N48: Porto Velho | O48: -8.768892 | P48: -63.831446 | Q48: -9.77417 | R48: -66.35955 | S48: IBGE Localidades 2010 (Vila)
A49: 110020518 | B49: Fortaleza do Abunã | C49: Não | D49: 1100205 | E49: Porto Velho | F49: Porto Velho - RO | G49: RO | H49: 11 | I49: Rondônia | J49: Norte | K49: 1101 | L49: Porto Velho | M49: 110001 | N49: Porto Velho | O49: -8.768892 | P49: -63.831446 | Q49: -9.773464 | R49: -65.52162 | S49: IBGE Localidades 2010 (Vila)
A50: 110020520 | B50: Jaci Paraná | C50: Não | D50: 1100205 | E50: Porto Velho | F50: Porto Velho - RO | G50: RO | H50: 11 | I50: Rondônia | J50: Norte | K50: 1101 | L50: Porto Velho | M50: 110001 | N50: Porto Velho | O50: -8.768892 | P50: -63.831446 | Q50: -9.252668 | R50: -64.395109 | S50: IBGE Localidades 2010 (Vila)
A51: 110020525 | B51: Mutum Paraná | C51: Não | D51: 1100205 | E51: Porto Velho | F51: Porto Velho - RO | G51: RO | H51: 11 | I51: Rondônia | J51: Norte | K51: 1101 | L51: Porto Velho | M51: 110001 | N51: Porto Velho | O51: -8.768892 | P51: -63.831446 | Q51: -9.618672 | R51: -64.942707 | S51: IBGE Localidades 2010 (Vila)
A52: 110020530 | B52: Nazaré | C52: Não | D52: 1100205 | E52: Porto Velho | F52: Porto Velho - RO | G52: RO | H52: 11 | I52: Rondônia | J52: Norte | K52: 1101 | L52: Porto Velho | M52: 110001 | N52: Porto Velho | O52: -8.768892 | P52: -63.831446 | Q52: -8.164217 | R52: -63.322309 | S52: IBGE Localidades 2010 (Vila)
A53: 110020535 | B53: Nova Califórnia | C53: Não | D53: 1100205 | E53: Porto Velho | F53: Porto Velho - RO | G53: RO | H53: 11 | I53: Rondônia | J53: Norte | K53: 1101 | L53: Porto Velho | M53: 110001 | N53: Porto Velho | O53: -8.768892 | P53: -63.831446 | Q53: -9.760173 | R53: -66.609748 | S53: IBGE Localidades 2010 (Vila)
A54: 110020540 | B54: São Carlos | C54: Não | D54: 1100205 | E54: Porto Velho | F54: Porto Velho - RO | G54: RO | H54: 11 | I54: Rondônia | J54: Norte | K54: 1101 | L54: Porto Velho | M54: 110001 | N54: Porto Velho | O54: -8.768892 | P54: -63.831446 | Q54: -8.43758 | R54: -63.52996 | S54: IBGE Localidades 2010 (Vila)
A55: 110020545 | B55: Vista Alegre do Abunã | C55: Não | D55: 1100205 | E55: Porto Velho | F55: Porto Velho - RO | G55: RO | H55: 11 | I55: Rondônia | J55: Norte | K55: 1101 | L55: Porto Velho | M55: 110001 | N55: Porto Velho | O55: -8.768892 | P55: -63.831446 | Q55: -9.656832 | R55: -65.729329 | S55: IBGE Localidades 2010 (Vila)
A56: 110025405 | B56: Presidente Médici | C56: Sim | D56: 1100254 | E56: Presidente Médici | F56: Presidente Médici - RO | G56: RO | H56: 11 | I56: Rondônia | J56: Norte | K56: 1102 | L56: Ji-Paraná | M56: 110004 | N56: Ji-Paraná | O56: -11.1698 | P56: -61.9041 | Q56: -11.1698 | R56: -61.9041 | S56: IBGE Localidades 2022 (Sede Municipal) — sede municipal
... A72: 110033820 | B72: Palmeiras | C72: Não | D72: 1100338 | E72: Nova Mamoré | F72: Nova Mamoré - RO | G72: RO | H72: 11 | I72: Rondônia | J72: Norte | K72: 1101 | L72: Porto Velho | M72: 110001 | N72: Porto Velho | O72: -10.4174 | P72: -65.3321 | Q72: -10.377768 | R72: -64.973524 | S72: IBGE Localidades 2010 (Vila)
A73: 110033825 | B73: Nova Marechal Rondon | C73: Não | D73: 1100338 | E73: Nova Mamoré | F73: Nova Mamoré - RO | G73: RO | H73: 11 | I73: Rondônia | J73: Norte | K73: 1101 | L73: Porto Velho | M73: 110001 | N73: Porto Velho | O73: -10.4174 | P73: -65.3321 | S73: Sem ponto oficial de sede distrital | T73: Distrito criado após 2010 (sem ponto IBGE 2022 nos arquivos disponíveis, que cobrem só GO, SC, AM, AP, PA e RR).
A74: 110034605 | B74: Alvorada D'Oeste | C74: Sim | D74: 1100346 | E74: Alvorada D'Oeste | F74: Alvorada D'Oeste - RO | G74: RO | H74: 11 | I74: Rondônia | J74: Norte | K74: 1102 | L74: Ji-Paraná | M74: 110004 | N74: Ji-Paraná | O74: -11.3547 | P74: -62.2845 | Q74: -11.3547 | R74: -62.2845 | S74: IBGE Localidades 2022 (Sede Municipal) — sede municipal
A75: 110034625 | B75: Tancredópolis | C75: Não | D75: 1100346 | E75: Alvorada D'Oeste | F75: Alvorada D'Oeste - RO | G75: RO | H75: 11 | I75: Rondônia | J75: Norte | K75: 1102 | L75: Ji-Paraná | M75: 110004 | N75: Ji-Paraná | O75: -11.3547 | P75: -62.2845 | Q75: -11.18757 | R75: -62.175487 | S75: IBGE Localidades 2010 (Vila)
A76: 110034630 | B76: Terra Boa | C76: Não | D76: 1100346 | E76: Alvorada D'Oeste | F76: Alvorada D'Oeste - RO | G76: RO | H76: 11 | I76: Rondônia | J76: Norte | K76: 1102 | L76: Ji-Paraná | M76: 110004 | N76: Ji-Paraná | O76: -11.3547 | P76: -62.2845 | Q76: -11.509905 | R76: -62.460043 | S76: IBGE Localidades 2010 (Vila)
A77: 110037905 | B77: Alto Alegre dos Parecis | C77: Sim | D77: 1100379 | E77: Alto Alegre dos Parecis | F77: Alto Alegre dos Parecis - RO | G77: RO | H77: 11 | I77: Rondônia | J77: Norte | K77: 1102 | L77: Ji-Paraná | M77: 110005 | N77: Cacoal | O77: -12.134 | P77: -61.8587 | Q77: -12.134 | R77: -61.8587 | S77: IBGE Localidades 2022 (Sede Municipal) — sede municipal
A78: 110040305 | B78: Alto Paraíso | C78: Sim | D78: 1100403 | E78: Alto Paraíso | F78: Alto Paraíso - RO | G78: RO | H78: 11 | I78: Rondônia | J78: Norte | K78: 1101 | L78: Porto Velho | M78: 110002 | N78: Ariquemes | O78: -9.7201 | P78: -63.3179 | Q78: -9.7201 | R78: -63.3179 | S78: IBGE Localidades 2022 (Sede Municipal) — sede municipal
A79: 110045205 | B79: Buritis | C79: Sim | D79: 1100452 | E79: Buritis | F79: Buritis - RO | G79: RO | H79: 11 | I79: Rondônia | J79: Norte | K79: 1101 | L79: Porto Velho | M79: 110002 | N79: Ariquemes | O79: -10.2025 | P79: -63.8349 | Q79: -10.2025 | R79: -63.8349 | S79: IBGE Localidades 2022 (Sede Municipal) — sede municipal
A80: 110050205 | B80: Novo Horizonte do Oeste | C80: Sim | D80: 1100502 | E80: Novo Horizonte do Oeste | F80: Novo Horizonte do Oeste - RO | G80: RO | H80: 11 | I80: Rondônia | J80: Norte | K80: 1102 | L80: Ji-Paraná | M80: 110005 | N80: Cacoal | O80: -11.7065 | P80: -62.0001 | Q80: -11.7065 | R80: -62.0001 | S80: IBGE Localidades 2022 (Sede Municipal) — sede municipal
A81: 110050210 | B81: Migrantinópolis | C81: Não | D81: 1100502 | E81: Novo Horizonte do Oeste | F81: Novo Horizonte do Oeste - RO | G81: RO | H81: 11 | I81: Rondônia | J81: Norte | K81: 1102 | L81: Ji-Paraná | M81: 110005 | N81: Cacoal | O81: -11.7065 | P81: -62.0001 | Q81: -11.731129 | R81: -62.144513 | S81: IBGE Localidades 2010 (localidade homônima: Povoado)
A82: 110060105 | B82: Cacaulândia | C82: Sim | D82: 1100601 | E82: Cacaulândia | F82: Cacaulândia - RO | G82: RO | H82: 11 | I82: Rondônia | J82: Norte | K82: 1101 | L82: Porto Velho | M82: 110002 | N82: Ariquemes | O82: -10.3423 | P82: -62.9011 | Q82: -10.3423 | R82: -62.9011 | S82: IBGE Localidades 2022 (Sede Municipal) — sede municipal
A83: 110070005 | B83: Campo Novo de Rondônia | C83: Sim | D83: 1100700 | E83: Campo Novo de Rondônia | F83: Campo Novo de Rondônia - RO | G83: RO | H83: 11 | I83: Rondônia | J83: Norte | K83: 1101 | L83: Porto Velho | M83: 110002 | N83: Ariquemes | O83: -10.568 | P83: -63.6201 | Q83: -10.568 | R83: -63.6201 | S83: IBGE Localidades 2022 (Sede Municipal) — sede municipal
A84: 110080905 | B84: Candeias do Jamari | C84: Sim | D84: 1100809 | E84: Candeias do Jamari | F84: Candeias do Jamari - RO | G84: RO | H84: 11 | I84: Rondônia | J84: Norte | K84: 1101 | L84: Porto Velho | M84: 110001 | N84: Porto Velho | O84: -8.7966 | P84: -63.7006 | Q84: -8.7966 | R84: -63.7006 | S84: IBGE Localidades 2022 (Sede Municipal) — sede municipal
A85: 110080920 | B85: Rio Preto do Candeias | C85: Não | D85: 1100809 | E85: Candeias do Jamari | F85: Candeias do Jamari - RO | G85: RO | H85: 11 | I85: Rondônia | J85: Norte | K85: 1101 | L85: Porto Velho | M85: 110001 | N85: Porto Velho | O85: -8.7966 | P85: -63.7006 | Q85: -9.281579 | R85: -63.46526 | S85: IBGE Localidades 2010 (Vila)
... A101: 110149210 | B101: Porto Murtinho | C101: Não | D101: 1101492 | E101: São Francisco do Guaporé | F101: São Francisco do Guaporé - RO | G101: RO | H101: 11 | I101: Rondônia | J101: Norte | K101: 1102 | L101: Ji-Paraná | M101: 110004 | N101: Ji-Paraná | O101: -12.0794 | P101: -63.5677 | Q101: -12.293498 | R101: -63.397729 | S101: IBGE Localidades 2010 (localidade homônima: Povoado)
A102: 110149215 | B102: Pedras Negras | C102: Não | D102: 1101492 | E102: São Francisco do Guaporé | F102: São Francisco do Guaporé - RO | G102: RO | H102: 11 | I102: Rondônia | J102: Norte | K102: 1102 | L102: Ji-Paraná | M102: 110004 | N102: Ji-Paraná | O102: -12.0794 | P102: -63.5677 | S102: Sem ponto oficial de sede distrital | T102: Distrito criado após 2010 (sem ponto IBGE 2022 nos arquivos disponíveis, que cobrem só GO, SC, AM, AP, PA e RR).
A103: 110149220 | B103: Santo Antônio do Guaporé | C103: Não | D103: 1101492 | E103: São Francisco do Guaporé | F103: São Francisco do Guaporé - RO | G103: RO | H103: 11 | I103: Rondônia | J103: Norte | K103: 1102 | L103: Ji-Paraná | M103: 110004 | N103: Ji-Paraná | O103: -12.0794 | P103: -63.5677 | S103: Sem ponto oficial de sede distrital | T103: Distrito criado após 2010 (sem ponto IBGE 2022 nos arquivos disponíveis, que cobrem só GO, SC, AM, AP, PA e RR).
A104: 110150005 | B104: Seringueiras | C104: Sim | D104: 1101500 | E104: Seringueiras | F104: Seringueiras - RO | G104: RO | H104: 11 | I104: Rondônia | J104: Norte | K104: 1102 | L104: Ji-Paraná | M104: 110004 | N104: Ji-Paraná | O104: -11.7714 | P104: -63.0369 | Q104: -11.7714 | R104: -63.0369 | S104: IBGE Localidades 2022 (Sede Municipal) — sede municipal
A105: 110155905 | B105: Teixeirópolis | C105: Sim | D105: 1101559 | E105: Teixeirópolis | F105: Teixeirópolis - RO | G105: RO | H105: 11 | I105: Rondônia | J105: Norte | K105: 1102 | L105: Ji-Paraná | M105: 110004 | N105: Ji-Paraná | O105: -10.9336 | P105: -62.2553 | Q105: -10.9336 | R105: -62.2553 | S105: IBGE Localidades 2022 (Sede Municipal) — sede municipal
A106: 110160905 | B106: Theobroma | C106: Sim | D106: 1101609 | E106: Theobroma | F106: Theobroma - RO | G106: RO | H106: 11 | I106: Rondônia | J106: Norte | K106: 1101 | L106: Porto Velho | M106: 110003 | N106: Jaru | O106: -10.2459 | P106: -62.3495 | Q106: -10.2459 | R106: -62.3495 | S106: IBGE Localidades 2022 (Sede Municipal) — sede municipal
A107: 110170805 | B107: Urupá | C107: Sim | D107: 1101708 | E107: Urupá | F107: Urupá - RO | G107: RO | H107: 11 | I107: Rondônia | J107: Norte | K107: 1102 | L107: Ji-Paraná | M107: 110004 | N107: Ji-Paraná | O107: -11.1215 | P107: -62.3756 | Q107: -11.1215 | R107: -62.3756 | S107: IBGE Localidades 2022 (Sede Municipal) — sede municipal
A108: 110175705 | B108: Vale do Anari | C108: Sim | D108: 1101757 | E108: Vale do Anari | F108: Vale do Anari - RO | G108: RO | H108: 11 | I108: Rondônia | J108: Norte | K108: 1101 | L108: Porto Velho | M108: 110003 | N108: Jaru | O108: -9.8557 | P108: -62.1762 | Q108: -9.8557 | R108: -62.1762 | S108: IBGE Localidades 2022 (Sede Municipal) — sede municipal
A109: 110180705 | B109: Vale do Paraíso | C109: Sim | D109: 1101807 | E109: Vale do Paraíso | F109: Vale do Paraíso - RO | G109: RO | H109: 11 | I109: Rondônia | J109: Norte | K109: 1102 | L109: Ji-Paraná | M109: 110004 | N109: Ji-Paraná | O109: -10.427 | P109: -62.1332 | Q109: -10.427 | R109: -62.1332 | S109: IBGE Localidades 2022 (Sede Municipal) — sede municipal
A110: 120001305 | B110: Acrelândia | C110: Sim | D110: 1200013 | E110: Acrelândia | F110: Acrelândia - AC | G110: AC | H110: 12 | I110: Acre | J110: Norte | K110: 1201 | L110: Rio Branco | M110: 120001 | N110: Rio Branco | O110: -10.0774 | P110: -67.0504 | Q110: -10.0774 | R110: -67.0504 | S110: IBGE Localidades 2022 (Sede Municipal) — sede municipal
A111: 120005405 | B111: Assis Brasil | C111: Sim | D111: 1200054 | E111: Assis Brasil | F111: Assis Brasil - AC | G111: AC | H111: 12 | I111: Acre | J111: Norte | K111: 1201 | L111: Rio Branco | M111: 120002 | N111: Brasiléia | O111: -10.9401 | P111: -69.5672 | Q111: -10.9401 | R111: -69.5672 | S111: IBGE Localidades 2022 (Sede Municipal) — sede municipal
A112: 120010405 | B112: Brasiléia | C112: Sim | D112: 1200104 | E112: Brasiléia | F112: Brasiléia - AC | G112: AC | H112: 12 | I112: Acre | J112: Norte | K112: 1201 | L112: Rio Branco | M112: 120002 | N112: Brasiléia | O112: -11.0154 | P112: -68.75 | Q112: -11.0154 | R112: -68.75 | S112: IBGE Localidades 2022 (Sede Municipal) — sede municipal
A113: 120013805 | B113: Bujari | C113: Sim | D113: 1200138 | E113: Bujari | F113: Bujari - AC | G113: AC | H113: 12 | I113: Acre | J113: Norte | K113: 1201 | L113: Rio Branco | M113: 120001 | N113: Rio Branco | O113: -9.8311 | P113: -67.9524 | Q113: -9.8311 | R113: -67.9524 | S113: IBGE Localidades 2022 (Sede Municipal) — sede municipal
A114: 120017905 | B114: Capixaba | C114: Sim | D114: 1200179 | E114: Capixaba | F114: Capixaba - AC | G114: AC | H114: 12 | I114: Acre | J114: Norte | K114: 1201 | L114: Rio Branco | M114: 120001 | N114: Rio Branco | O114: -10.5722 | P114: -67.6753 | Q114: -10.5722 | R114: -67.6753 | S114: IBGE Localidades 2022 (Sede Municipal) — sede municipal
A115: 120020305 | B115: Cruzeiro do Sul | C115: Sim | D115: 1200203 | E115: Cruzeiro do Sul | F115: Cruzeiro do Sul - AC | G115: AC | H115: 12 | I115: Acre | J115: Norte | K115: 1202 | L115: Cruzeiro do Sul | M115: 120004 | N115: Cruzeiro do Sul | O115: -7.6345 | P115: -72.6665 | Q115: -7.6345 | R115: -72.6665 | S115: IBGE Localidades 2022 (Sede Municipal) — sede municipal
... A132: 120080705 | B132: Porto Acre | C132: Sim | D132: 1200807 | E132: Porto Acre | F132: Porto Acre - AC | G132: AC | H132: 12 | I132: Acre | J132: Norte | K132: 1201 | L132: Rio Branco | M132: 120001 | N132: Rio Branco | O132: -9.5898 | P132: -67.533 | Q132: -9.5898 | R132: -67.533 | S132: IBGE Localidades 2022 (Sede Municipal) — sede municipal
A133: 120080720 | B133: Vila do Caquetá | C133: Não | D133: 1200807 | E133: Porto Acre | F133: Porto Acre - AC | G133: AC | H133: 12 | I133: Acre | J133: Norte | K133: 1201 | L133: Rio Branco | M133: 120001 | N133: Rio Branco | O133: -9.5898 | P133: -67.533 | S133: Sem ponto oficial de sede distrital | T133: Distrito criado após 2010 (sem ponto IBGE 2022 nos arquivos disponíveis, que cobrem só GO, SC, AM, AP, PA e RR).
A134: 120080723 | B134: Vila do Incra | C134: Não | D134: 1200807 | E134: Porto Acre | F134: Porto Acre - AC | G134: AC | H134: 12 | I134: Acre | J134: Norte | K134: 1201 | L134: Rio Branco | M134: 120001 | N134: Rio Branco | O134: -9.5898 | P134: -67.533 | S134: Sem ponto oficial de sede distrital | T134: Distrito criado após 2010 (sem ponto IBGE 2022 nos arquivos disponíveis, que cobrem só GO, SC, AM, AP, PA e RR).
A135: 120080725 | B135: Vila do V | C135: Não | D135: 1200807 | E135: Porto Acre | F135: Porto Acre - AC | G135: AC | H135: 12 | I135: Acre | J135: Norte | K135: 1201 | L135: Rio Branco | M135: 120001 | N135: Rio Branco | O135: -9.5898 | P135: -67.533 | S135: Sem ponto oficial de sede distrital | T135: Distrito criado após 2010 (sem ponto IBGE 2022 nos arquivos disponíveis, que cobrem só GO, SC, AM, AP, PA e RR).
A136: 130002905 | B136: Alvarães | C136: Sim | D136: 1300029 | E136: Alvarães | F136: Alvarães - AM | G136: AM | H136: 13 | I136: Amazonas | J136: Norte | K136: 1302 | L136: Tefé | M136: 130005 | N136: Tefé | O136: -3.2128 | P136: -64.8077 | Q136: -3.2128 | R136: -64.8077 | S136: IBGE Localidades 2022 (Sede Municipal) — sede municipal
A137: 130006005 | B137: Amaturá | C137: Sim | D137: 1300060 | E137: Amaturá | F137: Amaturá - AM | G137: AM | H137: 13 | I137: Amazonas | J137: Norte | K137: 1302 | L137: Tefé | M137: 130006 | N137: Tabatinga | O137: -3.3618 | P137: -68.2 | Q137: -3.3618 | R137: -68.2 | S137: IBGE Localidades 2022 (Sede Municipal) — sede municipal
A138: 130008605 | B138: Anamã | C138: Sim | D138: 1300086 | E138: Anamã | F138: Anamã - AM | G138: AM | H138: 13 | I138: Amazonas | J138: Norte | K138: 1301 | L138: Manaus | M138: 130004 | N138: Manacapuru | O138: -3.577 | P138: -61.4055 | Q138: -3.577 | R138: -61.4055 | S138: IBGE Localidades 2022 (Sede Municipal) — sede municipal
A139: 130010205 | B139: Anori | C139: Sim | D139: 1300102 | E139: Anori | F139: Anori - AM | G139: AM | H139: 13 | I139: Amazonas | J139: Norte | K139: 1301 | L139: Manaus | M139: 130003 | N139: Coari | O139: -3.7486 | P139: -61.66 | Q139: -3.7486 | R139: -61.66 | S139: IBGE Localidades 2022 (Sede Municipal) — sede municipal
A140: 130014405 | B140: Apuí | C140: Sim | D140: 1300144 | E140: Apuí | F140: Apuí - AM | G140: AM | H140: 13 | I140: Amazonas | J140: Norte | K140: 1303 | L140: Lábrea | M140: 130009 | N140: Manicoré | O140: -7.2034 | P140: -59.8844 | Q140: -7.2034 | R140: -59.8844 | S140: IBGE Localidades 2022 (Sede Municipal) — sede municipal
A141: 130014410 | B141: Sucunduri | C141: Não | D141: 1300144 | E141: Apuí | F141: Apuí - AM | G141: AM | H141: 13 | I141: Amazonas | J141: Norte | K141: 1303 | L141: Lábrea | M141: 130009 | N141: Manicoré | O141: -7.2034 | P141: -59.8844 | Q141: -6.802439 | R141: -59.039347 | S141: IBGE Localidades 2022 (Vila)
A142: 130020105 | B142: Atalaia do Norte | C142: Sim | D142: 1300201 | E142: Atalaia do Norte | F142: Atalaia do Norte - AM | G142: AM | H142: 13 | I142: Amazonas | J142: Norte | K142: 1302 | L142: Tefé | M142: 130006 | N142: Tabatinga | O142: -4.3649 | P142: -70.1911 | Q142: -4.3649 | R142: -70.1911 | S142: IBGE Localidades 2022 (Sede Municipal) — sede municipal
A143: 130030005 | B143: Autazes | C143: Sim | D143: 1300300 | E143: Autazes | F143: Autazes - AM | G143: AM | H143: 13 | I143: Amazonas | J143: Norte | K143: 1301 | L143: Manaus | M143: 130001 | N143: Manaus | O143: -3.5822 | P143: -59.13 | Q143: -3.5822 | R143: -59.13 | S143: IBGE Localidades 2022 (Sede Municipal) — sede municipal
A144: 130030010 | B144: Murutinga | C144: Não | D144: 1300300 | E144: Autazes | F144: Autazes - AM | G144: AM | H144: 13 | I144: Amazonas | J144: Norte | K144: 1301 | L144: Manaus | M144: 130001 | N144: Manaus | O144: -3.5822 | P144: -59.13 | Q144: -3.387222 | R144: -59.271628 | S144: IBGE Localidades 2022 (Vila)
A145: 130040905 | B145: Barcelos | C145: Sim | D145: 1300409 | E145: Barcelos | F145: Barcelos - AM | G145: AM | H145: 13 | I145: Amazonas | J145: Norte | K145: 1301 | L145: Manaus | M145: 130002 | N145: São Gabriel da Cachoeira | O145: -0.9692 | P145: -62.9264 | Q145: -0.9692 | R145: -62.9264 | S145: IBGE Localidades 2022 (Sede Municipal) — sede municipal
A146: 130050805 | B146: Barreirinha | C146: Sim | D146: 1300508 | E146: Barreirinha | F146: Barreirinha - AM | G146: AM | H146: 13 | I146: Amazonas | J146: Norte | K146: 1304 | L146: Parintins | M146: 130010 | N146: Parintins | O146: -2.7927 | P146: -57.0709 | Q146: -2.7927 | R146: -57.0709 | S146: IBGE Localidades 2022 (Sede Municipal) — sede municipal
A147: 130050810 | B147: Ariaú | C147: Não | D147: 1300508 | E147: Barreirinha | F147: Barreirinha - AM | G147: AM | H147: 13 | I147: Amazonas | J147: Norte | K147: 1304 | L147: Parintins | M147: 130010 | N147: Parintins | O147: -2.7927 | P147: -57.0709 | Q147: -3.164464 | R147: -57.237269 | S147: IBGE Localidades 2022 (Vila)
... A156: 130068020 | B156: Do Rio Urubu | C156: Não | D156: 1300680 | E156: Boa Vista do Ramos | F156: Boa Vista do Ramos - AM | G156: AM | H156: 13 | I156: Amazonas | J156: Norte | K156: 1304 | L156: Parintins | M156: 130010 | N156: Parintins | O156: -2.9704 | P156: -57.5884 | Q156: -3.122514 | R156: -57.837278 | S156: IBGE Localidades 2022 (Vila)
A157: 130070605 | B157: Boca do Acre | C157: Sim | D157: 1300706 | E157: Boca do Acre | F157: Boca do Acre - AM | G157: AM | H157: 13 | I157: Amazonas | J157: Norte | K157: 1303 | L157: Lábrea | M157: 130008 | N157: Lábrea | O157: -8.751243 | P157: -67.399578 | Q157: -8.751243 | R157: -67.399578 | S157: IBGE Localidades 2010 (Cidade) — sede municipal — a conferir | T157: Sede municipal marcada 'a conferir' — ver a observação na aba Municipios.
A158: 130070610 | B158: Floriano Peixoto | C158: Não | D158: 1300706 | E158: Boca do Acre | F158: Boca do Acre - AM | G158: AM | H158: 13 | I158: Amazonas | J158: Norte | K158: 1303 | L158: Lábrea | M158: 130008 | N158: Lábrea | O158: -8.751243 | P158: -67.399578 | Q158: -9.066283 | R158: -67.399522 | S158: IBGE Localidades 2022 (Vila)
A159: 130080505 | B159: Borba | C159: Sim | D159: 1300805 | E159: Borba | F159: Borba - AM | G159: AM | H159: 13 | I159: Amazonas | J159: Norte | K159: 1301 | L159: Manaus | M159: 130001 | N159: Manaus | O159: -4.3945 | P159: -59.589 | Q159: -4.3945 | R159: -59.589 | S159: IBGE Localidades 2022 (Sede Municipal) — sede municipal
A160: 130080520 | B160: Canumã | C160: Não | D160: 1300805 | E160: Borba | F160: Borba - AM | G160: AM | H160: 13 | I160: Amazonas | J160: Norte | K160: 1301 | L160: Manaus | M160: 130001 | N160: Manaus | O160: -4.3945 | P160: -59.589 | Q160: -3.996497 | R160: -59.091453 | S160: IBGE Localidades 2022 (Vila)
A161: 130080525 | B161: Axinin | C161: Não | D161: 1300805 | E161: Borba | F161: Borba - AM | G161: AM | H161: 13 | I161: Amazonas | J161: Norte | K161: 1301 | L161: Manaus | M161: 130001 | N161: Manaus | O161: -4.3945 | P161: -59.589 | Q161: -4.042489 | R161: -59.374525 | S161: IBGE Localidades 2022 (Vila)
A162: 130083905 | B162: Caapiranga | C162: Sim | D162: 1300839 | E162: Caapiranga | F162: Caapiranga - AM | G162: AM | H162: 13 | I162: Amazonas | J162: Norte | K162: 1301 | L162: Manaus | M162: 130004 | N162: Manacapuru | O162: -3.3268 | P162: -61.2134 | Q162: -3.3268 | R162: -61.2134 | S162: IBGE Localidades 2022 (Sede Municipal) — sede municipal
A163: 130090405 | B163: Canutama | C163: Sim | D163: 1300904 | E163: Canutama | F163: Canutama - AM | G163: AM | H163: 13 | I163: Amazonas | J163: Norte | K163: 1303 | L163: Lábrea | M163: 130008 | N163: Lábrea | O163: -6.5328 | P163: -64.3872 | Q163: -6.5328 | R163: -64.3872 | S163: IBGE Localidades 2022 (Sede Municipal) — sede municipal
A164: 130090410 | B164: Belo Monte | C164: Não | D164: 1300904 | E164: Canutama | F164: Canutama - AM | G164: AM | H164: 13 | I164: Amazonas | J164: Norte | K164: 1303 | L164: Lábrea | M164: 130008 | N164: Lábrea | O164: -6.5328 | P164: -64.3872 | Q164: -6.250581 | R164: -64.253442 | S164: IBGE Localidades 2022 (Vila)
A165: 130090415 | B165: Açuanópolis | C165: Não | D165: 1300904 | E165: Canutama | F165: Canutama - AM | G165: AM | H165: 13 | I165: Amazonas | J165: Norte | K165: 1303 | L165: Lábrea | M165: 130008 | N165: Lábrea | O165: -6.5328 | P165: -64.3872 | Q165: -8.198069 | R165: -63.869769 | S165: IBGE Localidades 2022 (Vila)
...

Sheet Regioes_Imediatas
A1: Código Região Imediata | B1: Região Geográfica Imediata | C1: Região Imediata - UF | D1: Código Região Intermediária | E1: Região Geográfica Intermediária | F1: UF | G1: Código UF | H1: Qtd. Municípios
A2: 110001 | B2: Porto Velho | C2: Porto Velho - RO | D2: 1101 | E2: Porto Velho | F2: RO | G2: 11 | H2: 5
A3: 110002 | B3: Ariquemes | C3: Ariquemes - RO | D3: 1101 | E3: Porto Velho | F3: RO | G3: 11 | H3: 8
A4: 110003 | B4: Jaru | C4: Jaru - RO | D4: 1101 | E4: Porto Velho | F4: RO | G4: 11 | H4: 5
A5: 110004 | B5: Ji-Paraná | C5: Ji-Paraná - RO | D5: 1102 | E5: Ji-Paraná | F5: RO | G5: 11 | H5: 13
A6: 110005 | B6: Cacoal | C6: Cacoal - RO | D6: 1102 | E6: Ji-Paraná | F6: RO | G6: 11 | H6: 14
A7: 110006 | B7: Vilhena | C7: Vilhena - RO | D7: 1102 | E7: Ji-Paraná | F7: RO | G7: 11 | H7: 7
A8: 120001 | B8: Rio Branco | C8: Rio Branco - AC | D8: 1201 | E8: Rio Branco | F8: AC | G8: 12 | H8: 7
A9: 120002 | B9: Brasiléia | C9: Brasiléia - AC | D9: 1201 | E9: Rio Branco | F9: AC | G9: 12 | H9: 4
A10: 120003 | B10: Sena Madureira | C10: Sena Madureira - AC | D10: 1201 | E10: Rio Branco | F10: AC | G10: 12 | H10: 3
A11: 120004 | B11: Cruzeiro do Sul | C11: Cruzeiro do Sul - AC | D11: 1202 | E11: Cruzeiro do Sul | F11: AC | G11: 12 | H11: 5
A12: 120005 | B12: Tarauacá | C12: Tarauacá - AC | D12: 1202 | E12: Cruzeiro do Sul | F12: AC | G12: 12 | H12: 3
A13: 130001 | B13: Manaus | C13: Manaus - AM | D13: 1301 | E13: Manaus | F13: AM | G13: 13 | H13: 10
... A511: 530001 | B511: Distrito Federal | C511: Distrito Federal - DF | D511: 5301 | E511: Distrito Federal | F511: DF | G511: 53 | H511: 1

Sheet Regioes_Intermediarias
A1: Código Região Intermediária | B1: Região Geográfica Intermediária | C1: UF | D1: Código UF | E1: Qtd. Regiões Imediatas | F1: Qtd. Municípios
A2: 1101 | B2: Porto Velho | C2: RO | D2: 11 | E2: 3 | F2: 18
A3: 1102 | B3: Ji-Paraná | C3: RO | D3: 11 | E3: 3 | F3: 34
A4: 1201 | B4: Rio Branco | C4: AC | D4: 12 | E4: 3 | F4: 14
A5: 1202 | B5: Cruzeiro do Sul | C5: AC | D5: 12 | E5: 2 | F5: 8
A6: 1301 | B6: Manaus | C6: AM | D6: 13 | E6: 4 | F6: 21
A7: 1302 | B7: Tefé | C7: AM | D7: 13 | E7: 3 | F7: 21
A8: 1303 | B8: Lábrea | C8: AM | D8: 13 | E8: 2 | F8: 9
A9: 1304 | B9: Parintins | C9: AM | D9: 13 | E9: 2 | F9: 11
A10: 1401 | B10: Boa Vista | C10: RR | D10: 14 | E10: 2 | F10: 9
A11: 1402 | B11: Rorainópolis - Caracaraí | C11: RR | D11: 14 | E11: 2 | F11: 6
A12: 1501 | B12: Belém | C12: PA | D12: 15 | E12: 3 | F12: 23
A13: 1502 | B13: Castanhal | C13: PA | D13: 15 | E13: 5 | F13: 39
... A134: 5301 | B134: Distrito Federal | C134: DF | D134: 53 | E134: 1 | F134: 1

Sheet UFs
A1: Código UF | B1: UF | C1: Estado | D1: Código Região | E1: Região | F1: Município Capital
A2: 11 | B2: RO | C2: Rondônia | D2: 1 | E2: Norte | F2: Porto Velho
A3: 12 | B3: AC | C3: Acre | D3: 1 | E3: Norte | F3: Rio Branco
A4: 13 | B4: AM | C4: Amazonas | D4: 1 | E4: Norte | F4: Manaus
A5: 14 | B5: RR | C5: Roraima | D5: 1 | E5: Norte | F5: Boa Vista
A6: 15 | B6: PA | C6: Pará | D6: 1 | E6: Norte | F6: Belém
A7: 16 | B7: AP | C7: Amapá | D7: 1 | E7: Norte | F7: Macapá
A8: 17 | B8: TO | C8: Tocantins | D8: 1 | E8: Norte | F8: Palmas
A9: 21 | B9: MA | C9: Maranhão | D9: 2 | E9: Nordeste | F9: São Luís
A10: 22 | B10: PI | C10: Piauí | D10: 2 | E10: Nordeste | F10: Teresina
A11: 23 | B11: CE | C11: Ceará | D11: 2 | E11: Nordeste | F11: Fortaleza
A12: 24 | B12: RN | C12: Rio Grande do Norte | D12: 2 | E12: Nordeste | F12: Natal
A13: 25 | B13: PB | C13: Paraíba | D13: 2 | E13: Nordeste | F13: João Pessoa
... A28: 53 | B28: DF | C28: Distrito Federal | D28: 5 | E28: Centro-Oeste | F28: Brasília

Sheet Resumo_UF
A1: UF | B1: Estado | C1: Região | D1: Municípios | E1: Distritos | F1: Regiões Imediatas | G1: Regiões Intermediárias | H1: Coord. corrigidas (IBGE 2010) | I1: Média distritos/município
A2: RO | B2: Rondônia | C2: Norte | D2: =COUNTIF(Municipios!$E$2:$E$5572,$A2) -> 52 | E2: =COUNTIF(Distritos!$G$2:$G$10752,$A2) -> 108 | F2: =COUNTIF(Regioes_Imediatas!$F$2:$F$511,$A2) -> 6 | G2: =COUNTIF(Regioes_Intermediarias!$C$2:$C$134,$A2) -> 2 | H2: =COUNTIFS(Municipios!$E$2:$E$5572,$A2,Municipios!$O$2:$O$5572,"IBGE Localidades 2010*") -> 8 | I2: =IF(D2=0,0,E2/D2) -> 2.0769231
A3: AC | B3: Acre | C3: Norte | D3: =COUNTIF(Municipios!$E$2:$E$5572,$A3) -> 22 | E3: =COUNTIF(Distritos!$G$2:$G$10752,$A3) -> 26 | F3: =COUNTIF(Regioes_Imediatas!$F$2:$F$511,$A3) -> 5 | G3: =COUNTIF(Regioes_Intermediarias!$C$2:$C$134,$A3) -> 2 | H3: =COUNTIFS(Municipios!$E$2:$E$5572,$A3,Municipios!$O$2:$O$5572,"IBGE Localidades 2010*") -> 0 | I3: =IF(D3=0,0,E3/D3) -> 1.1818182
A4: AM | B4: Amazonas | C4: Norte | D4: =COUNTIF(Municipios!$E$2:$E$5572,$A4) -> 62 | E4: =COUNTIF(Distritos!$G$2:$G$10752,$A4) -> 103 | F4: =COUNTIF(Regioes_Imediatas!$F$2:$F$511,$A4) -> 11 | G4: =COUNTIF(Regioes_Intermediarias!$C$2:$C$134,$A4) -> 4 | H4: =COUNTIFS(Municipios!$E$2:$E$5572,$A4,Municipios!$O$2:$O$5572,"IBGE Localidades 2010*") -> 2 | I4: =IF(D4=0,0,E4/D4) -> 1.6612903
A5: RR | B5: Roraima | C5: Norte | D5: =COUNTIF(Municipios!$E$2:$E$5572,$A5) -> 15 | E5: =COUNTIF(Distritos!$G$2:$G$10752,$A5) -> 15 | F5: =COUNTIF(Regioes_Imediatas!$F$2:$F$511,$A5) -> 4 | G5: =COUNTIF(Regioes_Intermediarias!$C$2:$C$134,$A5) -> 2 | H5: =COUNTIFS(Municipios!$E$2:$E$5572,$A5,Municipios!$O$2:$O$5572,"IBGE Localidades 2010*") -> 0 | I5: =IF(D5=0,0,E5/D5) -> 1
A6: PA | B6: Pará | C6: Norte | D6: =COUNTIF(Municipios!$E$2:$E$5572,$A6) -> 144 | E6: =COUNTIF(Distritos!$G$2:$G$10752,$A6) -> 261 | F6: =COUNTIF(Regioes_Imediatas!$F$2:$F$511,$A6) -> 21 | G6: =COUNTIF(Regioes_Intermediarias!$C$2:$C$134,$A6) -> 7 | H6: =COUNTIFS(Municipios!$E$2:$E$5572,$A6,Municipios!$O$2:$O$5572,"IBGE Localidades 2010*") -> 0 | I6: =IF(D6=0,0,E6/D6) -> 1.8125
A7: AP | B7: Amapá | C7: Norte | D7: =COUNTIF(Municipios!$E$2:$E$5572,$A7) -> 16 | E7: =COUNTIF(Distritos!$G$2:$G$10752,$A7) -> 34 | F7: =COUNTIF(Regioes_Imediatas!$F$2:$F$511,$A7) -> 4 | G7: =COUNTIF(Regioes_Intermediarias!$C$2:$C$134,$A7) -> 2 | H7: =COUNTIFS(Municipios!$E$2:$E$5572,$A7,Municipios!$O$2:$O$5572,"IBGE Localidades 2010*") -> 0 | I7: =IF(D7=0,0,E7/D7) -> 2.125
A8: TO | B8: Tocantins | C8: Norte | D8: =COUNTIF(Municipios!$E$2:$E$5572,$A8) -> 139 | E8: =COUNTIF(Distritos!$G$2:$G$10752,$A8) -> 157 | F8: =COUNTIF(Regioes_Imediatas!$F$2:$F$511,$A8) -> 11 | G8: =COUNTIF(Regioes_Intermediarias!$C$2:$C$134,$A8) -> 3 | H8: =COUNTIFS(Municipios!$E$2:$E$5572,$A8,Municipios!$O$2:$O$5572,"IBGE Localidades 2010*") -> 0 | I8: =IF(D8=0,0,E8/D8) -> 1.1294964
A9: MA | B9: Maranhão | C9: Nordeste | D9: =COUNTIF(Municipios!$E$2:$E$5572,$A9) -> 217 | E9: =COUNTIF(Distritos!$G$2:$G$10752,$A9) -> 243 | F9: =COUNTIF(Regioes_Imediatas!$F$2:$F$511,$A9) -> 22 | G9: =COUNTIF(Regioes_Intermediarias!$C$2:$C$134,$A9) -> 5 | H9: =COUNTIFS(Municipios!$E$2:$E$5572,$A9,Municipios!$O$2:$O$5572,"IBGE Localidades 2010*") -> 1 | I9: =IF(D9=0,0,E9/D9) -> 1.1198157
A10: PI | B10: Piauí | C10: Nordeste | D10: =COUNTIF(Municipios!$E$2:$E$5572,$A10) -> 224 | E10: =COUNTIF(Distritos!$G$2:$G$10752,$A10) -> 224 | F10: =COUNTIF(Regioes_Imediatas!$F$2:$F$511,$A10) -> 19 | G10: =COUNTIF(Regioes_Intermediarias!$C$2:$C$134,$A10) -> 6 | H10: =COUNTIFS(Municipios!$E$2:$E$5572,$A10,Municipios!$O$2:$O$5572,"IBGE Localidades 2010*") -> 0 | I10: =IF(D10=0,0,E10/D10) -> 1
A11: CE | B11: Ceará | C11: Nordeste | D11: =COUNTIF(Municipios!$E$2:$E$5572,$A11) -> 184 | E11: =COUNTIF(Distritos!$G$2:$G$10752,$A11) -> 894 | F11: =COUNTIF(Regioes_Imediatas!$F$2:$F$511,$A11) -> 18 | G11: =COUNTIF(Regioes_Intermediarias!$C$2:$C$134,$A11) -> 6 | H11: =COUNTIFS(Municipios!$E$2:$E$5572,$A11,Municipios!$O$2:$O$5572,"IBGE Localidades 2010*") -> 0 | I11: =IF(D11=0,0,E11/D11) -> 4.8586957
A12: RN | B12: Rio Grande do Norte | C12: Nordeste | D12: =COUNTIF(Municipios!$E$2:$E$5572,$A12) -> 167 | E12: =COUNTIF(Distritos!$G$2:$G$10752,$A12) -> 191 | F12: =COUNTIF(Regioes_Imediatas!$F$2:$F$511,$A12) -> 11 | G12: =COUNTIF(Regioes_Intermediarias!$C$2:$C$134,$A12) -> 3 | H12: =COUNTIFS(Municipios!$E$2:$E$5572,$A12,Municipios!$O$2:$O$5572,"IBGE Localidades 2010*") -> 1 | I12: =IF(D12=0,0,E12/D12) -> 1.1437126
A13: PB | B13: Paraíba | C13: Nordeste | D13: =COUNTIF(Municipios!$E$2:$E$5572,$A13) -> 223 | E13: =COUNTIF(Distritos!$G$2:$G$10752,$A13) -> 297 | F13: =COUNTIF(Regioes_Imediatas!$F$2:$F$511,$A13) -> 15 | G13: =COUNTIF(Regioes_Intermediarias!$C$2:$C$134,$A13) -> 4 | H13: =COUNTIFS(Municipios!$E$2:$E$5572,$A13,Municipios!$O$2:$O$5572,"IBGE Localidades 2010*") -> 1 | I13: =IF(D13=0,0,E13/D13) -> 1.3318386
... A28: DF | B28: Distrito Federal | C28: Centro-Oeste | D28: =COUNTIF(Municipios!$E$2:$E$5572,$A28) -> 1 | E28: =COUNTIF(Distritos!$G$2:$G$10752,$A28) -> 1 | F28: =COUNTIF(Regioes_Imediatas!$F$2:$F$511,$A28) -> 1 | G28: =COUNTIF(Regioes_Intermediarias!$C$2:$C$134,$A28) -> 1 | H28: =COUNTIFS(Municipios!$E$2:$E$5572,$A28,Municipios!$O$2:$O$5572,"IBGE Localidades 2010*") -> 0 | I28: =IF(D28=0,0,E28/D28) -> 1
A30: TOTAL BRASIL | D30: =SUM(D2:D28) -> 5571 | E30: =SUM(E2:E28) -> 10751 | F30: =SUM(F2:F28) -> 510 | G30: =SUM(G2:G28) -> 133 | H30: =SUM(H2:H28) -> 15 | I30: =IF(D30=0,0,E30/D30) -> 1.9298151
A32: Todas as colunas numéricas são fórmulas (COUNTIF/COUNTIFS/SUM) sobre as abas de dados. No Power BI, importe a tabela tbl_Resumo_UF (sem a linha de total).

Sheet Auditoria_Coordenadas
A1: Código IBGE | B1: Município | C1: UF | D1: Status da Coordenada | E1: Decisão | F1: Motivo da Inclusão | G1: Latitude Final | H1: Longitude Final | I1: Lat. IBGE 2022 | J1: Lon. IBGE 2022 | K1: Lat. IBGE 2010 | L1: Lon. IBGE 2010 | M1: Lat. Base Independente | N1: Lon. Base Independente | O1: Dist. 2022 x 2010 (km) | P1: Dist. 2022 x Independente (km) | Q1: Dist. 2010 x Independente (km) | R1: Sede dentro do Limite Municipal | S1: Observação
A2: 1100205 | B2: Porto Velho | C2: RO | D2: Corrigida - a conferir | E2: Usado IBGE 2010 (ponto 2022 rejeitado — evidência na observação) | F2: Divergência > 5 km entre fontes. Status diferente de OK. Curadoria documentada. | G2: -8.768892 | H2: -63.831446 | I2: -9.6462 | J2: -63.9599 | K2: -8.768892 | L2: -63.831446 | M2: -8.76077 | N2: -63.8999 | O2: 98.57 | P2: 98.68 | Q2: 7.58 | R2: Sim | S2: Ponto IBGE 2022 (-9,6462; -63,9599) divergia 98,6 km do IBGE 2010 e 98,7 km da base independente; substituído pelo IBGE 2010. O ponto 2022 está isolado (localidade IBGE 2010 mais próxima a 63,5 km). IBGE 2010 x base independente: 7,6 km. O ponto IBGE 2010 fica na Zona Leste da cidade; para análises que exijam o centro, use a coordenada publicada pela Prefeitura. Referência externa — Prefeitura de Porto Velho (8°45'43"S 63°54'14"W, centro): (-8,7619; -63,9039), a 8,0 km do ponto adotado.
A3: 1300706 | B3: Boca do Acre | C3: AM | D3: Corrigida - a conferir | E3: Usado IBGE 2010 (ponto 2022 rejeitado — evidência na observação) | F3: Divergência > 5 km entre fontes. Status diferente de OK. Curadoria documentada. | G3: -8.751243 | H3: -67.399578 | I3: -8.7724 | J3: -67.336 | K3: -8.751243 | L3: -67.399578 | M3: -8.74232 | N3: -67.3919 | O3: 7.37 | P3: 6.99 | Q3: 1.3 | R3: Sim | S3: Ponto IBGE 2022 (-8,7724; -67,3360) divergia 7,4 km do IBGE 2010 e 7,0 km da base independente; substituído pelo IBGE 2010. Fontes divergem ~7 km; o município tem mais de um núcleo urbano.
A4: 4322350 | B4: União da Serra | C4: RS | D4: A conferir | E4: Mantido IBGE 2022, a conferir (ver observação) | F4: Ponto 2022 a ≥ 3 km das duas referências. Status diferente de OK. Sede junto à sede de outro distrito. Curadoria documentada. | G4: -28.7546 | H4: -52.015 | I4: -28.7546 | J4: -52.015 | K4: -28.779899 | L4: -52.000417 | M4: -28.7833 | N4: -52.0238 | O4: 3.15 | P4: 3.3 | Q4: 2.31 | R4: Sim | S4: Ponto IBGE 2022 mantido, mas o IBGE 2010 (-28,7799; -52,0004) fica a 3,2 km e a base independente a 3,3 km dele; entre si, as duas referências distam 2,3 km. Na DTB 2025 o distrito-sede (05) chama-se 'São Luiz' e o distrito 20 'União da Serra'; no IBGE 2010 eram 05 'União da Serra' e 20 'Oeste'. O ponto IBGE 2022 fica junto à sede do distrito 20, ~3,2 km do ponto IBGE 2010 da sede. O ponto da sede fica a 0,21 km da sede do distrito 'União da Serra' (não-sede).
A5: 1302702 | B5: Manicoré | C5: AM | D5: Corrigida | E5: Usado IBGE 2010 (ponto 2022 rejeitado — evidência na observação) | F5: Divergência > 5 km entre fontes. Status diferente de OK. | G5: -5.813205 | H5: -61.299248 | I5: -7.9257 | J5: -61.5645 | K5: -5.813205 | L5: -61.299248 | M5: -5.80462 | N5: -61.2895 | O5: 236.72 | P5: 237.8 | Q5: 1.44 | R5: Sim | S5: Ponto IBGE 2022 (-7,9257; -61,5645) divergia 236,7 km do IBGE 2010 e 237,8 km da base independente; substituído pelo IBGE 2010. O ponto 2022 coincide com Projeto de Assentamento 'Agrovila do PA Santo Antonio do Matupi' (IBGE 2010, a 0,82 km).
A6: 1100130 | B6: Machadinho D'Oeste | C6: RO | D6: Corrigida | E6: Usado IBGE 2010 (ponto 2022 rejeitado — evidência na observação) | F6: Divergência > 5 km entre fontes. Status diferente de OK. | G6: -9.425562 | H6: -61.999593 | I6: -9.4657 | J6: -62.2562 | K6: -9.425562 | L6: -61.999593 | M6: -9.44363 | N6: -61.9818 | O6: 28.5 | P6: 30.2 | Q6: 2.8 | R6: Sim | S6: Ponto IBGE 2022 (-9,4657; -62,2562) divergia 28,5 km do IBGE 2010 e 30,2 km da base independente; substituído pelo IBGE 2010. O ponto 2022 está isolado (localidade IBGE 2010 mais próxima a 20,5 km).
A7: 1101401 | B7: Monte Negro | C7: RO | D7: Corrigida | E7: Usado IBGE 2010 (ponto 2022 rejeitado — evidência na observação) | F7: Divergência > 5 km entre fontes. Status diferente de OK. | G7: -10.263098 | H7: -63.295559 | I7: -10.0375 | J7: -63.3339 | K7: -10.263098 | L7: -63.295559 | M7: -10.2458 | N7: -63.29 | O7: 25.43 | P7: 23.66 | Q7: 2.02 | R7: Sim | S7: Ponto IBGE 2022 (-10,0375; -63,3339) divergia 25,4 km do IBGE 2010 e 23,7 km da base independente; substituído pelo IBGE 2010. O ponto 2022 está isolado (localidade IBGE 2010 mais próxima a 35,7 km).
A8: 1100288 | B8: Rolim de Moura | C8: RO | D8: Corrigida | E8: Usado IBGE 2010 (ponto 2022 rejeitado — evidência na observação) | F8: Divergência > 5 km entre fontes. Status diferente de OK. | G8: -11.722259 | H8: -61.785781 | I8: -11.7251 | J8: -61.5543 | K8: -11.722259 | L8: -61.785781 | M8: -11.7271 | N8: -61.7714 | O8: 25.2 | P8: 23.64 | Q8: 1.66 | R8: Sim | S8: Ponto IBGE 2022 (-11,7251; -61,5543) divergia 25,2 km do IBGE 2010 e 23,6 km da base independente; substituído pelo IBGE 2010. O ponto 2022 coincide com Povoado 'Nova Estrela' (IBGE 2010, a 0,80 km).
A9: 1100072 | B9: Corumbiara | C9: RO | D9: Corrigida | E9: Usado IBGE 2010 (ponto 2022 rejeitado — evidência na observação) | F9: Divergência > 5 km entre fontes. Status diferente de OK. Curadoria documentada. | G9: -12.99752 | H9: -60.948701 | I9: -13.0092 | J9: -61.1279 | K9: -12.99752 | L9: -60.948701 | M9: -12.9551 | N9: -60.8947 | O9: 19.46 | P9: 25.97 | Q9: 7.52 | R9: Sim | S9: Ponto IBGE 2022 (-13,0092; -61,1279) divergia 19,5 km do IBGE 2010 e 26,0 km da base independente; substituído pelo IBGE 2010. O ponto 2022 coincide com Povoado 'Vitória da União' (IBGE 2010, a 0,29 km). IBGE 2010 x base independente: 7,5 km. A base independente aponta para o Povoado Alto Guarajus; o ponto IBGE 2010 é a área urbana (CIDADE) da sede.
A10: 1101476 | B10: Primavera de Rondônia | C10: RO | D10: Corrigida | E10: Usado IBGE 2010 (ponto 2022 rejeitado — evidência na observação) | F10: Divergência > 5 km entre fontes. Status diferente de OK. | G10: -11.825707 | H10: -61.316546 | I10: -11.9749 | J10: -61.3769 | K10: -11.825707 | L10: -61.316546 | M10: -11.8295 | N10: -61.3153 | O10: 17.84 | P10: 17.5 | Q10: 0.44 | R10: Sim | S10: Ponto IBGE 2022 (-11,9749; -61,3769) divergia 17,8 km do IBGE 2010 e 17,5 km da base independente; substituído pelo IBGE 2010. O ponto 2022 coincide com Povoado 'Querência do Norte' (IBGE 2010, a 0,14 km).
A11: 1101484 | B11: São Felipe D'Oeste | C11: RO | D11: Corrigida | E11: Usado IBGE 2010 (ponto 2022 rejeitado — evidência na observação) | F11: Divergência > 5 km entre fontes. Status diferente de OK. | G11: -11.914389 | H11: -61.512508 | I11: -11.8002 | J11: -61.4737 | K11: -11.914389 | L11: -61.512508 | M11: -11.9023 | N11: -61.5026 | O11: 13.38 | P11: 11.78 | Q11: 1.72 | R11: Sim | S11: Ponto IBGE 2022 (-11,8002; -61,4737) divergia 13,4 km do IBGE 2010 e 11,8 km da base independente; substituído pelo IBGE 2010. O ponto 2022 coincide com Povoado 'Novo Paraíso' (IBGE 2010, a 0,09 km).
A12: 1100908 | B12: Castanheiras | C12: RO | D12: Corrigida | E12: Usado IBGE 2010 (ponto 2022 rejeitado — evidência na observação) | F12: Divergência > 5 km entre fontes. Status diferente de OK. | G12: -11.426842 | H12: -61.949161 | I12: -11.5005 | J12: -61.8876 | K12: -11.426842 | L12: -61.949161 | M12: -11.4253 | N12: -61.9482 | O12: 10.59 | P12: 10.66 | Q12: 0.2 | R12: Sim | S12: Ponto IBGE 2022 (-11,5005; -61,8876) divergia 10,6 km do IBGE 2010 e 10,7 km da base independente; substituído pelo IBGE 2010. O ponto 2022 coincide com Povoado 'Jardinópolis' (IBGE 2010, a 0,55 km).
A13: 3541000 | B13: Praia Grande | C13: SP | D13: Corrigida | E13: Usado IBGE 2010 (ponto 2022 rejeitado — evidência na observação) | F13: Divergência > 5 km entre fontes. Status diferente de OK. Curadoria documentada. | G13: -24.003022 | H13: -46.41205 | I13: -24.0307 | J13: -46.4939 | K13: -24.003022 | L13: -46.41205 | M13: -24.0084 | N13: -46.4121 | O13: 8.86 | P13: 8.67 | Q13: 0.6 | R13: Sim | S13: Ponto IBGE 2022 (-24,0307; -46,4939) divergia 8,9 km do IBGE 2010 e 8,7 km da base independente; substituído pelo IBGE 2010. O ponto 2022 está isolado (localidade IBGE 2010 mais próxima a 11,1 km). Referência externa — geodatos.net / Cidade Brasil (centro): (-24,0058; -46,4028), a 1,0 km do ponto adotado.
... A17: 2401008 | B17: Apodi | C17: RN | D17: Corrigida | E17: Usado IBGE 2010 (ponto 2022 arredondado ao minuto de arco) | F17: Ponto 2022 com precisão de minuto. | G17: -5.66377 | H17: -37.797784 | I17: -5.6666 | J17: -37.7999 | K17: -5.66377 | L17: -37.797784 | M17: -5.65349 | N17: -37.7946 | O17: 0.39 | P17: 1.57 | Q17: 1.2 | R17: Sim | S17: Ponto IBGE 2022 (-5,6666; -37,7999) arredondado ao minuto de arco; usado o ponto IBGE 2010, de precisão total, a 0,39 km.
A18: 4119954 | B18: Pontal do Paraná | C18: PR | D18: OK | E18: Mantido IBGE 2022 (nenhuma referência a < 3 km: IBGE 2010 a 11,9 km, base independente a 4,2 km; não houve divergência simultânea > limiar) | F18: Divergência > 5 km entre fontes. | G18: -25.6973 | H18: -48.4784 | I18: -25.6973 | J18: -48.4784 | K18: -25.594151 | L18: -48.448327 | M18: -25.6735 | N18: -48.5111 | O18: 11.86 | P18: 4.21 | Q18: 10.84 | R18: Sim
A19: 2408102 | B19: Natal | C19: RN | D19: OK | E19: Mantido IBGE 2022 (nenhuma referência a < 3 km: IBGE 2010 a 9,8 km, base independente a 4,4 km; não houve divergência simultânea > limiar) | F19: Divergência > 5 km entre fontes. | G19: -5.8301 | H19: -35.2128 | I19: -5.8301 | J19: -35.2128 | K19: -5.750899 | L19: -35.252255 | M19: -5.79357 | N19: -35.1986 | O19: 9.83 | P19: 4.36 | Q19: 7.6 | R19: Sim
A20: 4208450 | B20: Itapoá | C20: SC | D20: OK | E20: Mantido IBGE 2022 (nenhuma referência a < 3 km: IBGE 2010 a 8,4 km, base independente a 4,0 km; não houve divergência simultânea > limiar) | F20: Divergência > 5 km entre fontes. | G20: -26.0819 | H20: -48.6055 | I20: -26.0819 | J20: -48.6055 | K20: -26.006048 | L20: -48.604168 | M20: -26.1158 | N20: -48.6182 | O20: 8.44 | P20: 3.98 | Q20: 12.28 | R20: Sim
A21: 2304400 | B21: Fortaleza | C21: CE | D21: OK | E21: Mantido IBGE 2022 (base independente a 2,3 km confirma; IBGE 2010 a 7,4 km, ponto antigo) | F21: Divergência > 5 km entre fontes. | G21: -3.7254 | H21: -38.5236 | I21: -3.7254 | J21: -38.5236 | K21: -3.723805 | L21: -38.589928 | M21: -3.71664 | N21: -38.5423 | O21: 7.36 | P21: 2.29 | Q21: 5.34 | R21: Sim
A22: 4215109 | B22: Rodeio | C22: SC | D22: OK | E22: Mantido IBGE 2022 (base independente a 0,4 km confirma; IBGE 2010 a 6,7 km, ponto antigo) | F22: Divergência > 5 km entre fontes. | G22: -26.924 | H22: -49.3687 | I22: -26.924 | J22: -49.3687 | K22: -26.943502 | L22: -49.304707 | M22: -26.9243 | N22: -49.3649 | O22: 6.7 | P22: 0.38 | Q22: 6.34 | R22: Sim
A23: 4314423 | B23: Picada Café | C23: RS | D23: OK | E23: Mantido IBGE 2022 (base independente a 0,6 km confirma; IBGE 2010 a 6,7 km, ponto antigo) | F23: Divergência > 5 km entre fontes. | G23: -29.4505 | H23: -51.1328 | I23: -29.4505 | J23: -51.1328 | K23: -29.454384 | L23: -51.06405 | M23: -29.4464 | N23: -51.1367 | O23: 6.67 | P23: 0.59 | Q23: 7.09 | R23: Sim
A24: 4301057 | B24: Arroio do Sal | C24: RS | D24: OK | E24: Mantido IBGE 2022 (base independente a 0,6 km confirma; IBGE 2010 a 6,6 km, ponto antigo) | F24: Divergência > 5 km entre fontes. | G24: -29.5488 | H24: -49.8875 | I24: -29.5488 | J24: -49.8875 | K24: -29.592961 | L24: -49.932958 | M24: -29.5439 | N24: -49.8895 | O24: 6.59 | P24: 0.58 | Q24: 6.89 | R24: Sim
A25: 2927705 | B25: Santa Cruz Cabrália | C25: BA | D25: OK | E25: Mantido IBGE 2022 (base independente a 0,6 km confirma; IBGE 2010 a 6,3 km, ponto antigo) | F25: Divergência > 5 km entre fontes. | G25: -16.282 | H25: -39.0243 | I25: -16.282 | J25: -39.0243 | K25: -16.338097 | L25: -39.013183 | M25: -16.2825 | N25: -39.0295 | O25: 6.35 | P25: 0.56 | Q25: 6.42 | R25: Sim
A26: 1302603 | B26: Manaus | C26: AM | D26: OK | E26: Mantido IBGE 2022, divergência anotada (IBGE 2010 a 6,3 km e base independente a 5,3 km; entre si 1,8 km) | F26: Divergência > 5 km entre fontes. Ponto 2022 a ≥ 3 km das duas referências. | G26: -3.0922 | H26: -60.0604 | I26: -3.0922 | J26: -60.0604 | K26: -3.134691 | L26: -60.023335 | M26: -3.11866 | N26: -60.0212 | O26: 6.27 | P26: 5.25 | Q26: 1.8 | R26: Sim | S26: Ponto IBGE 2022 mantido (capital: o ponto só é substituído acima de 10 km), mas o IBGE 2010 (-3,1347; -60,0233) fica a 6,3 km e a base independente a 5,3 km dele; entre si, as duas referências distam 1,8 km.
A27: 4213500 | B27: Porto Belo | C27: SC | D27: OK | E27: Mantido IBGE 2022 (base independente a 0,6 km confirma; IBGE 2010 a 6,0 km, ponto antigo) | F27: Divergência > 5 km entre fontes. | G27: -27.1547 | H27: -48.5421 | I27: -27.1547 | J27: -48.5421 | K27: -27.149466 | L27: -48.602757 | M27: -27.1586 | N27: -48.5469 | O27: 6.03 | P27: 0.64 | Q27: 5.62 | R27: Sim
A28: 5006606 | B28: Ponta Porã | C28: MS | D28: OK | E28: Mantido IBGE 2022 (base independente a 1,1 km confirma; IBGE 2010 a 6,0 km, ponto antigo) | F28: Divergência > 5 km entre fontes. | G28: -22.5385 | H28: -55.7246 | I28: -22.5385 | J28: -55.7246 | K28: -22.486187 | L28: -55.71085 | M28: -22.5296 | N28: -55.7203 | O28: 5.99 | P28: 1.08 | Q28: 4.92 | R28: Sim
A29: 2927408 | B29: Salvador | C29: BA | D29: OK | E29: Mantido IBGE 2022 (base independente a 1,3 km confirma; IBGE 2010 a 5,2 km, ponto antigo) | F29: Divergência > 5 km entre fontes. | G29: -12.9742 | H29: -38.5124 | I29: -12.9742 | J29: -38.5124 | K29: -13.014772 | L29: -38.488061 | M29: -12.9718 | N29: -38.5011 | O29: 5.23 | P29: 1.25 | Q29: 4.98 | R29: Sim
A30: 3170107 | B30: Uberaba | C30: MG | D30: OK | E30: Mantido IBGE 2022 (base independente a 1,3 km confirma; IBGE 2010 a 5,2 km, ponto antigo) | F30: Divergência > 5 km entre fontes. | G30: -19.7487 | H30: -47.9509 | I30: -19.7487 | J30: -47.9509 | K30: -19.713535 | L30: -47.983625 | M30: -19.7472 | N30: -47.9381 | O30: 5.2 | P30: 1.35 | Q30: 6.06 | R30: Sim
A31: 1400159 | B31: Bonfim | C31: RR | D31: OK | E31: Mantido IBGE 2022 (base independente a 0,4 km confirma; IBGE 2010 a 5,2 km, ponto antigo) | F31: Divergência > 5 km entre fontes. | G31: 3.3579 | H31: -59.8319 | I31: 3.3579 | J31: -59.8319 | K31: 3.350289 | L31: -59.878007 | M31: 3.36161 | N31: -59.8333 | O31: 5.19 | P31: 0.44 | Q31: 5.12 | R31: Sim
A32: 1504208 | B32: Marabá | C32: PA | D32: OK | E32: Mantido IBGE 2022 (nenhuma referência a < 3 km: IBGE 2010 a 4,9 km, base independente a 5,3 km; não houve divergência simultânea > limiar) | F32: Divergência > 5 km entre fontes. | G32: -5.3478 | H32: -49.0984 | I32: -5.3478 | J32: -49.0984 | K32: -5.352606 | L32: -49.142025 | M32: -5.38075 | N32: -49.1327 | O32: 4.86 | P32: 5.28 | Q32: 3.3 | R32: Sim
A33: 3205002 | B33: Serra | C33: ES | D33: OK | E33: Mantido IBGE 2022 (ambas as referências a ≤ 5 km; elas divergem entre si 5,2 km) | F33: Divergência > 5 km entre fontes. | G33: -20.1244 | H33: -40.305 | I33: -20.1244 | J33: -40.305 | K33: -20.15677 | L33: -40.275217 | M33: -20.121 | N33: -40.3074 | O33: 4.76 | P33: 0.45 | Q33: 5.21 | R33: Sim
A34: 5218789 | B34: Rio Quente | C34: GO | D34: OK | E34: Mantido IBGE 2022, divergência anotada (IBGE 2010 a 4,8 km e base independente a 4,1 km; entre si 0,7 km) | F34: Ponto 2022 a ≥ 3 km das duas referências. | G34: -17.8094 | H34: -48.7625 | I34: -17.8094 | J34: -48.7625 | K34: -17.767746 | L34: -48.772668 | M34: -17.774 | N34: -48.7725 | O34: 4.76 | P34: 4.08 | Q34: 0.7 | R34: Sim | S34: Ponto IBGE 2022 mantido, mas o IBGE 2010 (-17,7677; -48,7727) fica a 4,8 km e a base independente a 4,1 km dele; entre si, as duas referências distam 0,7 km.
A35: 2100055 | B35: Açailândia | C35: MA | D35: OK | E35: Mantido IBGE 2022, divergência anotada (IBGE 2010 a 4,7 km e base independente a 4,0 km; entre si 0,8 km) | F35: Ponto 2022 a ≥ 3 km das duas referências. | G35: -4.9403 | H35: -47.4653 | I35: -4.9403 | J35: -47.4653 | K35: -4.951377 | L35: -47.506665 | M35: -4.94714 | N35: -47.5004 | O35: 4.75 | P35: 3.96 | Q35: 0.84 | R35: Sim | S35: Ponto IBGE 2022 mantido, mas o IBGE 2010 (-4,9514; -47,5067) fica a 4,7 km e a base independente a 4,0 km dele; entre si, as duas referências distam 0,8 km.
A36: 2800308 | B36: Aracaju | C36: SE | D36: OK | E36: Mantido IBGE 2022, divergência anotada (IBGE 2010 a 4,7 km e base independente a 3,9 km; entre si 2,1 km) | F36: Ponto 2022 a ≥ 3 km das duas referências. | G36: -10.9444 | H36: -37.069 | I36: -10.9444 | J36: -37.069 | K36: -10.907216 | L36: -37.048213 | M36: -10.9091 | N36: -37.0677 | O36: 4.72 | P36: 3.93 | Q36: 2.14 | R36: Sim | S36: Ponto IBGE 2022 mantido, mas o IBGE 2010 (-10,9072; -37,0482) fica a 4,7 km e a base independente a 3,9 km dele; entre si, as duas referências distam 2,1 km.
A37: 2614857 | B37: Tamandaré | C37: PE | D37: OK | E37: Mantido IBGE 2022 (ambas as referências a ≤ 5 km; elas divergem entre si 5,9 km) | F37: Divergência > 5 km entre fontes. | G37: -8.7468 | H37: -35.0937 | I37: -8.7468 | J37: -35.0937 | K37: -8.704689 | L37: -35.090647 | M37: -8.75665 | N37: -35.1033 | O37: 4.69 | P37: 1.52 | Q37: 5.94 | R37: Sim
A38: 5103379 | B38: Cotriguaçu | C38: MT | D38: OK | E38: Mantido IBGE 2022 (nenhuma referência a < 3 km: IBGE 2010 a 4,6 km, base independente a 17,4 km; não houve divergência simultânea > limiar) | F38: Divergência > 5 km entre fontes. | G38: -9.9053 | H38: -58.5698 | I38: -9.9053 | J38: -58.5698 | K38: -9.886254 | L38: -58.606895 | M38: -9.85656 | N38: -58.4192 | O38: 4.58 | P38: 17.36 | Q38: 20.83 | R38: Sim
A39: 3201308 | B39: Cariacica | C39: ES | D39: OK | E39: Mantido IBGE 2022 (nenhuma referência a < 3 km: IBGE 2010 a 4,6 km, base independente a 8,8 km; não houve divergência simultânea > limiar) | F39: Divergência > 5 km entre fontes. | G39: -20.3338 | H39: -40.3776 | I39: -20.3338 | J39: -40.3776 | K39: -20.294678 | L39: -40.390559 | M39: -20.2632 | N39: -40.4165 | O39: 4.56 | P39: 8.84 | Q39: 4.42 | R39: Sim
A40: 2707701 | B40: Rio Largo | C40: AL | D40: OK | E40: Mantido IBGE 2022, divergência anotada (IBGE 2010 a 4,4 km e base independente a 4,0 km; entre si 1,7 km) | F40: Ponto 2022 a ≥ 3 km das duas referências. | G40: -9.5075 | H40: -35.8182 | I40: -9.5075 | J40: -35.8182 | K40: -9.486158 | L40: -35.852422 | M40: -9.47783 | N40: -35.8394 | O40: 4.44 | P40: 4.04 | Q40: 1.7 | R40: Sim | S40: Ponto IBGE 2022 mantido, mas o IBGE 2010 (-9,4862; -35,8524) fica a 4,4 km e a base independente a 4,0 km dele; entre si, as duas referências distam 1,7 km.
A41: 3118601 | B41: Contagem | C41: MG | D41: OK | E41: Mantido IBGE 2022, divergência anotada (IBGE 2010 a 3,9 km e base independente a 4,3 km; entre si 1,8 km) | F41: Ponto 2022 a ≥ 3 km das duas referências. | G41: -19.9192 | H41: -44.0928 | I41: -19.9192 | J41: -44.0928 | K41: -19.943446 | L41: -44.066345 | M41: -19.9321 | N41: -44.0539 | O41: 3.86 | P41: 4.31 | Q41: 1.81 | R41: Sim | S41: Ponto IBGE 2022 mantido, mas o IBGE 2010 (-19,9434; -44,0663) fica a 3,9 km e a base independente a 4,3 km dele; entre si, as duas referências distam 1,8 km.
A42: 4304358 | B42: Candiota | C42: RS | D42: OK | E42: Mantido IBGE 2022, divergência anotada (IBGE 2010 a 3,8 km e base independente a 3,5 km; entre si 1,0 km) | F42: Ponto 2022 a ≥ 3 km das duas referências. | G42: -31.5468 | H42: -53.7143 | I42: -31.5468 | J42: -53.7143 | K42: -31.56101 | L42: -53.677805 | M42: -31.5516 | N42: -53.6773 | O42: 3.8 | P42: 3.55 | Q42: 1.05 | R42: Sim | S42: Ponto IBGE 2022 mantido, mas o IBGE 2010 (-31,5610; -53,6778) fica a 3,8 km e a base independente a 3,5 km dele; entre si, as duas referências distam 1,0 km.
A43: 3122306 | B43: Divinópolis | C43: MG | D43: OK | E43: Mantido IBGE 2022, divergência anotada (IBGE 2010 a 3,6 km e base independente a 3,5 km; entre si 0,4 km) | F43: Ponto 2022 a ≥ 3 km das duas referências. | G43: -20.1703 | H43: -44.9109 | I43: -20.1703 | J43: -44.9109 | K43: -20.142074 | L43: -44.893886 | M43: -20.1446 | N43: -44.8912 | O43: 3.61 | P43: 3.52 | Q43: 0.4 | R43: Sim | S43: Ponto IBGE 2022 mantido, mas o IBGE 2010 (-20,1421; -44,8939) fica a 3,6 km e a base independente a 3,5 km dele; entre si, as duas referências distam 0,4 km.
A44: 5003702 | B44: Dourados | C44: MS | D44: OK | E44: Mantido IBGE 2022, divergência anotada (IBGE 2010 a 3,3 km e base independente a 3,6 km; entre si 0,5 km) | F44: Ponto 2022 a ≥ 3 km das duas referências. | G44: -22.241 | H44: -54.7831 | I44: -22.241 | J44: -54.7831 | K44: -22.227236 | L44: -54.811289 | M44: -22.2231 | N44: -54.812 | O44: 3.28 | P44: 3.58 | Q44: 0.47 | R44: Sim | S44: Ponto IBGE 2022 mantido, mas o IBGE 2010 (-22,2272; -54,8113) fica a 3,3 km e a base independente a 3,6 km dele; entre si, as duas referências distam 0,5 km.
A45: 4317202 | B45: Santa Rosa | C45: RS | D45: OK | E45: Mantido IBGE 2022, divergência anotada (IBGE 2010 a 3,2 km e base independente a 3,4 km; entre si 0,4 km) | F45: Ponto 2022 a ≥ 3 km das duas referências. | G45: -27.8607 | H45: -54.4462 | I45: -27.8607 | J45: -54.4462 | K45: -27.86675 | L45: -54.478224 | M45: -27.8702 | N45: -54.4796 | O45: 3.22 | P45: 3.45 | Q45: 0.41 | R45: Sim | S45: Ponto IBGE 2022 mantido, mas o IBGE 2010 (-27,8667; -54,4782) fica a 3,2 km e a base independente a 3,4 km dele; entre si, as duas referências distam 0,4 km.
A46: 3304524 | B46: Rio das Ostras | C46: RJ | D46: OK | E46: Mantido IBGE 2022, divergência anotada (IBGE 2010 a 3,2 km e base independente a 3,4 km; entre si 1,3 km) | F46: Ponto 2022 a ≥ 3 km das duas referências. | G46: -22.4986 | H46: -41.922 | I46: -22.4986 | J46: -41.922 | K46: -22.523941 | L46: -41.936967 | M46: -22.5174 | N46: -41.9475 | O46: 3.21 | P46: 3.35 | Q46: 1.3 | R46: Sim | S46: Ponto IBGE 2022 mantido, mas o IBGE 2010 (-22,5239; -41,9370) fica a 3,2 km e a base independente a 3,4 km dele; entre si, as duas referências distam 1,3 km.
A47: 3202405 | B47: Guarapari | C47: ES | D47: OK | E47: Mantido IBGE 2022, divergência anotada (IBGE 2010 a 3,2 km e base independente a 5,0 km; entre si 1,9 km) | F47: Divergência > 5 km entre fontes. Ponto 2022 a ≥ 3 km das duas referências. | G47: -20.6404 | H47: -40.4814 | I47: -20.6404 | J47: -40.4814 | K47: -20.665975 | L47: -40.495021 | M47: -20.6772 | N47: -40.5093 | O47: 3.18 | P47: 5.02 | Q47: 1.94 | R47: Sim | S47: Ponto IBGE 2022 mantido, mas o IBGE 2010 (-20,6660; -40,4950) fica a 3,2 km e a base independente a 5,0 km dele; entre si, as duas referências distam 1,9 km.
A48: 3520400 | B48: Ilhabela | C48: SP | D48: OK | E48: Mantido IBGE 2022, divergência anotada (IBGE 2010 a 3,1 km e base independente a 4,1 km; entre si 1,1 km) | F48: Ponto 2022 a ≥ 3 km das duas referências. | G48: -23.8144 | H48: -45.3655 | I48: -23.8144 | J48: -45.3655 | K48: -23.788652 | L48: -45.354057 | M48: -23.7785 | N48: -45.3552 | O48: 3.09 | P48: 4.13 | Q48: 1.13 | R48: Sim | S48: Ponto IBGE 2022 mantido, mas o IBGE 2010 (-23,7887; -45,3541) fica a 3,1 km e a base independente a 4,1 km dele; entre si, as duas referências distam 1,1 km.
A49: 4216602 | B49: São José | C49: SC | D49: OK | E49: Mantido IBGE 2022 (IBGE 2010 a 3,1 km; base independente a 0,9 km) | F49: Sede junto à sede de outro distrito. | G49: -27.6159 | H49: -48.6278 | I49: -27.6159 | J49: -48.6278 | K49: -27.590312 | L49: -48.616023 | M49: -27.6136 | N49: -48.6366 | O49: 3.07 | P49: 0.9 | Q49: 3.29 | R49: Sim | S49: O ponto da sede fica a 0,02 km da sede do distrito 'Centro Histórico de São José' (não-sede).
A50: 1721000 | B50: Palmas | C50: TO | D50: OK | E50: Mantido IBGE 2022 (nenhuma referência a < 3 km: IBGE 2010 a 3,0 km, base independente a 6,6 km; não houve divergência simultânea > limiar) | F50: Divergência > 5 km entre fontes. | G50: -10.1845 | H50: -48.3337 | I50: -10.1845 | J50: -48.3337 | K50: -10.163253 | L50: -48.351044 | M50: -10.24 | N50: -48.3558 | O50: 3.03 | P50: 6.63 | Q50: 8.55 | R50: Sim
A51: 5106240 | B51: Nova Ubiratã | C51: MT | D51: OK | E51: Mantido IBGE 2022 (IBGE 2010 a 2,8 km confirma; base independente a 5,9 km diverge) | F51: Divergência > 5 km entre fontes. | G51: -13.0357 | H51: -55.247 | I51: -13.0357 | J51: -55.247 | K51: -13.033828 | L51: -55.273213 | M51: -12.9834 | N51: -55.2556 | O51: 2.85 | P51: 5.89 | Q51: 5.92 | R51: Sim
A52: 1600279 | B52: Laranjal do Jari | C52: AP | D52: OK | E52: Mantido IBGE 2022 (IBGE 2010 a 2,6 km confirma; base independente a 8,5 km diverge) | F52: Divergência > 5 km entre fontes. | G52: -0.8413 | H52: -52.5202 | I52: -0.8413 | J52: -52.5202 | K52: -0.855664 | L52: -52.539021 | M52: -0.804911 | N52: -52.453 | O52: 2.63 | P52: 8.5 | Q52: 11.11 | R52: Sim
A53: 2507507 | B53: João Pessoa | C53: PB | D53: OK | E53: Mantido IBGE 2022 (IBGE 2010 a 2,4 km confirma; base independente a 6,0 km diverge) | F53: Divergência > 5 km entre fontes. | G53: -7.1688 | H53: -34.8638 | I53: -7.1688 | J53: -34.8638 | K53: -7.149382 | L53: -34.873385 | M53: -7.11509 | N53: -34.8641 | O53: 2.4 | P53: 5.97 | Q53: 3.95 | R53: Sim
A54: 3550308 | B54: São Paulo | C54: SP | D54: OK | E54: Mantido IBGE 2022 (IBGE 2010 a 1,7 km confirma; base independente a 6,6 km diverge) | F54: Divergência > 5 km entre fontes. Curadoria documentada. | G54: -23.5548 | H54: -46.579 | I54: -23.5548 | J54: -46.579 | K54: -23.567386 | L54: -46.570383 | M54: -23.5329 | N54: -46.6395 | O54: 1.65 | P54: 6.63 | Q54: 8.02 | R54: Sim | S54: Ponto representativo da área urbana definido pelo IBGE (2010 e 2022 concordam); não é o marco zero. Referência externa — Praça da Sé (marco zero): (-23,5503; -46,6339), a 5,6 km do ponto adotado.
A55: 2607901 | B55: Jaboatão dos Guararapes | C55: PE | D55: OK | E55: Mantido IBGE 2022 (IBGE 2010 a 1,6 km confirma; base independente a 11,0 km diverge) | F55: Divergência > 5 km entre fontes. | G55: -8.1512 | H55: -34.923 | I55: -8.1512 | J55: -34.923 | K55: -8.165391 | L55: -34.921173 | M55: -8.11298 | N55: -35.015 | O55: 1.59 | P55: 10.98 | Q55: 11.86 | R55: Sim
A56: 2202851 | B56: Coronel José Dias | C56: PI | D56: OK | E56: Mantido IBGE 2022 (ambas as referências a ≤ 5 km; elas divergem entre si 5,8 km) | F56: Divergência > 5 km entre fontes. | G56: -8.8262 | H56: -42.4802 | I56: -8.8262 | J56: -42.4802 | K56: -8.816369 | L56: -42.470357 | M56: -8.81397 | N56: -42.5232 | O56: 1.54 | P56: 4.92 | Q56: 5.81 | R56: Sim
A57: 1505031 | B57: Novo Progresso | C57: PA | D57: OK | E57: Mantido IBGE 2022 (IBGE 2010 a 1,5 km confirma; base independente a 12,1 km diverge) | F57: Divergência > 5 km entre fontes. | G57: -7.0382 | H57: -55.4068 | I57: -7.0382 | J57: -55.4068 | K57: -7.034836 | L57: -55.41987 | M57: -7.14347 | N57: -55.3786 | O57: 1.49 | P57: 12.11 | Q57: 12.91 | R57: Sim
A58: 2307254 | B58: Jijoca de Jericoacoara | C58: CE | D58: OK | E58: Mantido IBGE 2022 (IBGE 2010 a 1,5 km confirma; base independente a 13,1 km diverge) | F58: Divergência > 5 km entre fontes. | G58: -2.8939 | H58: -40.4507 | I58: -2.8939 | J58: -40.4507 | K58: -2.899683 | L58: -40.438735 | M58: -2.79331 | N58: -40.5127 | O58: 1.48 | P58: 13.13 | Q58: 14.4 | R58: Sim
A59: 3300951 | B59: Comendador Levy Gasparian | C59: RJ | D59: OK | E59: Mantido IBGE 2022 (ponto na borda do limite; efeito da malha simplificada) | F59: Sede na borda/fora do limite. | G59: -22.0292 | H59: -43.2046 | I59: -22.0292 | J59: -43.2046 | K59: -22.033359 | L59: -43.217224 | M59: -22.0404 | N59: -43.214 | O59: 1.38 | P59: 1.58 | Q59: 0.85 | R59: Na borda (< 1 km)
A60: 5108006 | B60: Tapurah | C60: MT | D60: OK | E60: Mantido IBGE 2022 (IBGE 2010 a 1,3 km confirma; base independente a 5,3 km diverge) | F60: Divergência > 5 km entre fontes. | G60: -12.7422 | H60: -56.5135 | I60: -12.7422 | J60: -56.5135 | K60: -12.732069 | L60: -56.519486 | M60: -12.695 | N60: -56.5178 | O60: 1.3 | P60: 5.27 | Q60: 4.13 | R60: Sim
A61: 5102603 | B61: Campinápolis | C61: MT | D61: OK | E61: Mantido IBGE 2022 (IBGE 2010 a 1,2 km confirma; base independente a 11,4 km diverge) | F61: Divergência > 5 km entre fontes. | G61: -14.5493 | H61: -52.7926 | I61: -14.5493 | J61: -52.7926 | K61: -14.539617 | L61: -52.797495 | M61: -14.5162 | N61: -52.893 | O61: 1.2 | P61: 11.42 | Q61: 10.6 | R61: Sim
A62: 5106216 | B62: Nova Canaã do Norte | C62: MT | D62: OK | E62: Mantido IBGE 2022 (IBGE 2010 a 1,2 km confirma; base independente a 28,1 km diverge) | F62: Divergência > 5 km entre fontes. | G62: -10.6406 | H62: -55.7097 | I62: -10.6406 | J62: -55.7097 | K62: -10.631104 | L62: -55.714877 | M62: -10.558 | N62: -55.953 | O62: 1.2 | P62: 28.13 | Q62: 27.27 | R62: Sim
A63: 5107875 | B63: Sapezal | C63: MT | D63: OK | E63: Mantido IBGE 2022 (IBGE 2010 a 1,2 km confirma; base independente a 62,3 km diverge) | F63: Divergência > 5 km entre fontes. | G63: -13.5475 | H63: -58.8169 | I63: -13.5475 | J63: -58.8169 | K63: -13.538195 | L63: -58.812138 | M63: -12.9892 | N63: -58.7645 | O63: 1.16 | P63: 62.34 | Q63: 61.26 | R63: Sim
A64: 1505551 | B64: Pau D'Arco | C64: PA | D64: OK | E64: Mantido IBGE 2022 (IBGE 2010 a 1,1 km confirma; base independente a 774,1 km diverge) | F64: Divergência > 5 km entre fontes. | G64: -7.8304 | H64: -50.0402 | I64: -7.8304 | J64: -50.0402 | K64: -7.836794 | L64: -50.048276 | M64: -1.59772 | N64: -46.9268 | O64: 1.14 | P64: 774.1 | Q64: 775.13 | R64: Sim
A65: 2411601 | B65: São Bento do Norte | C65: RN | D65: OK | E65: Mantido IBGE 2022 (IBGE 2010 a 1,1 km confirma; base independente a 9,7 km diverge) | F65: Divergência > 5 km entre fontes. | G65: -5.067 | H65: -36.0422 | I65: -5.067 | J65: -36.0422 | K65: -5.059501 | L65: -36.035431 | M65: -5.09259 | N65: -35.9587 | O65: 1.12 | P65: 9.68 | Q65: 9.26 | R65: Sim
A66: 4320859 | B66: Tabaí | C66: RS | D66: OK | E66: Mantido IBGE 2022 (IBGE 2010 a 1,1 km confirma; base independente a 5,8 km diverge) | F66: Divergência > 5 km entre fontes. | G66: -29.6853 | H66: -51.7167 | I66: -29.6853 | J66: -51.7167 | K66: -29.687771 | L66: -51.727475 | M66: -29.643 | N66: -51.6823 | O66: 1.08 | P66: 5.76 | Q66: 6.62 | R66: Sim
... A101: 2306801 | B101: Jaguaribara | C101: CE | D101: OK | E101: Mantido IBGE 2022 (IBGE 2010 a 0,4 km confirma; base independente a 25,4 km diverge) | F101: Divergência > 5 km entre fontes. | G101: -5.4613 | H101: -38.4619 | I101: -5.4613 | J101: -38.4619 | K101: -5.457502 | L101: -38.463097 | M101: -5.67765 | N101: -38.5359 | O101: 0.44 | P101: 25.41 | Q101: 25.77 | R101: Sim
A102: 3304201 | B102: Resende | C102: RJ | D102: OK | E102: Mantido IBGE 2022 (IBGE 2010 a 0,4 km; base independente a 0,4 km) | F102: Sede junto à sede de outro distrito. | G102: -22.4693 | H102: -44.4474 | I102: -22.4693 | J102: -44.4474 | K102: -22.471184 | L102: -44.443613 | M102: -22.4705 | N102: -44.4509 | O102: 0.44 | P102: 0.38 | Q102: 0.75 | R102: Sim | S102: O ponto da sede fica a 0,45 km da sede do distrito 'Agulhas Negras' (não-sede).
A103: 1200385 | B103: Plácido de Castro | C103: AC | D103: OK | E103: Mantido IBGE 2022 (IBGE 2010 a 0,4 km confirma; base independente a 8,1 km diverge) | F103: Divergência > 5 km entre fontes. | G103: -10.3367 | H103: -67.1847 | I103: -10.3367 | J103: -67.1847 | K103: -10.335133 | L103: -67.18826 | M103: -10.2806 | N103: -67.1371 | O103: 0.43 | P103: 8.13 | Q103: 8.25 | R103: Sim
A104: 1507805 | B104: Senador José Porfírio | C104: PA | D104: OK | E104: Mantido IBGE 2022 (IBGE 2010 a 0,4 km confirma; base independente a 195,9 km diverge) | F104: Divergência > 5 km entre fontes. | G104: -2.5915 | H104: -51.9548 | I104: -2.5915 | J104: -51.9548 | K104: -2.59485 | L104: -51.953056 | M104: -4.31242 | N104: -51.5764 | O104: 0.42 | P104: 195.91 | Q104: 195.51 | R104: Sim
A105: 2611002 | B105: Petrolândia | C105: PE | D105: OK | E105: Mantido IBGE 2022 (IBGE 2010 a 0,4 km confirma; base independente a 13,5 km diverge) | F105: Divergência > 5 km entre fontes. | G105: -8.9802 | H105: -38.2184 | I105: -8.9802 | J105: -38.2184 | K105: -8.977343 | L105: -38.220734 | M105: -9.06863 | N105: -38.3027 | O105: 0.41 | P105: 13.51 | Q105: 13.57 | R105: Sim
A106: 2607406 | B106: Itacuruba | C106: PE | D106: OK | E106: Mantido IBGE 2022 (IBGE 2010 a 0,4 km confirma; base independente a 10,6 km diverge) | F106: Divergência > 5 km entre fontes. | G106: -8.7275 | H106: -38.6849 | I106: -8.7275 | J106: -38.6849 | K106: -8.724515 | L106: -38.686342 | M106: -8.82231 | N106: -38.6975 | O106: 0.37 | P106: 10.63 | Q106: 10.94 | R106: Sim
A107: 2509206 | B107: Massaranduba | C107: PB | D107: OK | E107: Mantido IBGE 2022 (IBGE 2010 a 0,4 km confirma; base independente a 5,7 km diverge) | F107: Divergência > 5 km entre fontes. | G107: -7.1802 | H107: -35.7343 | I107: -7.1802 | J107: -35.7343 | K107: -7.180199 | L107: -35.737515 | M107: -7.18995 | N107: -35.7848 | O107: 0.35 | P107: 5.68 | Q107: 5.33 | R107: Sim
A108: 5205471 | B108: Chapadão do Céu | C108: GO | D108: OK | E108: Mantido IBGE 2022 (IBGE 2010 a 0,4 km confirma; base independente a 12,7 km diverge) | F108: Divergência > 5 km entre fontes. | G108: -18.3967 | H108: -52.669 | I108: -18.3967 | J108: -52.669 | K108: -18.394032 | L108: -52.670801 | M108: -18.4073 | N108: -52.549 | O108: 0.35 | P108: 12.72 | Q108: 12.94 | R108: Sim
A109: 5103858 | B109: Gaúcha do Norte | C109: MT | D109: OK | E109: Mantido IBGE 2022 (IBGE 2010 a 0,3 km confirma; base independente a 20,3 km diverge) | F109: Divergência > 5 km entre fontes. | G109: -13.1867 | H109: -53.2586 | I109: -13.1867 | J109: -53.2586 | K109: -13.188043 | L109: -53.261519 | M109: -13.2443 | N109: -53.0809 | O109: 0.35 | P109: 20.27 | Q109: 20.53 | R109: Sim
A110: 3527603 | B110: Luís Antônio | C110: SP | D110: OK | E110: Mantido IBGE 2022 (IBGE 2010 a 0,3 km confirma; base independente a 7,9 km diverge) | F110: Divergência > 5 km entre fontes. | G110: -21.5513 | H110: -47.7036 | I110: -21.5513 | J110: -47.7036 | K110: -21.551707 | L110: -47.70028 | M110: -21.55 | N110: -47.7801 | O110: 0.35 | P110: 7.91 | Q110: 8.26 | R110: Sim
A111: 2501906 | B111: Belém | C111: PB | D111: OK | E111: Mantido IBGE 2022 (IBGE 2010 a 0,3 km confirma; base independente a 5,6 km diverge) | F111: Divergência > 5 km entre fontes. | G111: -6.6966 | H111: -35.5378 | I111: -6.6966 | J111: -35.5378 | K111: -6.694043 | L111: -35.536274 | M111: -6.74261 | N111: -35.5166 | O111: 0.33 | P111: 5.63 | Q111: 5.82 | R111: Sim
A112: 5209150 | B112: Gouvelândia | C112: GO | D112: OK | E112: Mantido IBGE 2022 (IBGE 2010 a 0,3 km confirma; base independente a 21,2 km diverge) | F112: Divergência > 5 km entre fontes. | G112: -18.4409 | H112: -50.1369 | I112: -18.4409 | J112: -50.1369 | K112: -18.438279 | L112: -50.137999 | M112: -18.6238 | N112: -50.0805 | O112: 0.31 | P112: 21.19 | Q112: 21.5 | R112: Sim
A113: 1718881 | B113: Santa Maria do Tocantins | C113: TO | D113: OK | E113: Mantido IBGE 2022 (IBGE 2010 a 0,3 km confirma; base independente a 5,5 km diverge) | F113: Divergência > 5 km entre fontes. | G113: -8.7756 | H113: -47.748 | I113: -8.7756 | J113: -47.748 | K113: -8.774976 | L113: -47.74527 | M113: -8.8046 | N113: -47.7887 | O113: 0.31 | P113: 5.51 | Q113: 5.8 | R113: Sim
A114: 5100805 | B114: Apiacás | C114: MT | D114: OK | E114: Mantido IBGE 2022 (IBGE 2010 a 0,3 km confirma; base independente a 7,6 km diverge) | F114: Divergência > 5 km entre fontes. | G114: -9.5634 | H114: -57.3937 | I114: -9.5634 | J114: -57.3937 | K114: -9.565495 | L114: -57.395402 | M114: -9.53981 | N114: -57.4587 | O114: 0.3 | P114: 7.59 | Q114: 7.51 | R114: Sim
... A131: 2613107 | B131: São Caitano | C131: PE | D131: OK | E131: Mantido IBGE 2022 (IBGE 2010 a 0,0 km confirma; base independente a 16,5 km diverge) | F131: Divergência > 5 km entre fontes. | G131: -8.3273 | H131: -36.1373 | I131: -8.3273 | J131: -36.1373 | K131: -8.32736 | L131: -36.13736 | M131: -8.33763 | N131: -36.2869 | O131: 0.01 | P131: 16.5 | Q131: 16.49 | R131: Sim

Sheet Validacao
A1: Origem | B1: Grupo | C1: Verificação | D1: Esperado | E1: Obtido | F1: Resultado | G1: Crítica
A2: Pipeline Python | B2: Contagem | C2: Municípios na DTB 2025 | D2: 5571 | E2: 5571 | F2: OK | G2: Sim
A3: Pipeline Python | B3: Contagem | C3: Códigos de município únicos | D3: 5571 | E3: 5571 | F3: OK | G3: Sim
A4: Pipeline Python | B4: Contagem | C4: UFs | D4: 27 | E4: 27 | F4: OK | G4: Sim
A5: Pipeline Python | B5: Contagem | C5: Regiões Imediatas | D5: 510 | E5: 510 | F5: OK | G5: Sim
A6: Pipeline Python | B6: Contagem | C6: Regiões Intermediárias | D6: 133 | E6: 133 | F6: OK | G6: Sim
A7: Pipeline Python | B7: Hierarquia | C7: Código do município começa com o código da UF | D7: 0 | E7: 0 | F7: OK | G7: Sim
A8: Pipeline Python | B8: Hierarquia | C8: Código da Reg. Imediata começa com o código da UF | D8: 0 | E8: 0 | F8: OK | G8: Sim
A9: Pipeline Python | B9: Hierarquia | C9: Código da Reg. Intermediária começa com o código da UF | D9: 0 | E9: 0 | F9: OK | G9: Sim
A10: Pipeline Python | B10: Hierarquia | C10: Cada Reg. Imediata pertence a uma única Reg. Intermediária | D10: 0 | E10: 0 | F10: OK | G10: Sim
A11: Pipeline Python | B11: Hierarquia | C11: Grande Região (API) coerente com 1º dígito da UF | D11: 0 | E11: 0 | F11: OK | G11: Sim
A12: Pipeline Python | B12: Hierarquia | C12: Nome da UF (DTB) = nome da UF (API) | D12: 0 | E12: 0 | F12: OK | G12: Sim
A13: Pipeline Python | B13: Texto | C13: Nomes (DTB municípios) com espaços irregulares na fonte | D13: 0 | E13: 0 | F13: OK | G13: Sim
A14: Pipeline Python | B14: Hierarquia | C14: Códigos oficiais que não satisfazem o dígito verificador (exceções conhecidas do IBGE) | D14: informativo | E14: 9 | F14: OK | G14: Não
A15: Pipeline Python | B15: DTB x API | C15: Municípios só em uma das fontes | D15: 0 | E15: 0 | F15: OK | G15: Sim
A16: Pipeline Python | B16: DTB x API | C16: Nome do município divergente | D16: 0 | E16: 0 | F16: OK | G16: Sim
A17: Pipeline Python | B17: DTB x API | C17: UF divergente | D17: 0 | E17: 0 | F17: OK | G17: Sim
A18: Pipeline Python | B18: DTB x API | C18: Código Reg. Imediata divergente | D18: 0 | E18: 0 | F18: OK | G18: Sim
A19: Pipeline Python | B19: DTB x API | C19: Código Reg. Intermediária divergente | D19: 0 | E19: 0 | F19: OK | G19: Sim
A20: Pipeline Python | B20: DTB x API | C20: Nome Reg. Imediata divergente | D20: 0 | E20: 0 | F20: OK | G20: Sim
A21: Pipeline Python | B21: DTB x API | C21: Nome Reg. Intermediária divergente | D21: 0 | E21: 0 | F21: OK | G21: Sim
A22: Pipeline Python | B22: Hierarquia | C22: Capitais (26 estaduais + Brasília) | D22: 27 | E22: 27 | F22: OK | G22: Sim
A23: Pipeline Python | B23: DTB x API | C23: Capitais divergentes da flag da API | D23: 0 | E23: 0 | F23: OK | G23: Sim
A24: Pipeline Python | B24: Distritos | C24: Distritos na DTB 2025 | D24: 10751 | E24: 10751 | F24: OK | G24: Sim
A25: Pipeline Python | B25: Distritos | C25: Códigos de distrito únicos | D25: 10751 | E25: 10751 | F25: OK | G25: Sim
A26: Pipeline Python | B26: Distritos | C26: Código do distrito com 9 dígitos | D26: 0 | E26: 0 | F26: OK | G26: Sim
... A37: Pipeline Python | B37: Distritos | C37: Sedes IBGE 2010 (Cidade) no distrito de sufixo 05 (5.564 verificadas) | D37: 0 | E37: 0 | F37: OK | G37: Sim
A38: Pipeline Python | B38: Distritos | C38: Distrito-sede com nome diferente do município (verificar renomeações) | D38: informativo | E38: 2515401 São Vicente do Seridó/PB (sede 'Seridó'), 4322350 União da Serra/RS (sede 'São Luiz') | F38: OK | G38: Não
A39: Pipeline Python | B39: Coordenadas | C39: Municípios com ponto IBGE 2022 | D39: 5571 | E39: 5571 | F39: OK | G39: Sim
A40: Pipeline Python | B40: Coordenadas | C40: Extração 2022 B cobre todos os códigos da extração A | D40: 0 | E40: 0 | F40: OK | G40: Sim
A41: Pipeline Python | B41: Coordenadas | C41: Consistência de extração 2022 A x B: maior diferença (m) | D41: < 1 | E41: 0 | F41: OK | G41: Sim
A42: Pipeline Python | B42: Coordenadas | C42: Sedes 2022 x bases 2022 por município (778 sedes, GO/SC/AM/AP/PA/RR): maior diferença (m) | D42: < 20 | E42: 7.9 | F42: OK | G42: Sim
A43: Pipeline Python | B43: Coordenadas | C43: Municípios sem coordenada final | D43: 0 | E43: 0 | F43: OK | G43: Sim
A44: Pipeline Python | B44: Coordenadas | C44: Coordenadas fora da caixa envolvente do Brasil | D44: 0 | E44: 0 | F44: OK | G44: Sim
A45: Pipeline Python | B45: Coordenadas | C45: Sede fora do próprio polígono por mais de 1 km (Malha 2025) | D45: 0 | E45: 0 | F45: OK | G45: Não
A46: Pipeline Python | B46: Coordenadas | C46: Sede dentro do próprio polígono (estrito, malha simplificada) | D46: ≥ 99,5% | E46: 99,96% | F46: OK | G46: Não
A47: Pipeline Python | B47: Coordenadas | C47: Pontos IBGE 2022 substituídos pelo IBGE 2010 | D47: informativo | E47: 15 | F47: OK | G47: Não
A48: Pipeline Python | B48: Coordenadas | C48: Pontos IBGE 2022 mantidos a ≥ 3 km das duas referências (anotados) | D48: informativo | E48: 14 | F48: OK | G48: Não
A49: Pipeline Python | B49: Coordenadas | C49: Mediana da distância final x base independente (km) | D49: < 1 | E49: 0.606 | F49: OK | G49: Não
A50: Pipeline Python | B50: Malha | C50: Municípios com polígono na Malha 2025 | D50: 5571 | E50: 5571 | F50: OK | G50: Sim
A51: Pipeline Python | B51: Malha | C51: Ponto interno dentro do polígono | D51: 5571 | E51: 5571 | F51: OK | G51: Sim
A52: Pipeline Python | B52: Malha | C52: Centroide dentro do polígono (informativo: formas côncavas ficam fora) | D52: informativo | E52: 5519 | F52: OK | G52: Não
A53: Pipeline Python | B53: Distritos | C53: Distritos com coordenada de sede distrital | D53: informativo | E53: 10.256 de 10.751 (95,4%) | F53: OK | G53: Não
A54: Pipeline Python | B54: Distritos | C54: Coordenadas de distrito obtidas por localidade homônima | D54: informativo | E54: 147 | F54: OK | G54: Não
A55: Pipeline Python | B55: Distritos | C55: Coordenadas de distrito de localidade com outro nome (a conferir) | D55: informativo | E55: 10 | F55: OK | G55: Não
A56: Pipeline Python | B56: Dimensões | C56: Linhas em Regioes_Imediatas | D56: 510 | E56: 510 | F56: OK | G56: Sim
A57: Pipeline Python | B57: Dimensões | C57: Linhas em Regioes_Intermediarias | D57: 133 | E57: 133 | F57: OK | G57: Sim
A58: Pipeline Python | B58: Dimensões | C58: Linhas em UFs | D58: 27 | E58: 27 | F58: OK | G58: Sim
A59: Pipeline Python | B59: Tabelas | C59: Soma de 'Qtd. Distritos' = linhas da aba Distritos | D59: 10751 | E59: 10751 | F59: OK | G59: Sim
A60: Pipeline Python | B60: Tabelas | C60: Campos-chave vazios (aba Municipios) | D60: 0 | E60: 0 | F60: OK | G60: Sim
A61: Pipeline Python | B61: Tabelas | C61: Campos-chave vazios (aba Distritos) | D61: 0 | E61: 0 | F61: OK | G61: Sim
A62: Pipeline Python | B62: Texto | C62: Células de texto com caractere corrompido (U+00BF, U+FFFD) ou de controle | D62: 0 | E62: 0 | F62: OK | G62: Sim
A63: Fórmula Excel | B63: Excel | C63: Linhas na aba Municipios | D63: 5571 | E63: =COUNTA(Municipios!A2:A5572) -> 5571 | F63: =IF(E63=D63,"OK","FALHA") -> OK | G63: Sim
A64: Fórmula Excel | B64: Excel | C64: Linhas na aba Distritos | D64: 10751 | E64: =COUNTA(Distritos!A2:A10752) -> 10751 | F64: =IF(E64=D64,"OK","FALHA") -> OK | G64: Sim
A65: Fórmula Excel | B65: Excel | C65: Soma de Qtd. Distritos (aba Municipios) | D65: 10751 | E65: =SUM(Municipios!R2:R5572) -> 10751 | F65: =IF(E65=D65,"OK","FALHA") -> OK | G65: Sim
A66: Fórmula Excel | B66: Excel | C66: Regiões Imediatas | D66: 510 | E66: =COUNTA(Regioes_Imediatas!A2:A511) -> 510 | F66: =IF(E66=D66,"OK","FALHA") -> OK | G66: Sim
A67: Fórmula Excel | B67: Excel | C67: Regiões Intermediárias | D67: 133 | E67: =COUNTA(Regioes_Intermediarias!A2:A134) -> 133 | F67: =IF(E67=D67,"OK","FALHA") -> OK | G67: Sim
A68: Fórmula Excel | B68: Excel | C68: UFs | D68: 27 | E68: =COUNTA(UFs!A:A)-1 -> 27 | F68: =IF(E68=D68,"OK","FALHA") -> OK | G68: Sim
A69: Fórmula Excel | B69: Excel | C69: Municípios sem latitude | D69: 0 | E69: =COUNTBLANK(Municipios!M2:M5572) -> 0 | F69: =IF(E69=D69,"OK","FALHA") -> OK | G69: Sim
A70: Fórmula Excel | B70: Excel | C70: Municípios sem longitude | D70: 0 | E70: =COUNTBLANK(Municipios!N2:N5572) -> 0 | F70: =IF(E70=D70,"OK","FALHA") -> OK | G70: Sim
A71: Fórmula Excel | B71: Excel | C71: Latitude fora do Brasil (< -34 ou > 5,5) | D71: 0 | E71: =SUMPRODUCT(--(Municipios!M2:M5572<-34))+SUMPRODUCT(--(Municipios!M2:M5572>5.5)) -> 0 | F71: =IF(E71=D71,"OK","FALHA") -> OK | G71: Sim
A72: Fórmula Excel | B72: Excel | C72: Longitude fora do Brasil (< -74,2 ou > -28,5) | D72: 0 | E72: =SUMPRODUCT(--(Municipios!N2:N5572<-74.2))+SUMPRODUCT(--(Municipios!N2:N5572>-28.5)) -> 0 | F72: =IF(E72=D72,"OK","FALHA") -> OK | G72: Sim
A73: Fórmula Excel | B73: Excel | C73: Distrito-sede marcado 'Sim' | D73: 5570 | E73: =COUNTIF(Distritos!C2:C10752,"Sim") -> 5570 | F73: =IF(E73=D73,"OK","FALHA") -> OK | G73: Sim

Sheet Fontes
A1: Chave | B1: Produto | C1: Safra / Data-base | D1: Uso no pipeline | E1: Origem do arquivo usado | F1: Endereço oficial (IBGE) | G1: Arquivo | H1: SHA-256
A2: dtb_municipios | B2: IBGE — Divisão Territorial Brasileira (DTB) 2025 — Relatório de Municípios | C2: Data-base 31/12/2025 (divulgada pelo IBGE em 30/03/2026) | D2: PRIMÁRIA: código/nome do município, UF, Região Imediata e Intermediária | E2: Arquivo original do IBGE (DTB_2025.zip), espelhado em github.com/murilo-mg/rastro-de-territorio (referencias/ibge/dtb2025/original.ods) | F2: https://www.ibge.gov.br/geociencias/organizacao-do-territorio/estrutura-territorial/23701-divisao-territorial-brasileira.html | G2: dtb2025/RELATORIO_DTB_BRASIL_2025_MUNICIPIOS.ods | H2: a0606b9706c248138131511287e582a9293ba786096e0395192be36108d029fa
A3: dtb_distritos | B3: IBGE — DTB 2025 — Relatório de Distritos (RELATORIO_DTB_BRASIL_2025_DISTRITOS.xls convertido para CSV) | C3: Data-base 31/12/2025 | D3: PRIMÁRIA: código e nome dos 10.751 distritos | E3: github.com/norteiadev/norteia-brave @24a365ae (data/ibge/ibge_distritos.csv) | F3: https://www.ibge.gov.br/geociencias/organizacao-do-territorio/estrutura-territorial/23701-divisao-territorial-brasileira.html | G3: dtb2025/RELATORIO_DTB_BRASIL_2025_DISTRITOS.csv | H3: c96aa5680659ce6c2f434fe3e8ce855d24b1c3d32e60f140b693039c1b8c8ed8
A4: api_municipios | B4: IBGE — API de Localidades v1 (/localidades/municipios) — snapshot | C4: Capturado em 11/09/2026 | D4: CHECAGEM CRUZADA de municípios/regiões; sigla da UF e capital | E4: npm @br-geo-kit/ibge@1.0.0 (data/2026/tables) | F4: https://servicodados.ibge.gov.br/api/docs/localidades | G4: api_localidades/municipalities.json | H4: d79ca47b701dd62f1d4c20320457bd871bd7d1c856d722edeb6d8803e8e82c4f
A5: api_regioes | B5: IBGE — API de Localidades v1 (regiões imediatas/intermediárias) — snapshot | C5: Capturado em 11/09/2026 | D5: CHECAGEM CRUZADA dos nomes das regiões | E5: npm @br-geo-kit/ibge@1.0.0 | F5: https://servicodados.ibge.gov.br/api/docs/localidades | G5: api_localidades/regions.json | H5: 9ddb9d309519502701a1ecc1478d78067c2b9949a2a0387bca691cbd93ba5d83
A6: api_ufs | B6: IBGE — API de Localidades v1 (/localidades/estados) — snapshot | C6: Capturado em 11/09/2026 | D6: Sigla da UF, Grande Região e código da capital | E6: npm @br-geo-kit/ibge@1.0.0 | F6: https://servicodados.ibge.gov.br/api/docs/localidades | G6: api_localidades/states.json | H6: b8bd9cc4e0110bc609af5c026d04a7a0c16e8a7aa719fcb3b25edff75258015e
A7: api_distritos | B7: IBGE — API de Localidades v1 (/localidades/distritos) — snapshot | C7: Capturado em ~08/10/2026 | D7: CHECAGEM CRUZADA da lista de distritos (código a código, nome a nome) | E7: github.com/domjerse/duckdb @7a539c4d (uf_municipio.parquet) | F7: https://servicodados.ibge.gov.br/api/docs/localidades | G7: api_localidades/distritos_api_ibge_2026-10.parquet | H7: b81db8ee4ce3239016a1a319f0e2e5c7ebb5a63553aaa7fbba29e8d8b36e2597
A8: sedes_2022_a | B8: IBGE — Localidades do Brasil 2022 (Censo 2022) — pontos 'Sede Municipal'/'Capital' | C8: Base Censo 2022 (arquivo IBGE publicado em nov/2025) | D8: PRIMÁRIA: latitude/longitude da sede municipal | E8: github.com/luandarod/luandarodrigues @4b5a148d (projects/ubs-healthcare-mapping/data/reference/ibge_municipal_seats_2022.csv) | F8: https://geoftp.ibge.gov.br/organizacao_do_territorio/estrutura_territorial/localidades/Localidades_do_Brasil/2022/Localidades_Brasil_shp.zip | G8: localidades_2022/sedes_municipais_2022_A.csv | H8: a79c1f74ed94fa34edc340cb930856b7e46005fae7972da1538540e198357bd7
A9: sedes_2022_b | B9: IBGE — Localidades do Brasil 2022 — sedes municipais (extração independente, por UF) | C9: Base Censo 2022 | D9: CHECAGEM CRUZADA da extração A (consistência de extração) | E9: github.com/brasil-em-camadas/brasil-em-camadas.github.io @2e9cbdbd (scripts/dados/sedes_municipais.csv) | F9: https://geoftp.ibge.gov.br/organizacao_do_territorio/estrutura_territorial/localidades/Localidades_do_Brasil/2022/Localidades_UFs_shp.zip | G9: localidades_2022/sedes_municipais_2022_B.csv | H9: fd9859f8efe201213ddb4aed4aca32c2f76f1d73276b2c58dbc17cf30e5f5f13
A10: loc_2022_go | B10: IBGE — Localidades do Brasil 2022 — KML por município (GO), todas as categorias | C10: Base Censo 2022 | D10: Sede distrital ('Vila') e checagem independente das sedes municipais (GO) | E10: github.com/johnerick-py/map_select @69477491 (goias_kml/) | F10: https://geoftp.ibge.gov.br/organizacao_do_territorio/estrutura_territorial/localidades/ | G10: localidades_2022/vilas/GO | H10: 3b3ef193f3c5699e38299f21be19c864e394fa2a1738b5526a808528ad3eddf9
A11: loc_2022_sc | B11: IBGE — Localidades do Brasil 2022 — KML por município (SC), todas as categorias | C11: Base Censo 2022 | D11: Sede distrital ('Vila') e checagem independente das sedes municipais (SC) | E11: github.com/FelipeFDN/Projeto-ML-Seguranca @f5501208 (data/IBGE/SC/) | F11: https://geoftp.ibge.gov.br/organizacao_do_territorio/estrutura_territorial/localidades/ | G11: localidades_2022/vilas/SC | H11: 2d1a8a2cef879f91a42d00b77ea060ecd07e11eef5c58c449c6266b125322087
A12: loc_2022_norte | B12: IBGE — Localidades do Brasil 2022 — GeoJSON (AM, AP, PA, RR), todas as categorias | C12: Base Censo 2022 | D12: Sede distrital ('Vila') e checagem independente das sedes municipais (AM, AP, PA, RR) | E12: github.com/Charles-Igeotecnologia/infovias @d9f9e88d (localidades_por_uf/) | F12: https://geoftp.ibge.gov.br/organizacao_do_territorio/estrutura_territorial/localidades/ | G12: localidades_2022/vilas/AM_AP_PA_RR | H12: 145f5fd6b6916cde9d9b31c9b613f46ab7be9f1e16b23a8a42cd997e94ccacc0
... A15: kelvins | B15: Base comunitária kelvins/municipios-brasileiros (NÃO oficial; fonte das coordenadas não documentada) | C15: Commit 503e2f70 (10/12/2025) | D15: SOMENTE CHECAGEM CRUZADA independente (nunca usada como valor final) | E15: github.com/kelvins/municipios-brasileiros (csv/municipios.csv) | F15: - | G15: referencia_independente/kelvins_municipios.csv | H15: 22bd03d004361329f69ddfa3f6c99cd53012aa53972a172e10b141288ad0b1fe
